Workbook
Name AA: #REF!
Name JD: #REF!
Name 一般贸易: #REF!
Name addresses: #REF!
Name AA: #REF!
Name 一般贸易: #REF!
Name AA: #REF!
Name 一般贸易: #REF!
Name AA: #REF!
Name 一般贸易: #REF!
Name AA: #REF!
Name 一般贸易: #REF!
Name AA: #REF!
Name 一般贸易: #REF!
Name AA: #REF!
Name 一般贸易: #REF!

Sheet 已到ARRIVED
A1: 序号 serial number | B1: 中国HSCODE（China） | C1: 印尼HS CODE (Indonesia) | D1: 货号 Item No. | E1: 产品中文名称 Chinese name of the product | F1: 产品英文名称 English name of the product | G1: 规格 specification | H1: 用量 dosage | I1: 单位 Unit | J1: 需求数量 Quantity | K1: 产品数量Product quantity | L1: 单位 Unit | M1: 供应商 Supplier | N1: 采购单日期 Date of purchase order | O1: 采购单号 PO No. | P1: 采购单价 Purchase price | Q1: 采购金额Purchase Amount | R1: 采购总额 Total Amount | S1: 单个毛重 Gross weight（KGM） | T1: 毛重总重 Total Gross weight（KGM） | U1: 单个净重 Net weight（KGM） | V1: 净重总重Total Net weight（KGM） | W1: 卡板号 Pallet No. | X1: 箱号 Carton No. | Y1: 箱数 Carton No. | Z1: 每箱数量Qty/Per carton | AA1: 长 Length | AB1: 宽 Width | AC1: 高 Height | AD1: 立方数/每箱CBM/Per carton | AE1: 总立方数Total CBM | AF1: 图片 Picture | AG1: 产品用途 product use | AH1: 合同号码 Contract No. | AI1: 合同日期 Date of contract | AJ1: 发票号 Invoice No. | AK1: 发票日期 Date of Invoice | AL1: 发票单价 Unit price on invoice | AM1: 金额 Invoice amount | AN1: 发票合计金额Invoice total amount | AO1: 产品数量Product quantity | AP1: 单位 Unit | AQ1: 柜号 Container No. | AR1: 走柜日期 Shipping date | AS1: 提单号 Bl No. | AT1: 预计到港日期 ETA PORT | AU1: 实际到厂日期 Actual arrival date | AV1: Container Size | AW1: Vessel Name/Voyage No. | AX1: 总集装箱运费金额（中国运费） Total Container Freight Amount (China's Freight) | AY1: 货运代理运输费用 Forwarder Transportation Costs (Indonesia Freight) | AZ1: Actual freight for product
A2: 1 | B2: 3923900000 | C2: 392390 | E2: 塑胶件-折叠筐 | F2: folding basket | I2: PCE | J2: 4400 | K2: 4400 | L2: pcs | M2: BRIGHT STAR (HK)INDUSTRY/LIMITED | P2: 56 | Q2: 246400 | R2: 246400 | T2: 10620 | V2: 10296 | W2: 1-22 | X2: 1-22 | Y2: 22 | Z2: 200 | AA2: 119 | AB2: 99 | AC2: 243 | AD2: 2.8610896 | AE2: 62.94 | AF2: =_xlfn.DISPIMG("ID_6B6B16C4FA4B4B8B89694FFDC87BFBE3",1) -> =DISPIMG("ID_6B6B16C4FA4B4B8B89694FFDC87BFBE3",1) | AH2: RPRRI00139 | AI2: 45996 | AJ2: PR202400139 | AK2: 45996 | AL2: 56 | AM2: 246400 | AN2: 246400 | AO2: 4400 | AP2: pcs | AQ2: WHSU6160759 | AR2: 45659 | AS2: 030F500038 | AT2: 45674 | AU2: 45677 | AV2: 40HQ | AW2: WAN HAI 371/S011 | AX2: 16188 | AZ2: ¥212,872.84
Q3: 246400 | R3: 246400 | T3: 10620 | V3: 10296 | Y3: 22 | AE3: 62.94 | AM3: 246400 | AN3: 246400
R5: 总合计 | T5: 10620 | V5: 10296 | Y5: 22 | AE5: 62.94 | AM5: 246400 | AN5: 246400
A6: 1 | B6: 3923900000 | C6: 392390 | E6: 塑胶件-折叠筐 | F6: folding basket | I6: PCE | J6: 4400 | K6: 4400 | L6: pcs | M6: BRIGHT STAR (HK)INDUSTRY/LIMITED | P6: 56 | Q6: 246400 | R6: 246400 | T6: 10560 | V6: 10296 | W6: 1-22 | X6: 1-22 | Y6: 22 | Z6: 200 | AA6: 119 | AB6: 99 | AC6: 243 | AD6: 2.8610896 | AE6: 62.94 | AF6: =_xlfn.DISPIMG("ID_6B6B16C4FA4B4B8B89694FFDC87BFBE3",1) -> =DISPIMG("ID_6B6B16C4FA4B4B8B89694FFDC87BFBE3",1) | AH6: RPRRI00140 | AI6: 45631 | AJ6: PR202400140 | AK6: 45631 | AL6: 56 | AM6: 246400 | AN6: 246400 | AO6: 4400 | AP6: pcs | AQ6: WHSU5417230 | AR6: 45660 | AS6: 030F500039 | AT6: 45674 | AU6: 45677 | AV6: 40HQ | AW6: WAN HAI 371/S011 | AX6: 16188 | AZ6: ¥212,872.84
Q7: 246400 | R7: 246400 | T7: 10560 | V7: 10296 | Y7: 22 | AE7: 62.94 | AM7: 246400 | AN7: 246400
R9: 总合计 | T9: 10560 | V9: 10296 | Y9: 22 | AE9: 62.94 | AM9: 246400 | AN9: 246400
A10: 1 | B10: 8480790090 | C10: 848079 | D10: J00002-Jack Lantern-南瓜灯 | E10: 工具灯IC板打螺丝底模 | F10: Tool light IC board screw bottom die | I10: PCE | J10: 4 | K10: 4 | L10: pcs | M10: 河源市源城区新汇丰机械模具加工部 | P10: 120 | Q10: 480 | R10: 26320 | T10: 0.97 | V10: 0.91 | W10: 2 | X10: 序号1 | Y10: 1 | Z10: 4 | AD10: 0 | AE10: 0.1 | AF10: =_xlfn.DISPIMG("ID_8FE94ACA647642CD956D85F203645F70",1) -> =DISPIMG("ID_8FE94ACA647642CD956D85F203645F70",1) | AH10: RPRRI00146 | AI10: 45631 | AJ10: PR202400146 | AK10: 45631 | AL10: 120 | AM10: 480 | AN10: 13830 | AO10: 4 | AP10: pcs | AQ10: WHSU2789070 | AR10: 45660 | AS10: 030F500175 | AT10: 45674 | AU10: 45677 | AV10: 20FT | AW10: WAN HAI 371/S011 | AX10: ¥9,738.00 | AZ10: ¥351,329.77
A11: 2 | B11: 8480790090 | C11: 848079 | D11: J00002-Jack Lantern-南瓜灯 | E11: 工具灯压电池片上下模 | F11: The tool light presses the upper and lower die of the battery | I11: PCE | J11: 2 | K11: 2 | L11: pcs | P11: 700 | Q11: 1400 | T11: 3.36 | V11: 3.3 | Z11: 2 | AF11: =_xlfn.DISPIMG("ID_F0EA65887D414FBD88E7003B0A02AFF3",1) -> =DISPIMG("ID_F0EA65887D414FBD88E7003B0A02AFF3",1) | AL11: 700 | AM11: 1400 | AO11: 2 | AP11: pcs | AQ11: WHSU2789070 | AR11: 45660 | AS11: 030F500175 | AT11: 45674 | AU11: 45677 | AV11: 20FT | AW11: WAN HAI 371/S011
A12: 3 | B12: 9405990000 | C12: 940599 | D12: J00002-Jack Lantern-南瓜灯 | E12: 假电池 | F12: Dummy cell | I12: PCE | J12: 2 | K12: 2 | L12: pcs | P12: 110 | Q12: 220 | T12: 1.32 | V12: 1.26 | Z12: 2 | AF12: =_xlfn.DISPIMG("ID_C2634432D5F8470D94EBC8DCEA3AC690",1) -> =DISPIMG("ID_C2634432D5F8470D94EBC8DCEA3AC690",1) | AL12: 110 | AM12: 220 | AO12: 2 | AP12: pcs | AQ12: WHSU2789070 | AR12: 45660 | AS12: 030F500175 | AT12: 45674 | AU12: 45677 | AV12: 20FT | AW12: WAN HAI 371/S011
A13: 4 | B13: 8480790090 | C13: 848079 | D13: J00002-Jack Lantern-南瓜灯 | E13: 南瓜锥超声上模 | F13: Ultrasonic molding of pumpkin cone | I13: PCE | J13: 2 | K13: 2 | L13: pcs | P13: 500 | Q13: 1000 | T13: 1.86 | V13: 1.8 | Z13: 2 | AF13: =_xlfn.DISPIMG("ID_CF02C89252324C018514166078A94805",1) -> =DISPIMG("ID_CF02C89252324C018514166078A94805",1) | AL13: 500 | AM13: 1000 | AO13: 2 | AP13: pcs | AQ13: WHSU2789070 | AR13: 45660 | AS13: 030F500175 | AT13: 45674 | AU13: 45677 | AV13: 20FT | AW13: WAN HAI 371/S011
A14: 5 | B14: 8480790090 | C14: 848079 | D14: J00002-Jack Lantern-南瓜灯 | E14: 南瓜锥超声下模 | F14: Pumpkin cone ultrasonic mold | I14: PCE | J14: 2 | K14: 2 | L14: pcs | P14: 500 | Q14: 1000 | T14: 0.76 | V14: 0.7 | Z14: 2 | AF14: =_xlfn.DISPIMG("ID_745DB565B82B4711AA974B3E3591D4E1",1) -> =DISPIMG("ID_745DB565B82B4711AA974B3E3591D4E1",1) | AL14: 500 | AM14: 1000 | AO14: 2 | AP14: pcs | AQ14: WHSU2789070 | AR14: 45660 | AS14: 030F500175 | AT14: 45674 | AU14: 45677 | AV14: 20FT | AW14: WAN HAI 371/S011
A15: 6 | B15: 8480790090 | C15: 848079 | D15: J00025-Color Changing Pumpkin Light-变色南瓜灯 | E15: 压电池片上下模 | F15: Press the upper and lower die of the battery | I15: PCE | J15: 2 | K15: 2 | L15: pcs | P15: 475 | Q15: 950 | T15: 2.56 | V15: 2.5 | Z15: 2 | AF15: =_xlfn.DISPIMG("ID_32A27F73F46047C8969CD2866D9955D3",1) -> =DISPIMG("ID_32A27F73F46047C8969CD2866D9955D3",1) | AL15: 475 | AM15: 950 | AO15: 2 | AP15: pcs | AQ15: WHSU2789070 | AR15: 45660 | AS15: 030F500175 | AT15: 45674 | AU15: 45677 | AV15: 20FT | AW15: WAN HAI 371/S011
A16: 7 | B16: 8480790090 | C16: 848079 | D16: J00025-Color Changing Pumpkin Light-变色南瓜灯 | E16: 三档开关烫胶固定底模 | F16: Three speed switch hot glue fixed bottom die | I16: PCE | J16: 1 | K16: 1 | L16: pcs | P16: 160 | Q16: 160 | T16: 0.5 | V16: 0.44 | Z16: 1 | AF16: =_xlfn.DISPIMG("ID_0B5834FE48B24586813C530B349AC09B",1) -> =DISPIMG("ID_0B5834FE48B24586813C530B349AC09B",1) | AL16: 160 | AM16: 160 | AO16: 1 | AP16: pcs | AQ16: WHSU2789070 | AR16: 45660 | AS16: 030F500175 | AT16: 45674 | AU16: 45677 | AV16: 20FT | AW16: WAN HAI 371/S011
A17: 8 | B17: 8480790090 | C17: 848079 | D17: J00025-Color Changing Pumpkin Light-变色南瓜灯 | E17: 南瓜灯打螺丝底模 | F17: Jack-o '-lantern screw bottom mold | I17: PCE | J17: 6 | K17: 6 | L17: pcs | P17: 160 | Q17: 960 | T17: 2.22 | V17: 2.16 | Z17: 6 | AF17: =_xlfn.DISPIMG("ID_AA5B34CBC225478795798F5B047E221C",1) -> =DISPIMG("ID_AA5B34CBC225478795798F5B047E221C",1) | AL17: 160 | AM17: 960 | AO17: 6 | AP17: pcs | AQ17: WHSU2789070 | AR17: 45660 | AS17: 030F500175 | AT17: 45674 | AU17: 45677 | AV17: 20FT | AW17: WAN HAI 371/S011
A18: 9 | B18: 8480790090 | C18: 848079 | D18: J00025-Color Changing Pumpkin Light-变色南瓜灯 | E18: 电池盖打螺丝底模 | F18: Screw the bottom mold of the battery cover | I18: PCE | J18: 1 | K18: 1 | L18: pcs | P18: 160 | Q18: 160 | T18: 0.44 | V18: 0.38 | Z18: 1 | AF18: =_xlfn.DISPIMG("ID_FB614F5E6C6C4DA695E98E76D90969E3",1) -> =DISPIMG("ID_FB614F5E6C6C4DA695E98E76D90969E3",1) | AL18: 160 | AM18: 160 | AO18: 1 | AP18: pcs | AQ18: WHSU2789070 | AR18: 45660 | AS18: 030F500175 | AT18: 45674 | AU18: 45677 | AV18: 20FT | AW18: WAN HAI 371/S011
A19: 10 | B19: 9405990000 | C19: 940599 | D19: J00025-Color Changing Pumpkin Light-变色南瓜灯 | E19: 假电池 | F19: Dummy cell | I19: PCE | J19: 3 | K19: 3 | L19: pcs | P19: 130 | Q19: 390 | T19: 1.68 | V19: 1.62 | Z19: 3 | AF19: =_xlfn.DISPIMG("ID_2F549D4391284DE89FA5AF61D8FFBEBE",1) -> =DISPIMG("ID_2F549D4391284DE89FA5AF61D8FFBEBE",1) | AL19: 130 | AM19: 390 | AO19: 3 | AP19: pcs | AQ19: WHSU2789070 | AR19: 45660 | AS19: 030F500175 | AT19: 45674 | AU19: 45677 | AV19: 20FT | AW19: WAN HAI 371/S011
A20: 11 | B20: 8480790090 | C20: 848079 | D20: J00012-Little Pumpkin Lamp-小南瓜灯 | E20: 压电池片上下模 | F20: Press the upper and lower die of the battery | I20: PCE | J20: 2 | K20: 2 | L20: pcs | P20: 525 | Q20: 1050 | T20: 1.96 | V20: 1.9 | Z20: 2 | AF20: =_xlfn.DISPIMG("ID_874FB425E2B142E5831E2C22D2A0C7DB",1) -> =DISPIMG("ID_874FB425E2B142E5831E2C22D2A0C7DB",1) | AL20: 525 | AM20: 1050 | AO20: 2 | AP20: pcs | AQ20: WHSU2789070 | AR20: 45660 | AS20: 030F500175 | AT20: 45674 | AU20: 45677 | AV20: 20FT | AW20: WAN HAI 371/S011
A21: 12 | B21: 8480790090 | C21: 848079 | D21: J00012-Little Pumpkin Lamp-小南瓜灯 | E21: 打螺丝底模 | F21: Screw the bottom die | I21: PCE | J21: 6 | K21: 6 | L21: pcs | P21: 300 | Q21: 1800 | T21: 3.54 | V21: 3.48 | Z21: 6 | AF21: =_xlfn.DISPIMG("ID_AC2CE519F2DA48B8BE1152F4470C1397",1) -> =DISPIMG("ID_AC2CE519F2DA48B8BE1152F4470C1397",1) | AL21: 300 | AM21: 1800 | AO21: 6 | AP21: pcs | AQ21: WHSU2789070 | AR21: 45660 | AS21: 030F500175 | AT21: 45674 | AU21: 45677 | AV21: 20FT | AW21: WAN HAI 371/S011
A22: 13 | B22: 8480790090 | C22: 848079 | D22: J00012-Little Pumpkin Lamp-小南瓜灯 | E22: 电池盖打螺丝底模 | F22: Screw the bottom mold of the battery cover | I22: PCE | J22: 1 | K22: 2 | L22: pcs | P22: 160 | Q22: 160 | T22: 0.32 | V22: 0.26 | Z22: 2 | AF22: =_xlfn.DISPIMG("ID_5DF9D5C8671B44538AC5D5471D0F5F4F",1) -> =DISPIMG("ID_5DF9D5C8671B44538AC5D5471D0F5F4F",1) | AL22: 160 | AM22: 160 | AO22: 2 | AP22: pcs | AQ22: WHSU2789070 | AR22: 45660 | AS22: 030F500175 | AT22: 45674 | AU22: 45677 | AV22: 20FT | AW22: WAN HAI 371/S011
A23: 14 | B23: 9405990000 | C23: 940599 | D23: J00012-Little Pumpkin Lamp-小南瓜灯 | E23: 假电池 | F23: Dummy cell | I23: PCE | J23: 3 | K23: 3 | L23: pcs | P23: 130 | Q23: 390 | T23: 1.47 | V23: 1.41 | Z23: 3 | AF23: =_xlfn.DISPIMG("ID_E36A17B71E7E4BC687D67895DFDC1011",1) -> =DISPIMG("ID_E36A17B71E7E4BC687D67895DFDC1011",1) | AL23: 130 | AM23: 390 | AO23: 3 | AP23: pcs | AQ23: WHSU2789070 | AR23: 45660 | AS23: 030F500175 | AT23: 45674 | AU23: 45677 | AV23: 20FT | AW23: WAN HAI 371/S011
A24: 15 | B24: 8480790090 | C24: 848079 | D24: W83669-Lighting Ground Plug Arm-亮灯地插手臂 | E24: 手臂L件啤钉轴 | F24: Arm L piece pin shaft | I24: PCE | J24: 1 | K24: 1 | L24: pcs | P24: 460 | Q24: 460 | T24: 0.83 | V24: 0.77 | Z24: 1 | AF24: =_xlfn.DISPIMG("ID_CB076EEA3F11448FB6EFD66B270BAB7C",1) -> =DISPIMG("ID_CB076EEA3F11448FB6EFD66B270BAB7C",1) | AL24: 460 | AM24: 460 | AO24: 1 | AP24: pcs | AQ24: WHSU2789070 | AR24: 45660 | AS24: 030F500175 | AT24: 45674 | AU24: 45677 | AV24: 20FT | AW24: WAN HAI 371/S011
A25: 16 | B25: 8480790090 | C25: 848079 | D25: W83669-Lighting Ground Plug Arm-亮灯地插手臂 | E25: 手臂R件啤钉轴 | F25: Arm R piece stud shaft | I25: PCE | J25: 2 | K25: 2 | L25: pcs | P25: 460 | Q25: 920 | T25: 1.6 | V25: 1.54 | Z25: 2 | AF25: =_xlfn.DISPIMG("ID_2612B1D56C7A4C79A70B63CC3389FE42",1) -> =DISPIMG("ID_2612B1D56C7A4C79A70B63CC3389FE42",1) | AL25: 460 | AM25: 920 | AO25: 2 | AP25: pcs | AQ25: WHSU2789070 | AR25: 45660 | AS25: 030F500175 | AT25: 45674 | AU25: 45677 | AV25: 20FT | AW25: WAN HAI 371/S011
A26: 17 | B26: 8480790090 | C26: 848079 | D26: W83669-Lighting Ground Plug Arm-亮灯地插手臂 | E26: L件打螺丝底模 | F26: L part screw bottom die | I26: PCE | J26: 2 | K26: 2 | L26: pcs | P26: 300 | Q26: 600 | T26: 2.46 | V26: 2.4 | Z26: 2 | AF26: =_xlfn.DISPIMG("ID_BCE0AF53F03A4CDBB66CC875E432543D",1) -> =DISPIMG("ID_BCE0AF53F03A4CDBB66CC875E432543D",1) | AL26: 300 | AM26: 600 | AO26: 2 | AP26: pcs | AQ26: WHSU2789070 | AR26: 45660 | AS26: 030F500175 | AT26: 45674 | AU26: 45677 | AV26: 20FT | AW26: WAN HAI 371/S011
A27: 18 | B27: 8480790090 | C27: 848079 | D27: W83669-Lighting Ground Plug Arm-亮灯地插手臂 | E27: R件打螺丝底模 | F27: Screw bottom die for R pieces | I27: PCE | J27: 4 | K27: 4 | L27: pcs | P27: 320 | Q27: 1280 | T27: 3.66 | V27: 3.6 | Z27: 4 | AF27: =_xlfn.DISPIMG("ID_5B37FD293022479AB7094F4A3BAF3335",1) -> =DISPIMG("ID_5B37FD293022479AB7094F4A3BAF3335",1) | AL27: 320 | AM27: 1280 | AO27: 4 | AP27: pcs | AQ27: WHSU2789070 | AR27: 45660 | AS27: 030F500175 | AT27: 45674 | AU27: 45677 | AV27: 20FT | AW27: WAN HAI 371/S011
A28: 19 | B28: 9405990000 | C28: 940599 | D28: W83669-Lighting Ground Plug Arm-亮灯地插手臂 | E28: 假电池 | F28: Dummy cell | I28: PCE | J28: 3 | K28: 3 | L28: pcs | P28: 150 | Q28: 450 | T28: 9.66 | V28: 9.6 | Z28: 3 | AF28: =_xlfn.DISPIMG("ID_AE927983D05D414FA7ECC092712BE40B",1) -> =DISPIMG("ID_AE927983D05D414FA7ECC092712BE40B",1) | AL28: 150 | AM28: 450 | AO28: 3 | AP28: pcs | AQ28: WHSU2789070 | AR28: 45660 | AS28: 030F500175 | AT28: 45674 | AU28: 45677 | AV28: 20FT | AW28: WAN HAI 371/S011
A29: 20 | B29: 8480790090 | C29: 848079 | D29: J00038-Remote Control Light-遥控灯 | E29: 压电池片上下模 | F29: Press the upper and lower die of the battery | I29: PCE | J29: 2 | K29: 2 | L29: pcs | P29: 700 | Q29: 1400 | T29: 3.36 | V29: 3.3 | Z29: 2 | AF29: =_xlfn.DISPIMG("ID_A60754604D9845D092C090C02088DE3B",1) -> =DISPIMG("ID_A60754604D9845D092C090C02088DE3B",1) | AH29: RPRRI00147 | AI29: 45631 | AJ29: PR202400147 | AK29: 45631 | AL29: 700 | AM29: 1400 | AN29: 12490 | AO29: 2 | AP29: pcs | AQ29: WHSU2789070 | AR29: 45660 | AS29: 030F500175 | AT29: 45674 | AU29: 45677 | AV29: 20FT | AW29: WAN HAI 371/S011
A30: 21 | B30: 8480790090 | C30: 848079 | D30: J00038-Remote Control Light-遥控灯 | E30: 电池盖打螺丝底模 | F30: Screw the bottom mold of the battery cover | I30: PCE | J30: 1 | K30: 1 | L30: pcs | P30: 160 | Q30: 160 | T30: 0.43 | V30: 0.37 | Z30: 1 | AF30: =_xlfn.DISPIMG("ID_A8DE022D494E4CA58B27116046E35C5C",1) -> =DISPIMG("ID_A8DE022D494E4CA58B27116046E35C5C",1) | AL30: 160 | AM30: 160 | AO30: 1 | AP30: pcs | AQ30: WHSU2789070 | AR30: 45660 | AS30: 030F500175 | AT30: 45674 | AU30: 45677 | AV30: 20FT | AW30: WAN HAI 371/S011
A31: 22 | B31: 8480790090 | C31: 848079 | D31: J00038-Remote Control Light-遥控灯 | E31: 打螺丝底模 | F31: Screw the bottom die | I31: PCE | J31: 6 | K31: 6 | L31: pcs | P31: 260 | Q31: 1560 | T31: 1.86 | V31: 1.8 | Z31: 6 | AF31: =_xlfn.DISPIMG("ID_842636CCA3A9420F97B9D38FAB5398E4",1) -> =DISPIMG("ID_842636CCA3A9420F97B9D38FAB5398E4",1) | AL31: 260 | AM31: 1560 | AO31: 6 | AP31: pcs | AQ31: WHSU2789070 | AR31: 45660 | AS31: 030F500175 | AT31: 45674 | AU31: 45677 | AV31: 20FT | AW31: WAN HAI 371/S011
A32: 23 | B32: 9405990000 | C32: 940599 | D32: J00038-Remote Control Light-遥控灯 | E32: 假电池 | F32: Dummy cell | I32: PCE | J32: 3 | K32: 3 | L32: pcs | P32: 140 | Q32: 420 | T32: 1.94 | V32: 1.89 | Z32: 3 | AF32: =_xlfn.DISPIMG("ID_82D82D5E0FF14328BD66F7157A7977B9",1) -> =DISPIMG("ID_82D82D5E0FF14328BD66F7157A7977B9",1) | AL32: 140 | AM32: 420 | AO32: 3 | AP32: pcs | AQ32: WHSU2789070 | AR32: 45660 | AS32: 030F500175 | AT32: 45674 | AU32: 45677 | AV32: 20FT | AW32: WAN HAI 371/S011
A33: 24 | B33: 8480790090 | C33: 848079 | D33: J00002-Jack Lantern-南瓜灯 | E33: 吸塑模 | F33: Blister die | I33: PCE | J33: 4 | K33: 4 | L33: pcs | P33: 380 | Q33: 1520 | T33: 3.47 | V33: 3.12 | X33: 序号2 | Y33: 1 | Z33: 4 | AD33: 0 | AE33: 0.05 | AF33: =_xlfn.DISPIMG("ID_353C71C1CBCF4AAB91E96F2A91B2086B",1) -> =DISPIMG("ID_353C71C1CBCF4AAB91E96F2A91B2086B",1) | AL33: 380 | AM33: 1520 | AO33: 4 | AP33: pcs | AQ33: WHSU2789070 | AR33: 45660 | AS33: 030F500175 | AT33: 45674 | AU33: 45677 | AV33: 20FT | AW33: WAN HAI 371/S011
A34: 25 | B34: 8516800000 | C34: 851680 | D34: J00002-Jack Lantern-南瓜灯 | E34: 发热片 | F34: Heating sheet | I34: PCE | J34: 20 | K34: 20 | L34: pcs | P34: 25 | Q34: 500 | T34: 0.47 | V34: 0.12 | Z34: 20 | AF34: =_xlfn.DISPIMG("ID_99402CBAEFA74B30B46EAADD916293AC",1) -> =DISPIMG("ID_99402CBAEFA74B30B46EAADD916293AC",1) | AL34: 25 | AM34: 500 | AO34: 20 | AP34: pcs | AQ34: WHSU2789070 | AR34: 45660 | AS34: 030F500175 | AT34: 45674 | AU34: 45677 | AV34: 20FT | AW34: WAN HAI 371/S011
A35: 26 | B35: 8480790090 | C35: 848079 | D35: J00002-Jack Lantern-南瓜灯 | E35: 吸塑模 | F35: Blister die | I35: PCE | J35: 6 | K35: 6 | L35: pcs | P35: 380 | Q35: 2280 | T35: 6.35 | V35: 6 | Z35: 6 | AF35: =_xlfn.DISPIMG("ID_9DB3E0628C6C482E97694BE6D94B66A2",1) -> =DISPIMG("ID_9DB3E0628C6C482E97694BE6D94B66A2",1) | AL35: 380 | AM35: 2280 | AO35: 6 | AP35: pcs | AQ35: WHSU2789070 | AR35: 45660 | AS35: 030F500175 | AT35: 45674 | AU35: 45677 | AV35: 20FT | AW35: WAN HAI 371/S011
A36: 27 | B36: 8516800000 | C36: 851680 | D36: J00002-Jack Lantern-南瓜灯 | E36: 发热片 | F36: Heating sheet | I36: PCE | J36: 30 | K36: 30 | L36: pcs | P36: 35 | Q36: 1050 | T36: 0.61 | V36: 0.26 | Z36: 30 | AF36: =_xlfn.DISPIMG("ID_6F35E7324FE241CF9740B1F58C1901C3",1) -> =DISPIMG("ID_6F35E7324FE241CF9740B1F58C1901C3",1) | AL36: 35 | AM36: 1050 | AO36: 30 | AP36: pcs | AQ36: WHSU2789070 | AR36: 45660 | AS36: 030F500175 | AT36: 45674 | AU36: 45677 | AV36: 20FT | AW36: WAN HAI 371/S011
A37: 28 | B37: 8480790090 | C37: 848079 | D37: J00035-Tools Series-工具系列 | E37: 彩钉切水口上下模 | F37: Color nail cut water top and bottom die | I37: PCE | J37: 2 | K37: 2 | L37: pcs | P37: 1800 | Q37: 3600 | T37: 4.9 | V37: 4 | X37: 序号3 | Y37: 1 | Z37: 2 | AD37: 0 | AE37: 0.04 | AF37: =_xlfn.DISPIMG("ID_C553DC26AFCF43389914D771C3A2228C",1) -> =DISPIMG("ID_C553DC26AFCF43389914D771C3A2228C",1) | AL37: 1800 | AM37: 3600 | AO37: 2 | AP37: pcs | AQ37: WHSU2789070 | AR37: 45660 | AS37: 030F500175 | AT37: 45674 | AU37: 45677 | AV37: 20FT | AW37: WAN HAI 371/S011
J38: 123 | Q38: 26320 | R38: 26320 | T38: 64.56 | V38: 60.89 | Y38: 3 | AE38: 0.19 | AM38: 26320 | AN38: 26320
A39: 29 | B39: 7326909000 | C39: 731829 | D39: J00016-Ladle Set-大勺套装 | E39: 2.5x5.5光轴 | F39: 2.5x5.5 optical axis | I39: KGM | J39: 8 | K39: 40000 | L39: PCE | M39: 河源市港正五金制造有限公司 | P39: 75 | Q39: 600 | R39: 141009.77 | T39: 8.47 | V39: 8 | W39: 1 | X39: 序号1 | Y39: 1 | Z39: 序号1箱装4万颗 | AD39: 0 | AE39: 0.02 | AF39: =_xlfn.DISPIMG("ID_F8D7BD56BD9C4739BA64128F900B7C0C",1) -> =DISPIMG("ID_F8D7BD56BD9C4739BA64128F900B7C0C",1) | AH39: RPRRI00148 | AI39: 45631 | AJ39: PR202400148 | AK39: 45631 | AL39: 75 | AM39: 600 | AN39: 126558.19 | AO39: 40000 | AP39: PCE | AQ39: WHSU2789070 | AR39: 45660 | AS39: 030F500175 | AT39: 45674 | AU39: 45677 | AV39: 20FT | AW39: WAN HAI 371/S011 | AX39: ¥9,738.00 | AZ39: 351329.77
A40: 30 | B40: 7326909000 | C40: 732690 | D40: J00016-Ladle Set-大勺套装 | E40: 1.0t*ID2.7*∅18*打孔轮 | F40: 1.0t*ID2.7*∅18* Punch wheel | I40: KGM | J40: 58.9 | K40: 40000 | L40: PCE | P40: 158.3 | Q40: 9323.87 | T40: 59.39 | V40: 58.9 | X40: 序号2 | Y40: 1 | Z40: 序号2箱装4万颗 | AD40: 0 | AE40: 0.02 | AF40: =_xlfn.DISPIMG("ID_533EC456924442BD9A4924A4E3684D7C",1) -> =DISPIMG("ID_533EC456924442BD9A4924A4E3684D7C",1) | AL40: 158.3 | AM40: 9323.87 | AO40: 40000 | AP40: PCE | AQ40: WHSU2789070 | AR40: 45660 | AS40: 030F500175 | AT40: 45674 | AU40: 45677 | AV40: 20FT | AW40: WAN HAI 371/S011
A41: 31 | B41: 7326909000 | C41: 732690 | D41: J00016-Ladle Set-大勺套装 | E41: 1.0t*9.7*117.9齿条 | F41: 1.0t x 9.7 x 117.9 rack | I41: KGM | J41: 76 | K41: 16000 | L41: PCE | P41: 139.42 | Q41: 10595.92 | T41: 88.94 | V41: 76 | X41: 序号3-4 | Y41: 5 | Z41: 序号3至4箱装8千颗 | AD41: 0 | AE41: 0.1 | AF41: =_xlfn.DISPIMG("ID_A095E048115E4230A5098DD4252295AF",1) -> =DISPIMG("ID_A095E048115E4230A5098DD4252295AF",1) | AL41: 139.42 | AM41: 10595.92 | AO41: 16000 | AP41: PCE | AQ41: WHSU2789070 | AR41: 45660 | AS41: 030F500175 | AT41: 45674 | AU41: 45677 | AV41: 20FT | AW41: WAN HAI 371/S011
A42: 32 | B42: 7326909000 | C42: 732690 | D42: J00015-Spade Set-铲子套装 | E42: 0.8t*7.2*71齿条 | F42: 0.8t*7.2*71 rack | I42: KGM | J42: 64.38 | K42: 37000 | L42: PCE | P42: 177.5 | Q42: 11427.45 | T42: 69.72 | V42: 64.38 | X42: 序号8-9 | Y42: 2 | Z42: 序号8箱装2.1万颗 序号9箱装1.6万颗 | AD42: 0 | AE42: 0.04 | AF42: =_xlfn.DISPIMG("ID_39FBA0FA05C84292AB6B4BEDE7A43250",1) -> =DISPIMG("ID_39FBA0FA05C84292AB6B4BEDE7A43250",1) | AL42: 177.5 | AM42: 11427.45 | AO42: 37000 | AP42: PCE | AQ42: WHSU2789070 | AR42: 45660 | AS42: 030F500175 | AT42: 45674 | AU42: 45677 | AV42: 20FT | AW42: WAN HAI 371/S011
A43: 33 | B43: 7326909000 | C43: 732690 | D43: J00015-Spade Set-铲子套装 J00016-Ladle Set-大勺套装 | E43: 0.8t*8.2*68.4细齿齿条 | F43: 0.8t*8.2*68.4 fine tooth rack | I43: KGM | J43: 58.52 | K43: 44000 | L43: PCE | P43: 321 | Q43: 18784.92 | T43: 61.65 | V43: 58.52 | X43: 序号10-12、16 | Y43: 7 | Z43: 序号10至12箱装1.2万颗 序号16箱装8千颗 | AD43: 0 | AE43: 0.14 | AF43: =_xlfn.DISPIMG("ID_0C5B4E5496B446BC99850A6205D9CCAB",1) -> =DISPIMG("ID_0C5B4E5496B446BC99850A6205D9CCAB",1) | AL43: 321 | AM43: 18784.92 | AO43: 44000 | AP43: PCE | AQ43: WHSU2789070 | AR43: 45660 | AS43: 030F500175 | AT43: 45674 | AU43: 45677 | AV43: 20FT | AW43: WAN HAI 371/S011
A44: 34 | B44: 7326909000 | C44: 732690 | D44: J00015-Spade Set-铲子套装 | E44: 0.8t*3.4*66.1齿条 | F44: 0.8t x 3.4 x 66.1 rack | I44: KGM | J44: 52.1 | K44: 40000 | L44: PCE | P44: 288.6 | Q44: 15036.06 | T44: 56.59 | V44: 52.1 | X44: 序号17-18 | Y44: 2 | Z44: 序号17箱装2.4万颗 序号18箱装1.6万颗 | AD44: 0 | AE44: 0.04 | AF44: =_xlfn.DISPIMG("ID_48CE83A4F18B486992B6FA4525FC452D",1) -> =DISPIMG("ID_48CE83A4F18B486992B6FA4525FC452D",1) | AL44: 288.6 | AM44: 15036.06 | AO44: 40000 | AP44: PCE | AQ44: WHSU2789070 | AR44: 45660 | AS44: 030F500175 | AT44: 45674 | AU44: 45677 | AV44: 20FT | AW44: WAN HAI 371/S011
A45: 35 | B45: 7326909000 | C45: 732690 | D45: J00002-Jack Lantern-南瓜灯 | E45: 0.3t*8W*7H正极 | F45: 0.3t*8W*7H positive electrode | I45: KGM | J45: 8.3 | K45: 60000 | L45: PCE | P45: 343.4 | Q45: 2850.22 | T45: 8.81 | V45: 8.3 | X45: 序号19 | Y45: 1 | Z45: 序号19箱装6万颗 | AD45: 0 | AE45: 0.02 | AF45: =_xlfn.DISPIMG("ID_833C30FF772A46EDAF611826D78B2482",1) -> =DISPIMG("ID_833C30FF772A46EDAF611826D78B2482",1) | AL45: 343.4 | AM45: 2850.22 | AO45: 60000 | AP45: PCE | AQ45: WHSU2789070 | AR45: 45660 | AS45: 030F500175 | AT45: 45674 | AU45: 45677 | AV45: 20FT | AW45: WAN HAI 371/S011
A46: 36 | B46: 7326909000 | C46: 732690 | D46: J00002-Jack Lantern-南瓜灯 | E46: 0.3t*8W*7H负极 | F46: 0.3t*8W*7H negative electrode | I46: KGM | J46: 13.6 | K46: 60000 | L46: PCE | P46: 375.45 | Q46: 5106.12 | T46: 14.09 | V46: 13.6 | X46: 序号20 | Y46: 1 | Z46: 序号20箱装6万颗 | AD46: 0 | AE46: 0.02 | AF46: =_xlfn.DISPIMG("ID_A795A2B5AE2641E0B5E181416F19E319",1) -> =DISPIMG("ID_A795A2B5AE2641E0B5E181416F19E319",1) | AL46: 375.45 | AM46: 5106.12 | AO46: 60000 | AP46: PCE | AQ46: WHSU2789070 | AR46: 45660 | AS46: 030F500175 | AT46: 45674 | AU46: 45677 | AV46: 20FT | AW46: WAN HAI 371/S011
A47: 37 | B47: 7326909000 | C47: 732690 | D47: J00002-Jack Lantern-南瓜灯 | E47: 0.3t*16.8W*7H负正极 | F47: 0.3t*16.8W*7H negative positive electrode | I47: KGM | J47: 42.1 | K47: 120000 | L47: PCE | P47: 370.5 | Q47: 15598.05 | T47: 44 | V47: 42.1 | X47: 序号21-24 | Y47: 4 | Z47: 序号21至24箱装3万颗 | AD47: 0 | AE47: 0.08 | AF47: =_xlfn.DISPIMG("ID_0684888A734548CB8CBA2966956BE895",1) -> =DISPIMG("ID_0684888A734548CB8CBA2966956BE895",1) | AL47: 370.5 | AM47: 15598.05 | AO47: 120000 | AP47: PCE | AQ47: WHSU2789070 | AR47: 45660 | AS47: 030F500175 | AT47: 45674 | AU47: 45677 | AV47: 20FT | AW47: WAN HAI 371/S011
A48: 38 | B48: 7326909000 | C48: 741533 | D48: J00002-Jack Lantern-南瓜灯 | E48: 螺丝 2.3*6PB | F48: Screws 2.3*6PB | I48: KGM | J48: 11.6 | K48: 60000 | L48: PCE | P48: 20.2 | Q48: 234.32 | T48: 12.11 | V48: 11.6 | X48: 序号25 | Y48: 1 | Z48: 序号25箱装6万颗 | AD48: 0 | AE48: 0.02 | AF48: =_xlfn.DISPIMG("ID_06DC40AD45A043DABB05292CC4E7786D",1) -> =DISPIMG("ID_06DC40AD45A043DABB05292CC4E7786D",1) | AL48: 20.2 | AM48: 234.32 | AO48: 60000 | AP48: PCE | AQ48: WHSU2789070 | AR48: 45660 | AS48: 030F500175 | AT48: 45674 | AU48: 45677 | AV48: 20FT | AW48: WAN HAI 371/S011
A49: 39 | B49: 7326909000 | C49: 741533 | D49: J00002-Jack Lantern-南瓜灯 | E49: 螺丝 2.3*8PB | F49: Screws 2.3*8PB | I49: KGM | J49: 43.7 | K49: 180000 | L49: PCE | P49: 20.6 | Q49: 900.22 | T49: 44.21 | V49: 43.7 | X49: 序号26 | Y49: 1 | Z49: 序号26箱装18万颗 | AD49: 0 | AE49: 0.02 | AF49: =_xlfn.DISPIMG("ID_EABDAAE6FFCF40A899C663441ECD4974",1) -> =DISPIMG("ID_EABDAAE6FFCF40A899C663441ECD4974",1) | AL49: 20.6 | AM49: 900.22 | AO49: 180000 | AP49: PCE | AQ49: WHSU2789070 | AR49: 45660 | AS49: 030F500175 | AT49: 45674 | AU49: 45677 | AV49: 20FT | AW49: WAN HAI 371/S011
A50: 40 | B50: 7326909000 | C50: 732690 | D50: J00012-Little Pumpkin Light-小南瓜灯 | E50: 正极电池片0.4t*11W*9H 叶仔1.0±0.1 坡高1.5 | F50: Positive battery 0.4t*11W*9H Blade 1.0±0.1 Slope height 1.5 | I50: KGM | J50: 78.3 | K50: 300000 | L50: PCE | P50: 100.8 | Q50: 7892.64 | T50: 79.71 | V50: 78.3 | X50: 序号27-29 | Y50: 3 | Z50: 序号27-29箱装10万颗 | AD50: 0 | AE50: 0.06 | AF50: =_xlfn.DISPIMG("ID_A8B656F1C78140A986BCBCF0528DBCAD",1) -> =DISPIMG("ID_A8B656F1C78140A986BCBCF0528DBCAD",1) | AL50: 100.8 | AM50: 7892.64 | AO50: 300000 | AP50: PCE | AQ50: WHSU2789070 | AR50: 45660 | AS50: 030F500175 | AT50: 45674 | AU50: 45677 | AV50: 20FT | AW50: WAN HAI 371/S011
A51: 41 | B51: 7326909000 | C51: 732690 | D51: J00012-Little Pumpkin Light-小南瓜灯 | E51: 负极电池片0.4t*11W*9H 叶仔1.0±0.1 | F51: Negative battery 0.4t*11W*9H blade size 1.0±0.1 | I51: KGM | J51: 111.6 | K51: 300000 | L51: PCE | P51: 182 | Q51: 20311.2 | T51: 128.3 | V51: 111.6 | X51: 序号30-39 | Y51: 10 | Z51: 序号30-39箱装3万颗 | AD51: 0 | AE51: 0.2 | AF51: =_xlfn.DISPIMG("ID_78EA6292A86A49DE810C08F497ACB3BA",1) -> =DISPIMG("ID_78EA6292A86A49DE810C08F497ACB3BA",1) | AL51: 182 | AM51: 20311.2 | AO51: 300000 | AP51: PCE | AQ51: WHSU2789070 | AR51: 45660 | AS51: 030F500175 | AT51: 45674 | AU51: 45677 | AV51: 20FT | AW51: WAN HAI 371/S011
A52: 42 | B52: 7326909000 | C52: 741533 | D52: J00012-Little Pumpkin Light-小南瓜灯 | E52: 螺丝 2.3*6PB | F52: Screws 2.3*6PB | I52: KGM | J52: 116.5 | K52: 600000 | L52: PCE | P52: 20.1 | Q52: 2341.65 | T52: 131.92 | V52: 116.5 | X52: 序号40-42 | Y52: 3 | Z52: 序号40-41箱装28万颗 序号42箱装4万颗 | AD52: 0 | AE52: 0.06 | AF52: =_xlfn.DISPIMG("ID_7D32CB1B8CC74264932F0CA497DD1B62",1) -> =DISPIMG("ID_7D32CB1B8CC74264932F0CA497DD1B62",1) | AL52: 20.1 | AM52: 2341.65 | AO52: 600000 | AP52: PCE | AQ52: WHSU2789070 | AR52: 45660 | AS52: 030F500175 | AT52: 45674 | AU52: 45677 | AV52: 20FT | AW52: WAN HAI 371/S011
A53: 43 | B53: 7326909000 | C53: 741533 | D53: J00012-Little Pumpkin Light-小南瓜灯 | E53: M2.6*8PM 牙=5.5mm D=3.6(带槽倒扣） | F53: M2.6*8PM tooth =5.5mm D=3.6(back-up with slot) | I53: KGM | J53: 84 | K53: 300000 | L53: PCE | P53: 32.5 | Q53: 2730 | T53: 86.98 | V53: 84 | X53: 序号43-44 | Y53: 2 | Z53: 序号43箱装22万颗 序号44箱装8万颗 | AD53: 0 | AE53: 0.04 | AF53: =_xlfn.DISPIMG("ID_DFC6DF3E3D6749D9922DD1F7276A1895",1) -> =DISPIMG("ID_DFC6DF3E3D6749D9922DD1F7276A1895",1) | AL53: 32.5 | AM53: 2730 | AO53: 300000 | AP53: PCE | AQ53: WHSU2789070 | AR53: 45660 | AS53: 030F500175 | AT53: 45674 | AU53: 45677 | AV53: 20FT | AW53: WAN HAI 371/S011
A54: 44 | B54: 7326909000 | C54: 741533 | D54: J00012-Little Pumpkin Light-小南瓜灯 | E54: M2.6*2.0L丝母 | F54: M2.6*2.0L silk masterbatch | I54: KGM | J54: 72 | K54: 300000 | L54: PCE | P54: 29.17 | Q54: 2100.24 | T54: 73.38 | V54: 72 | W54: 2 | X54: 序号45-46 | Y54: 2 | Z54: 序号45箱装28万颗 序号46箱装2万颗 | AD54: 0 | AE54: 0.04 | AF54: =_xlfn.DISPIMG("ID_B95023C6E9324BCD882DF3050F66A2E5",1) -> =DISPIMG("ID_B95023C6E9324BCD882DF3050F66A2E5",1) | AL54: 29.17 | AM54: 2100.24 | AO54: 300000 | AP54: PCE | AQ54: WHSU2789070 | AR54: 45660 | AS54: 030F500175 | AT54: 45674 | AU54: 45677 | AV54: 20FT | AW54: WAN HAI 371/S011
A55: 45 | B55: 7326909000 | C55: 741533 | D55: J00025-Color Changing Pumpkin Light-变色南瓜灯 | E55: 螺丝 2.3*4PB D=3.6 | F55: Screw 2.3*4PB D=3.6 | I55: KGM | J55: 12.45 | K55: 79800 | L55: PCE | P55: 25 | Q55: 311.25 | T55: 12.92 | V55: 12.45 | X55: 序号47 | Y55: 1 | Z55: 序号47箱装79800颗 | AD55: 0 | AE55: 0.02 | AF55: =_xlfn.DISPIMG("ID_8DA5CEABB3984060932420E7516144D4",1) -> =DISPIMG("ID_8DA5CEABB3984060932420E7516144D4",1) | AL55: 25 | AM55: 311.25 | AO55: 79800 | AP55: PCE | AQ55: WHSU2789070 | AR55: 45660 | AS55: 030F500175 | AT55: 45674 | AU55: 45677 | AV55: 20FT | AW55: WAN HAI 371/S011
A56: 46 | B56: 7326909000 | C56: 741533 | D56: J00025-Color Changing Pumpkin Light-变色南瓜灯 | E56: 螺丝 2.3*6PB D=3.6 | F56: Screw 2.3*6PB D=3.6 | I56: KGM | J56: 20.6 | K56: 106200 | L56: PCE | P56: 20.1 | Q56: 414.06 | T56: 21.07 | V56: 20.6 | X56: 序号48 | Y56: 1 | Z56: 序号48箱装106200颗 | AD56: 0 | AE56: 0.02 | AF56: =_xlfn.DISPIMG("ID_804AE914AB3847D2A102549677A81EE6",1) -> =DISPIMG("ID_804AE914AB3847D2A102549677A81EE6",1) | AL56: 20.1 | AM56: 414.06 | AO56: 106200 | AP56: PCE | AQ56: WHSU2789070 | AR56: 45660 | AS56: 030F500175 | AT56: 45674 | AU56: 45677 | AV56: 20FT | AW56: WAN HAI 371/S011
A57: 47 | B57: 7326909000 | C57: 741533 | D57: J00025-Color Changing Pumpkin Light-变色南瓜灯 | E57: M2.6*8PM 牙=5.5mm D=3.6(带槽倒扣） | F57: M2.6*8PM tooth =5.5mm D=3.6(back-up with slot) | I57: KGM | J57: 7.5 | K57: 26900 | L57: PCE | P57: 32.6 | Q57: 244.5 | T57: 8 | V57: 7.5 | X57: 序号49 | Y57: 1 | Z57: 序号49箱装26900颗 | AD57: 0 | AE57: 0.02 | AF57: =_xlfn.DISPIMG("ID_6AD4E7B28D2941B980E6AB35944228F9",1) -> =DISPIMG("ID_6AD4E7B28D2941B980E6AB35944228F9",1) | AH57: RPRRI00149 | AI57: 45631 | AJ57: PR202400149 | AK57: 45631 | AL57: 32.6 | AM57: 244.5 | AN57: 14451.58 | AO57: 26900 | AP57: PCE | AQ57: WHSU2789070 | AR57: 45660 | AS57: 030F500175 | AT57: 45674 | AU57: 45677 | AV57: 20FT | AW57: WAN HAI 371/S011
A58: 48 | B58: 7326909000 | C58: 741533 | D58: J00025-Color Changing Pumpkin Light-变色南瓜灯 | E58: M2.6*2.0L丝母 | F58: M2.6*2.0L silk masterbatch | I58: KGM | J58: 6.45 | K58: 26900 | L58: PCE | P58: 29.2 | Q58: 188.34 | T58: 6.93 | V58: 6.45 | X58: 序号50 | Y58: 1 | Z58: 序号50箱装26900颗 | AD58: 0 | AE58: 0.02 | AF58: =_xlfn.DISPIMG("ID_BA306B473CD54201851EDC7A9BEB86C4",1) -> =DISPIMG("ID_BA306B473CD54201851EDC7A9BEB86C4",1) | AL58: 29.2 | AM58: 188.34 | AO58: 26900 | AP58: PCE | AQ58: WHSU2789070 | AR58: 45660 | AS58: 030F500175 | AT58: 45674 | AU58: 45677 | AV58: 20FT | AW58: WAN HAI 371/S011
A59: 49 | B59: 7326909000 | C59: 732690 | D59: J00025-Color Changing Pumpkin Light-变色南瓜灯 | E59: CI226正片 | F59: CI226 positive | I59: KGM | J59: 7.6 | K59: 26900 | L59: PCE | P59: 64.7 | Q59: 491.72 | T59: 8.08 | V59: 7.6 | X59: 序号51 | Y59: 1 | Z59: 序号51箱装26900颗 | AD59: 0 | AE59: 0.02 | AF59: =_xlfn.DISPIMG("ID_2F40AC44AE12468C8F39E0E2C5CB4C90",1) -> =DISPIMG("ID_2F40AC44AE12468C8F39E0E2C5CB4C90",1) | AL59: 64.7 | AM59: 491.72 | AO59: 26900 | AP59: PCE | AQ59: WHSU2789070 | AR59: 45660 | AS59: 030F500175 | AT59: 45674 | AU59: 45677 | AV59: 20FT | AW59: WAN HAI 371/S011
A60: 50 | B60: 7326909000 | C60: 732690 | D60: J00025-Color Changing Pumpkin Light-变色南瓜灯 | E60: CI226负片 | F60: CI226 negative | I60: KGM | J60: 11.36 | K60: 26900 | L60: PCE | P60: 98 | Q60: 1113.28 | T60: 11.82 | V60: 11.36 | X60: 序号52 | Y60: 1 | Z60: 序号52箱装26900颗 | AD60: 0 | AE60: 0.02 | AF60: =_xlfn.DISPIMG("ID_8A80BE17CF0446D4AA6FB494A91F28B5",1) -> =DISPIMG("ID_8A80BE17CF0446D4AA6FB494A91F28B5",1) | AL60: 98 | AM60: 1113.28 | AO60: 26900 | AP60: PCE | AQ60: WHSU2789070 | AR60: 45660 | AS60: 030F500175 | AT60: 45674 | AU60: 45677 | AV60: 20FT | AW60: WAN HAI 371/S011
A61: 51 | B61: 7326909000 | C61: 732690 | D61: J00025-Color Changing Pumpkin Light-变色南瓜灯 | E61: CI226正负片 | F61: CI226 positive and negative | I61: KGM | J61: 16.8 | K61: 26900 (ACTUAL QTY 23,600) | L61: PCE | P61: 71.1 | Q61: 1194.48 | T61: 17.3 | V61: 16.8 | X61: 序号53 | Y61: 1 | Z61: 序号53箱装26900颗 | AD61: 0 | AE61: 0.02 | AF61: =_xlfn.DISPIMG("ID_6924EDB86E67465F8FB1FB9A86DD6655",1) -> =DISPIMG("ID_6924EDB86E67465F8FB1FB9A86DD6655",1) | AL61: 71.1 | AM61: 1194.48 | AO61: 26900 (ACTUAL QTY 23,600) | AP61: PCE | AQ61: WHSU2789070 | AR61: 45660 | AS61: 030F500175 | AT61: 45674 | AU61: 45677 | AV61: 20FT | AW61: WAN HAI 371/S011
A62: 52 | B62: 7326909000 | C62: 732690 | D62: J00025-Color Changing Pumpkin Light-变色南瓜灯 | E62: CI226负正片 | F62: CI226 negative and positive | I62: KGM | J62: 17 | K62: 26900 | L62: PCE | P62: 71.8 | Q62: 1220.6 | T62: 17.5 | V62: 17 | X62: 序号54 | Y62: 1 | Z62: 序号54箱装26900颗 | AD62: 0 | AE62: 0.02 | AF62: =_xlfn.DISPIMG("ID_794B66885793491E88BADFB5BA09E1CA",1) -> =DISPIMG("ID_794B66885793491E88BADFB5BA09E1CA",1) | AL62: 71.8 | AM62: 1220.6 | AO62: 26900 | AP62: PCE | AQ62: WHSU2789070 | AR62: 45660 | AS62: 030F500175 | AT62: 45674 | AU62: 45677 | AV62: 20FT | AW62: WAN HAI 371/S011
A63: 53 | B63: 7326909000 | C63: 732690 | D63: J00038-Remote Control Light-遥控灯 | E63: 0.3t*8W*7H正极 | F63: 0.3t*8W*7H positive electrode | I63: KGM | J63: 3.1 | K63: 22200 | L63: PCE | P63: 340.4 | Q63: 1055.24 | T63: 3.56 | V63: 3.1 | X63: 序号55 | Y63: 1 | Z63: 序号55箱装22200颗 | AD63: 0 | AE63: 0.02 | AF63: =_xlfn.DISPIMG("ID_9F94EB0BAC4F42D9B01943BD63E6F47B",1) -> =DISPIMG("ID_9F94EB0BAC4F42D9B01943BD63E6F47B",1) | AL63: 340.4 | AM63: 1055.24 | AO63: 22200 | AP63: PCE | AQ63: WHSU2789070 | AR63: 45660 | AS63: 030F500175 | AT63: 45674 | AU63: 45677 | AV63: 20FT | AW63: WAN HAI 371/S011
A64: 54 | B64: 7326909000 | C64: 732690 | D64: J00038-Remote Control Light-遥控灯 | E64: 0.3t*8W*7H负极 | F64: 0.3t*8W*7H negative electrode | I64: KGM | J64: 5 | K64: 22200 | L64: PCE | P64: 377.8 | Q64: 1889 | T64: 5.51 | V64: 5 | X64: 序号56 | Y64: 1 | Z64: 序号56箱装22200颗 | AD64: 0 | AE64: 0.02 | AF64: =_xlfn.DISPIMG("ID_F1BEA163CABD42AAAFF172AEC37F91C8",1) -> =DISPIMG("ID_F1BEA163CABD42AAAFF172AEC37F91C8",1) | AL64: 377.8 | AM64: 1889 | AO64: 22200 | AP64: PCE | AQ64: WHSU2789070 | AR64: 45660 | AS64: 030F500175 | AT64: 45674 | AU64: 45677 | AV64: 20FT | AW64: WAN HAI 371/S011
A65: 55 | B65: 7326909000 | C65: 732690 | D65: J00038-Remote Control Light-遥控灯 | E65: 0.3t*16.8W*7H负正极 | F65: 0.3t*16.8W*7H negative positive electrode | I65: KGM | J65: 15.44 | K65: 44000 | L65: PCE | P65: 370.5 | Q65: 5720.52 | T65: 17.39 | V65: 15.44 | X65: 序号57-58 | Y65: 2 | Z65: 序号57箱装3万颗 序号58箱装1万4千4百颗 | AD65: 0 | AE65: 0.04 | AF65: =_xlfn.DISPIMG("ID_6737849078134CEC9F439833E9A53B7E",1) -> =DISPIMG("ID_6737849078134CEC9F439833E9A53B7E",1) | AL65: 370.5 | AM65: 5720.52 | AO65: 44000 | AP65: PCE | AQ65: WHSU2789070 | AR65: 45660 | AS65: 030F500175 | AT65: 45674 | AU65: 45677 | AV65: 20FT | AW65: WAN HAI 371/S011
A66: 56 | B66: 7326909000 | C66: 741533 | D66: J00038-Remote Control Light-遥控灯 | E66: 螺丝 2.6*6PB | F66: Screws 2.6*6PB | I66: KGM | J66: 16.8 | K66: 66000 | L66: PCE | P66: 16.1 | Q66: 270.48 | T66: 17.23 | V66: 16.8 | X66: 序号59 | Y66: 1 | Z66: 序号59箱装66000颗 | AD66: 0 | AE66: 0.02 | AF66: =_xlfn.DISPIMG("ID_00D8AA44ACAF45848FCC012D4820E73A",1) -> =DISPIMG("ID_00D8AA44ACAF45848FCC012D4820E73A",1) | AL66: 16.1 | AM66: 270.48 | AO66: 66000 | AP66: PCE | AQ66: WHSU2789070 | AR66: 45660 | AS66: 030F500175 | AT66: 45674 | AU66: 45677 | AV66: 20FT | AW66: WAN HAI 371/S011
A67: 57 | B67: 7326909000 | C67: 741533 | D67: J00038-Remote Control Light-遥控灯 | E67: M2.6*8PM 牙=5.5mm D=3.6(带槽倒扣） | F67: M2.6*8PM tooth =5.5mm D=3.6(back-up with slot) | I67: KGM | J67: 18.48 | K67: 66000 | L67: PCE | P67: 32.5 | Q67: 600.6 | T67: 18.95 | V67: 18.48 | X67: 序号60 | Y67: 1 | Z67: 序号60箱装66000颗 | AD67: 0 | AE67: 0.02 | AF67: =_xlfn.DISPIMG("ID_F8BE3957FC4E4BE2B4142C110478568A",1) -> =DISPIMG("ID_F8BE3957FC4E4BE2B4142C110478568A",1) | AL67: 32.5 | AM67: 600.6 | AO67: 66000 | AP67: PCE | AQ67: WHSU2789070 | AR67: 45660 | AS67: 030F500175 | AT67: 45674 | AU67: 45677 | AV67: 20FT | AW67: WAN HAI 371/S011
A68: 58 | B68: 7326909000 | C68: 741533 | D68: J00038-Remote Control Light-遥控灯 | E68: M2.6*2.0L丝母 | F68: M2.6*2.0L silk masterbatch | I68: KGM | J68: 15.85 | K68: 66000 | L68: PCE | P68: 29.2 | Q68: 462.82 | T68: 16.31 | V68: 15.85 | X68: 序号61 | Y68: 1 | Z68: 序号61箱装66000颗 | AD68: 0 | AE68: 0.02 | AF68: =_xlfn.DISPIMG("ID_E4819AA4033A4F65AFE678DCCDF74B80",1) -> =DISPIMG("ID_E4819AA4033A4F65AFE678DCCDF74B80",1) | AL68: 29.2 | AM68: 462.82 | AO68: 66000 | AP68: PCE | AQ68: WHSU2789070 | AR68: 45660 | AS68: 030F500175 | AT68: 45674 | AU68: 45677 | AV68: 20FT | AW68: WAN HAI 371/S011
J69: 1074.03 | Q69: 141009.77 | R69: 141009.77 | T69: 1150.84 | V69: 1074.03 | Y69: 61 | AE69: 1.22 | AM69: 141009.77 | AN69: 141009.77
T70: 7524.6 | V70: 0 | Y70: 16 | AE70: 3.64 | AM70: 18400 | AN70: 184
R71: 总合计 | T71: 8740 | V71: 1134.92 | Y71: 80 | AE71: 5.05 | AM71: #REF! | AN71: #REF!
A72: 1 | B72: 3920430090 | C72: 392043 | D72: J00012/J00038/W85202 -Shared-共用 | E72: 4.5CM绝缘片/厚度0.26MM | F72: 4.5CM insulation sheet/Thickness 0.26MM | I72: KGM | J72: 196.5 | K72: 580000 | L72: PCE | M72: 东莞市太初纸品有限公司 | P72: 451.62 | Q72: 88743.33 | R72: 88743.33 | T72: 240.05 | V72: 196.5 | W72: 8 | X72: 326-337 | Y72: 13 | Z72: 1至12箱数量为45100pcs 13箱数量为38800pcs | AD72: 0 | AE72: 0.27 | AF72: =_xlfn.DISPIMG("ID_474804668E924D46915EDAEB9D7E89D9",1) -> =DISPIMG("ID_474804668E924D46915EDAEB9D7E89D9",1) | AH72: RPIRRI00150 | AI72: 45631 | AJ72: PR202400150 | AK72: 45631 | AL72: 460.7 | AM72: 90527.55 | AN72: 92721.75 | AO72: 580000 | AP72: PCE | AQ72: WHSU2230204 | AR72: 45661 | AS72: 030F500396 | AT72: 45674 | AU72: 45677 | AV72: 20FT | AW72: WAN HAI 371/S011 | AX72: 9738 | AZ72: 497,888.32
A73: 2 | B73: 3926909090 | C73: 392310 | D73: W84670/W84863-Shared-共用 | E73: 5英寸子母扣 | F73: 5 inch child buckle | I73: KGM | J73: 26.5 | K73: 500000 | L73: PCE | M73: 河源市正华包装有限公司 | P73: 81.14 | Q73: 2150.21 | R73: 2150.21 | T73: 40.75 | V73: 26.5 | W73: 8 | X73: 338-342 | Y73: 5 | Z73: 每箱20盒 | AD73: 0 | AE73: 0.28 | AF73: =_xlfn.DISPIMG("ID_99EEF22C199942BB876E04057BC7DA34",1) -> =DISPIMG("ID_99EEF22C199942BB876E04057BC7DA34",1) | AL73: 82.8 | AM73: 2194.2 | AO73: 500000 | AP73: PCE | AQ73: WHSU2230204 | AR73: 45661 | AS73: 030F500396 | AT73: 45674 | AU73: 45677 | AV73: 20FT | AW73: WAN HAI 371/S011
J74: 223 | Q74: 90893.54 | R74: 90893.54 | T74: 280.8 | V74: 223 | Y74: 18 | AE74: 0.55 | AM74: 92721.75 | AN74: 92721.75
A75: 3 | B75: 9503009000 | C75: 392690 | D75: E73622A布鲁伊 家族沐浴玩具 | E75: 塑胶件-布鲁伊爸爸杯 | F75: Plastic. - Bluey's Daddy Cup | I75: KGM | J75: 111.6 | K75: 2080 | L75: PCS | M75: 东莞兴信塑胶制品有限公司 | P75: 47.3 | Q75: 5278.68 | R75: 17900.57 | T75: 166.33 | V75: 111.6 | W75: 1 | X75: 1-24 | Y75: 26 | Z75: 80 | AD75: 0 | AE75: 2.23 | AF75: =_xlfn.DISPIMG("ID_147D4E7BAA9541EDBA62F5F53D5E8EE8",1) -> =DISPIMG("ID_147D4E7BAA9541EDBA62F5F53D5E8EE8",1) | AH75: RPIRRI00151 | AI75: 45631 | AJ75: PR202400151 | AK75: 45631 | AL75: 47.3 | AM75: 5278.68 | AN75: 17900.57 | AO75: 2080 | AP75: PCS | AQ75: WHSU2230204 | AR75: 45661 | AS75: 030F500396 | AT75: 45674 | AU75: 45677 | AV75: 20FT | AW75: WAN HAI 371/S011 | AX75: 9738
A76: 4 | B76: 9503009000 | C76: 392690 | D76: E73622A布鲁伊 家族沐浴玩具 | E76: 塑胶件-布鲁伊杯 | F76: Plastic - Bluey Cup | I76: KGM | J76: 52.5 | K76: 2100 | L76: PCS | P76: 76.86 | Q76: 4035.15 | T76: 90.19 | V76: 52.5 | W76: 2 | X76: 24-34 | Y76: 10 | Z76: 210 | AD76: 0 | AE76: 0.86 | AF76: =_xlfn.DISPIMG("ID_76F3F86CC145416EAACB95F504B6A3F3",1) -> =DISPIMG("ID_76F3F86CC145416EAACB95F504B6A3F3",1) | AL76: 76.86 | AM76: 4035.15 | AO76: 2100 | AP76: PCS | AQ76: WHSU2230204 | AR76: 45661 | AS76: 030F500396 | AT76: 45674 | AU76: 45677 | AV76: 20FT | AW76: WAN HAI 371/S011
A77: 5 | B77: 9503009000 | C77: 392690 | D77: E73622A布鲁伊 家族沐浴玩具 | E77: 塑胶件-宾果妈妈杯 | F77: Plastic - Bingo mother cup | I77: KGM | J77: 135.8 | K77: 2400 | L77: PCS | P77: 41.75 | Q77: 5669.65 | T77: 185.8 | V77: 135.8 | W77: 2 | X77: 35-54 | Y77: 20 | Z77: 120 | AD77: 0 | AE77: 1.72 | AF77: =_xlfn.DISPIMG("ID_CCECD8DF9CF74AC0A5B4391F62A455D4",1) -> =DISPIMG("ID_CCECD8DF9CF74AC0A5B4391F62A455D4",1) | AL77: 41.75 | AM77: 5669.65 | AO77: 2400 | AP77: PCS | AQ77: WHSU2230204 | AR77: 45661 | AS77: 030F500396 | AT77: 45674 | AU77: 45677 | AV77: 20FT | AW77: WAN HAI 371/S011
A78: 6 | B78: 9503009000 | C78: 392690 | D78: E73635A布鲁伊沐浴浮水玩具 | E78: 塑胶件-布鲁伊泳游圈面 | F78: Plastic - Bluey swimming circle | I78: KGM | J78: 115.3 | K78: 3978 | L78: PCS | P78: 25.3 | Q78: 2917.09 | T78: 219.67 | V78: 115.3 | W78: 3卡/30箱 1卡/4箱 | X78: 35-88 | Y78: 34 | Z78: 117 | AD78: 0 | AE78: 2.92 | AF78: =_xlfn.DISPIMG("ID_75C10B8CD9334FFDB3DC03F8EB9CDC77",1) -> =DISPIMG("ID_75C10B8CD9334FFDB3DC03F8EB9CDC77",1) | AL78: 25.3 | AM78: 2917.09 | AO78: 3978 | AP78: PCS | AQ78: WHSU2230204 | AR78: 45661 | AS78: 030F500396 | AT78: 45674 | AU78: 45677 | AV78: 20FT | AW78: WAN HAI 371/S011
Q79: 17900.57 | R79: 17900.57 | T79: 661.99 | V79: 415.2 | Y79: 90 | AE79: 7.73 | AM79: 17900.57 | AN79: 17900.57
A80: 7 | B80: 8506101210 | C80: 850610 | E80: 碱性锌锰电池 | F80: Alkaline zinc-manganese battery | I80: PCE | J80: 1970000 | K80: 1970000 | L80: pcs | M80: 耐科森(香港)科技有限公司 | P80: 0.178 | Q80: 350660 | R80: 350660 | T80: 4397 | V80: 4235.5 | W80: 4-7 | X80: 129-325 | Y80: 4 | Z80: 1至3箱数量为480000pcs 4箱数量为530000pcs | AD80: 0 | AE80: 4.25 | AF80: =_xlfn.DISPIMG("ID_AA13D2F409114E95BE6C61E973A35C6F",1) -> =DISPIMG("ID_AA13D2F409114E95BE6C61E973A35C6F",1) | AG80: ∣提供电源∣碱性锌锰成分∣圆柱型∣无牌∣1.5v|无汞 AG13|不享惠 | AH80: RPIRRI00152 | AI80: 45631 | AJ80: PR202400152 | AK80: 45631 | AL80: 0.178 | AM80: 350660 | AN80: 350660 | AO80: 1970000 | AP80: pcs | AQ80: WHSU2230204 | AR80: 45661 | AS80: 030F500816 | AT80: 45674 | AU80: 45677 | AV80: 20FT | AW80: WAN HAI 371/S011 | AX80: 9738 | AZ80: 316252.34
A81: 8 | B81: 8506109010 | C81: 850610 | D81: 47602J | E81: 47602T-AAA-碳性电池(GP)AAA RO3绿色CE标 | F81: 47602T-AAA-Carbon Battery (GP) AAA RO3 Green CE Standard | I81: PCE | J81: 40000 | K81: 40000 | L81: PCS | M81: 东莞市莞力电子科技有限公司 | P81: 0.0586 | Q81: 2344 | R81: 2344 | T81: 359.71 | V81: 328 | W81: 4-7 | X81: 89-128 | Y81: 40 | Z81: 1000 | AD81: 0 | AE81: 0.36 | AF81: =_xlfn.DISPIMG("ID_582EECE49FE54679AFB3355D867FEA25",1) -> =DISPIMG("ID_582EECE49FE54679AFB3355D867FEA25",1) | AH81: RPIRRI00153 | AI81: 45631 | AJ81: PR202400153 | AK81: 45631 | AL81: 0.0586 | AM81: 2344 | AN81: 2344 | AO81: 40000 | AP81: PCS | AQ81: WHSU2230204 | AR81: 45661 | AS81: 030F500817 | AT81: 45674 | AU81: 45677 | AV81: 20FT | AW81: WAN HAI 371/S011 | AZ81: 7252.11
Q82: 353004 | R82: 353004 | T82: 4756.71 | V82: 4563.5 | Y82: 44 | AE82: 4.61 | AM82: 353004 | AN82: 353004
A83: 9 | B83: 8479899990 | C83: 847989 | E83: 胶针机 | F83: Glue needle machine | G83: ML120-BEP | I83: PCE | J83: 1 | K83: 1 | L83: PCS | M83: 东莞市雅洛轩进出口贸易有限公司 | P83: 6800 | Q83: 6800 | R83: 44000 | T83: 69 | V83: 50 | W83: 8 | X83: 343 | Y83: 1 | Z83: 1 | AD83: 0 | AE83: 0.42 | AF83: =_xlfn.DISPIMG("ID_78F153490C5F4E3F986F87830727CEC5",1) -> =DISPIMG("ID_78F153490C5F4E3F986F87830727CEC5",1) | AG83: 打胶钉 | AH83: YN00096 | AI83: 45637 | AJ83: YNA00096 | AK83: 45637 | AL83: 6800 | AM83: 6800 | AN83: 44000 | AO83: 1 | AP83: PCS | AQ83: WHSU2230204 | AR83: 45661 | AS83: 030F500818 | AT83: 45674 | AU83: 45677 | AV83: 20FT | AW83: WAN HAI 371/S011 | AX83: 9738 | AZ83: 34262
A84: 10 | B84: 8443321300 | C84: 844332 | E84: 喷码机 | F84: Inkjet printer | G84: S680-S PLUS | I84: PCE | J84: 2 | K84: 2 | L84: PCS | P84: 18600 | Q84: 37200 | T84: 121.5 | V84: 96.5 | W84: 8 | X84: 344-348 | Y84: 5 | AD84: 0 | AE84: 2.46 | AF84: =_xlfn.DISPIMG("ID_BAA5FDDCD8004A308E90FC1E999A5D02",1) -> =DISPIMG("ID_BAA5FDDCD8004A308E90FC1E999A5D02",1) | AG84: 打印日期码 | AL84: 18600 | AM84: 37200 | AO84: 2 | AP84: PCS | AQ84: WHSU2230204 | AR84: 45661 | AS84: 030F500818 | AT84: 45674 | AU84: 45677 | AV84: 20FT | AW84: WAN HAI 371/S011
Q85: 44000 | R85: 44000 | T85: 190.5 | V85: 146.5 | Y85: 6 | AE85: 2.88 | AM85: 44000 | AN85: 44000
M87: 合计 | Q87: 505798.11 | R87: 505798.11 | T87: 5890 | V87: 5348.2 | Y87: 158 | AE87: 15.77 | AM87: 507626.32 | AN87: 507626.32
A88: 1 | B88: 4004000090 | C88: 390950 | D88: FC83591GN-Dinosaur-恐龙/FC83541GN-Unicorn-独角兽 | E88: 碎海绵 | F88: Shredded Foam | I88: KGM | J88: 17390 | K88: 28 | L88: 包 | M88: 东莞市正隆家居用品有限公司 | P88: 5.1 | Q88: 88689 | R88: 88689 | T88: 17390 | V88: 17390 | W88: 1-28 | X88: 1-28 | Y88: 28 | AD88: 2.1437312 | AE88: 66 | AH88: CGDD007446-2 | AI88: 45631 | AJ88: CGDD007446-2 | AK88: 45631 | AL88: 5.1 | AM88: 88689 | AN88: 88689 | AO88: 28 | AP88: 包 | AQ88: MRSU4935317 | AR88: 06/01/2025 | AS88: MAEU-248336436 | AT88: 19/01/2025 | AU88: 21/01/2025 | AV88: 40HQ | AW88: AS NARA/502S | AX88: 16188 | AZ88: 66264.61
Q89: 88689 | R89: 88689 | T89: 17390 | V89: 17390 | Y89: 28 | AE89: 66 | AM89: 88689 | AN89: 88689
A91: 1 | B91: 4004000090 | C91: 390950 | D91: FC86005GN-Teddy Dog-泰迪狗/FC83645GN-White Nose Dog-白鼻子狗 | E91: 碎海绵 | F91: Shredded Foam | I91: KGM | J91: 19740 | K91: 28 | L91: 包 | M91: 东莞市正隆家居用品有限公司 | P91: 5.1 | Q91: 100674 | R91: 100674 | T91: 19740 | V91: 19740 | W91: 1-28 | X91: 1-28 | Y91: 28 | AD91: 2.1437312 | AE91: 66 | AH91: CGDD007446-1 | AI91: 45631 | AJ91: CGD007446-1 | AK91: 45631 | AL91: 5.1 | AM91: 100674 | AN91: 100674 | AO91: 28 | AP91: 包 | AQ91: BMOU4677162 | AR91: 06/01/2025 | AS91: MAEU 248336447 | AT91: 19/01/2025 | AU91: 21/01/2025 | AV91: 40HQ | AW91: AS NARA/502S | AX91: 16188 | AZ91: 77404.52
Q92: 100674 | R92: 100674 | T92: 19740 | V92: 19740 | Y92: 28 | AE92: 66 | AM92: 100674 | AN92: 100674
A94: 1 | B94: 4821100000 | C94: 482110 | D94: 47669-JD THE COWS ARE OUT-奶牛农场公仔与铲车 | E94: 产品贴纸 | F94: Product sticker | I94: KGM | J94: 0.44 | K94: 800 | L94: SET | M94: 东莞清溪台聚印刷有限公司 | P94: 1136.5 | Q94: =P94*J94 -> 500.06 | R94: =Q94 -> 500.06 | T94: 1.13 | V94: 0.44 | W94: 8 | X94: 230 | Y94: 1 | Z94: 800 | AD94: =AA94*AB94*AC94/28316.75*0.0283 -> 0 | AE94: 0.01 | AG94: 产品配件 | AH94: RPRRI00141 | AI94: 45631 | AJ94: PR202400141 | AK94: 45631 | AL94: 1159.25 | AM94: =AL94*J94 -> 510.07 | AN94: =SUM(AM94:AM108) -> 15414.22 | AO94: 800 | AP94: SET | AQ94: WHLU5810690 | AR94: 45660 | AS94: 030F500040 | AT94: 45674 | AU94: 22/01/2025 | AV94: 40HQ | AW94: WAN HAI 371/S011 | AX94: 16188 | AZ94: 109969.82
A95: 2 | B95: 4819200000 | C95: 481920 | D95: 47669-JD THE COWS ARE OUT-奶牛农场公仔与铲车 | E95: 彩盒 | F95: Color box | G95: 34.3CM(L) x7.6CM(D) x 25.4CM(H) | I95: KGM | J95: 29.24 | K95: 200 | L95: pcs | M95: 东莞市恒新昌彩印有限公司 | P95: 171 | Q95: =P95*J95 -> 5000.04 | R95: =Q95 -> 5000.04 | T95: 30.54 | V95: 29.24 | W95: 8 | X95: 231-232 | Y95: 3 | Z95: 100 | AD95: =AA95*AB95*AC95/28316.75*0.0283 -> 0 | AE95: 0.26 | AG95: 产品配件 | AL95: 174.5 | AM95: =AL95*J95 -> 5102.38 | AO95: 200 | AP95: pcs | AQ95: WHLU5810690 | AR95: 45660 | AS95: 030F500040 | AT95: 45674 | AU95: 22/01/2025 | AV95: 40HQ | AW95: WAN HAI 371/S011
A96: 3 | B96: 4007000000 | C96: 400700 | D96: 47669-JD THE COWS ARE OUT-奶牛农场公仔与铲车 | E96: 透明橡皮筋-3024 | F96: Clear rubber band -3024 | I96: KGM | J96: 0.73 | K96: 10000 | L96: pcs | M96: 江西艺达辉工艺品有限公司 | P96: 452 | Q96: =P96*J96 -> 329.96 | R96: =Q96 -> 329.96 | T96: 0.86 | V96: 0.73 | W96: 8 | X96: 233 | Y96: 1 | Z96: 10000 | AD96: =AA96*AB96*AC96/28316.75*0.0283 -> 0 | AE96: 0.01 | AG96: 产品配件 | AL96: 461 | AM96: =AL96*J96 -> 336.53 | AO96: 10000 | AP96: pcs | AQ96: WHLU5810690 | AR96: 45660 | AS96: 030F500040 | AT96: 45674 | AU96: 22/01/2025 | AV96: 40HQ | AW96: WAN HAI 371/S011
A97: 4 | B97: 4821100000 | C97: 481920 | D97: 47669-JD THE COWS ARE OUT-奶牛农场公仔与铲车 | E97: 彩盒顶固定咭 | F97: Color box top fixing card | I97: KGM | J97: 3.35 | K97: 50 | L97: pcs | M97: 东莞市星徽纸品有限公司 | P97: 18.8 | Q97: =P97*J97 -> 62.98 | R97: =SUM(Q97:Q98) -> 75.49 | T97: 3.83 | V97: 3.35 | W97: 8 | X97: 235 | Y97: 1 | Z97: 50 | AD97: =AA97*AB97*AC97/28316.75*0.0283 -> 0 | AE97: 0.03 | AG97: 产品配件 | AL97: 19.2 | AM97: =AL97*J97 -> 64.32 | AO97: 50 | AP97: pcs | AQ97: WHLU5810690 | AR97: 45660 | AS97: 030F500040 | AT97: 45674 | AU97: 22/01/2025 | AV97: 40HQ | AW97: WAN HAI 371/S011
A98: 5 | B98: 4819100000 | C98: 481910 | D98: 47669-JD THE COWS ARE OUT-奶牛农场公仔与铲车 | E98: 外箱 | F98: Outer box | I98: KGM | J98: 9 | K98: 30 | L98: PCS | P98: 1.39 | Q98: =P98*J98 -> 12.51 | T98: 9 | V98: 9 | W98: 8 | X98: 236 | Y98: 1 | Z98: 30 | AD98: =AA98*AB98*AC98/28316.75*0.0283 -> 0 | AE98: 0.08 | AG98: 产品配件 | AL98: 1.42 | AM98: =AL98*J98 -> 12.78 | AO98: 30 | AP98: PCS | AQ98: WHLU5810690 | AR98: 45660 | AS98: 030F500040 | AT98: 45674 | AU98: 22/01/2025 | AV98: 40HQ | AW98: WAN HAI 371/S011
A99: 6 | B99: 4823909000 | C99: 482390 | D99: E73635A-Splash & Float Bluey-布鲁伊沐浴浮水玩具 | E99: 1.6mm纸绳 | F99: 1.6mm Paper rope | I99: KGM | J99: 49.5 | K99: 30 | L99: PCS | M99: 深圳市鸿滨洋制品有限公司 | P99: 27.88 | Q99: =P99*J99 -> 1380.06 | R99: =Q99 -> 1380.06 | T99: 52.05 | V99: 49.5 | W99: 8 | X99: 237-240 | Y99: 4 | Z99: 1-3/8 4/6 | AD99: =AA99*AB99*AC99/28316.75*0.0283 -> 0 | AE99: 0.09 | AL99: 28.44 | AM99: =AL99*J99 -> 1407.78 | AO99: 30 | AP99: PCS | AQ99: WHLU5810690 | AR99: 45660 | AS99: 030F500040 | AT99: 45674 | AU99: 22/01/2025 | AV99: 40HQ | AW99: WAN HAI 371/S011
A100: 7 | B100: 5808100090 | C100: 580890 | D100: 92120-02-White Salamande-白色蝾螈 | E100: 6MM白色棉带 | F100: 6mm white cotton tape | I100: KGM | J100: 27.09 | K100: 67 | L100: pcs | M100: 东莞市华信兴服装有限公司 | P100: 47 | Q100: =P100*J100 -> 1273.23 | R100: =SUM(Q100:Q108) -> 7819.09 | T100: 28.56 | V100: 27.09 | W100: 3 | X100: 38 | Y100: 1 | Z100: 67 | AD100: =AA100*AB100*AC100/28316.75*0.0283 -> 0 | AE100: 0.14 | AL100: 48 | AM100: =AL100*J100 -> 1300.32 | AO100: 67 | AP100: pcs | AQ100: WHLU5810690 | AR100: 45660 | AS100: 030F500040 | AT100: 45674 | AU100: 22/01/2025 | AV100: 40HQ | AW100: WAN HAI 371/S011
A101: 8 | B101: 5401101000 | C101: 540239 | D101: 92120-02-White Salamande-白色蝾螈 | E101: 604#1431蓝色强力线 | F101: 604#1410 blue strong thread | I101: KGM | J101: 1.6 | K101: 10 | L101: pcs | P101: 62.5 | Q101: =P101*J101 -> 100 | T101: 1.6 | V101: 1.6 | Z101: 10 | AL101: =P101*1.02 -> 63.75 | AM101: =AL101*J101 -> 102 | AO101: 10 | AP101: pcs | AQ101: WHLU5810690 | AR101: 45660 | AS101: 030F500040 | AT101: 45674 | AU101: 22/01/2025 | AV101: 40HQ | AW101: WAN HAI 371/S011
A102: 9 | B102: 5401101000 | C102: 540239 | D102: 92120-02-White Salamande-白色蝾螈 | E102: 604#白色强力线 | F102: 604# white strong thread | I102: KGM | J102: 21.6 | K102: 135 | L102: pcs | P102: 62.5 | Q102: =P102*J102 -> 1350 | T102: 21.6 | V102: 21.6 | Z102: 135 | AL102: =P102*1.02 -> 63.75 | AM102: =AL102*J102 -> 1377 | AO102: 135 | AP102: pcs | AQ102: WHLU5810690 | AR102: 45660 | AS102: 030F500040 | AT102: 45674 | AU102: 22/01/2025 | AV102: 40HQ | AW102: WAN HAI 371/S011
A103: 10 | B103: 5808100090 | C103: 580890 | D103: 92120-04-Green Salamander-绿色蝾螈 | E103: 6MM白色棉带 | F103: 6mm white cotton tape | I103: KGM | J103: 27.19 | K103: 67 | L103: pcs | P103: 47 | Q103: =P103*J103 -> 1277.93 | T103: 28.56 | V103: 27.19 | W103: 8 | X103: 113 | Y103: 1 | Z103: 67 | AD103: =AA103*AB103*AC103/28316.75*0.0283 -> 0 | AE103: 0.14 | AL103: 48 | AM103: =AL103*J103 -> 1305.12 | AO103: 67 | AP103: pcs | AQ103: WHLU5810690 | AR103: 45660 | AS103: 030F500040 | AT103: 45674 | AU103: 22/01/2025 | AV103: 40HQ | AW103: WAN HAI 371/S011
A104: 11 | B104: 5401101000 | C104: 540239 | D104: 92120-04-Green Salamander-绿色蝾螈 | E104: 604#白色强力线 | F104: 604# white strong thread | I104: KGM | J104: 23.36 | K104: 146 | L104: pcs | P104: 62.5 | Q104: =P104*J104 -> 1460 | T104: 23.36 | V104: 23.36 | Z104: 146 | AL104: =P104*1.02 -> 63.75 | AM104: =AL104*J104 -> 1489.2 | AO104: 146 | AP104: pcs | AQ104: WHLU5810690 | AR104: 45660 | AS104: 030F500040 | AT104: 45674 | AU104: 22/01/2025 | AV104: 40HQ | AW104: WAN HAI 371/S011
A105: 12 | B105: 5401101000 | C105: 540239 | D105: 92120-04-Green Salamander-绿色蝾螈 | E105: 604#1008粉色强力线 | F105: 604#1008 pink strong thread | I105: KGM | J105: 1.6 | K105: 10 | L105: pcs | P105: 62.5 | Q105: =P105*J105 -> 100 | T105: 1.6 | V105: 1.6 | Z105: 10 | AL105: =P105*1.02 -> 63.75 | AM105: =AL105*J105 -> 102 | AO105: 10 | AP105: pcs | AQ105: WHLU5810690 | AR105: 45660 | AS105: 030F500040 | AT105: 45674 | AU105: 22/01/2025 | AV105: 40HQ | AW105: WAN HAI 371/S011
...

Sheet 类别金额
A3: 序号 | B3: 类别 | C3: 金额
B4: 水口料 | C4: =SUMIFS('5.21出货明细'!AA:AA,'5.21出货明细'!I:I,B4) -> 0
B5: 色粉 | C5: =SUMIFS('5.21出货明细'!AA:AA,'5.21出货明细'!I:I,B5) -> 0
B6: 化学品 | C6: =SUMIFS('5.21出货明细'!AA:AA,'5.21出货明细'!I:I,B6) -> 0
B7: 原料 | C7: =SUMIFS('5.21出货明细'!AA:AA,'5.21出货明细'!I:I,B7) -> 0
B8: 电子类 | C8: =SUMIFS('5.21出货明细'!AA:AA,'5.21出货明细'!I:I,B8) -> 0
B9: 塑胶 | C9: =SUMIFS('5.21出货明细'!AA:AA,'5.21出货明细'!I:I,B9) -> 1411.8
B10: 搪胶 | C10: =SUMIFS('5.21出货明细'!AA:AA,'5.21出货明细'!I:I,B10) -> 0
B11: 五金 | C11: =SUMIFS('5.21出货明细'!AA:AA,'5.21出货明细'!I:I,B11) -> 0
B12: 电池 | C12: =SUMIFS('5.21出货明细'!AA:AA,'5.21出货明细'!I:I,B12) -> 0
B13: 吸塑 | C13: =SUMIFS('5.21出货明细'!AA:AA,'5.21出货明细'!I:I,B13) -> 0
B14: 胶袋 | C14: =SUMIFS('5.21出货明细'!AA:AA,'5.21出货明细'!I:I,B14) -> 0
B15: 利宝说明书 | C15: =SUMIFS('5.21出货明细'!AA:AA,'5.21出货明细'!I:I,B15) -> 0
... B25: 注塑模具 | C25: =SUMIFS('5.21出货明细'!AA:AA,'5.21出货明细'!I:I,B25) -> 0
B26: 签办
C27: =SUM(C4:C26) -> 1411.8

Sheet 实业合同
B1: 華登製品實業有限公司
B2: (ROYAL REGENT PRODUCTS INDUSTRIES LIMITED)
B3: 购销合同 Purchase Contract
B5: 买方: The Buyers: | C5: 華登製品實業有限公司 | G5: 合同编码： No.: | H5: RPIRRI260276
C6: ROYAL REGENT PRODUCTS INDUSTRIES LIMITED
C7: 九龍尖沙咀科学馆道1号康宏广场南座12楼07-08室
C8: Unit 07-08,12/F,Greenfield Tower,Concordia Plaza,No.1 Science Museum Road,Tsim Sha Tsui,Kowloon,Postal Code:999077,Hong Kong TEL: 00852-2425 0720 FAX: 00852-2424 3407 EMAIL: chloe@royalregenthk.com Attention: Ms Tang
G9: 签定日期： Date: | H9: 46076
B11: 卖方: The Sellers: | C11: 深圳市华胜益出口贸易有限公司
C12: SHENZHEN HUASHENGYI EXPORT TRADING LIMITED
C13: 深圳市龙华区大浪街道龙胜社区龙胜综合服务大楼602 Room 602, Longsheng Comprehensive Service Building, Longsheng Community, Dalang Street, Longhua District, Shenzhen City,Postal Code518083, China TEL: 0755-27745367 Email: liuyan@hanson2.com ATTN: Peng yuqiang | G13: 签定地点： Signed at: | H13: SHENZHEN
B15: The Consignee: | C15: PT. ROYAL REGENT INDONESIA
C16: KAWASAN INDUSTRI KENDAL, JL. WANAMARTA RAYA NO 33A & 35, BRANGSONG, BRANGSONG, KAB. KENDAL, JAWA TENGAH, 51371, INDONESIA
C17: Tel.: 62 895-3269-82429 Email: exim@royalregentid.com，exim2@royalregentid.com，exim3@royalregentid.com
C18: Attention: Novi Azka Tiurlan Putri Marpaung
B19: 经甲乙双方确认，根据下列条款订立本合同：
B20: The undersigned Sellers and Buyers have confirmed this contrasct in accordance with theterms and conditions stipulated below:
B22: 型 号 Item No. | C22: 品名描述 Names and Descriptions | D22: 數量 Quantities | E22: 單位 Unit | F22: 單價 Unit Price | G22: 金額 Amount | H22: 備註
F23: FOB IDSRG,Semarang
A24: 1 | B24: {=LOOKUP(1,0/(('5.21出货明细'!V:V=$H$5)*('5.21出货明细'!A:A=A24)),'5.21出货明细'!D:D)} -> #N/A | C24: {=LOOKUP(1,0/(('5.21出货明细'!V:V=$H$5)*('5.21出货明细'!A:A=A24)),'5.21出货明细'!G:G&'5.21出货明细'!F:F)} -> #N/A | D24: {=LOOKUP(1,0/(('5.21出货明细'!V:V=$H$5)*('5.21出货明细'!A:A=A24)),'5.21出货明细'!K:K)} -> #N/A | E24: {=LOOKUP(1,0/(('5.21出货明细'!V:V=$H$5)*('5.21出货明细'!A:A=A24)),'5.21出货明细'!J:J)} -> #N/A | F24: {=LOOKUP(1,0/(('5.21出货明细'!V:V=$H$5)*('5.21出货明细'!A:A=A24)),'5.21出货明细'!Z:Z)} -> #N/A | G24: =F24*D24 -> #N/A
A25: 2 | B25: {=LOOKUP(1,0/(('5.21出货明细'!V:V=$H$5)*('5.21出货明细'!A:A=A25)),'5.21出货明细'!D:D)} -> #N/A | C25: {=LOOKUP(1,0/(('5.21出货明细'!V:V=$H$5)*('5.21出货明细'!A:A=A25)),'5.21出货明细'!G:G&'5.21出货明细'!F:F)} -> #N/A | D25: {=LOOKUP(1,0/(('5.21出货明细'!V:V=$H$5)*('5.21出货明细'!A:A=A25)),'5.21出货明细'!K:K)} -> #N/A | E25: {=LOOKUP(1,0/(('5.21出货明细'!V:V=$H$5)*('5.21出货明细'!A:A=A25)),'5.21出货明细'!J:J)} -> #N/A | F25: {=LOOKUP(1,0/(('5.21出货明细'!V:V=$H$5)*('5.21出货明细'!A:A=A25)),'5.21出货明细'!Z:Z)} -> #N/A | G25: =F25*D25 -> #N/A
A26: 3 | B26: {=LOOKUP(1,0/(('5.21出货明细'!V:V=$H$5)*('5.21出货明细'!A:A=A26)),'5.21出货明细'!D:D)} -> #N/A | C26: {=LOOKUP(1,0/(('5.21出货明细'!V:V=$H$5)*('5.21出货明细'!A:A=A26)),'5.21出货明细'!G:G&'5.21出货明细'!F:F)} -> #N/A | D26: {=LOOKUP(1,0/(('5.21出货明细'!V:V=$H$5)*('5.21出货明细'!A:A=A26)),'5.21出货明细'!K:K)} -> #N/A | E26: {=LOOKUP(1,0/(('5.21出货明细'!V:V=$H$5)*('5.21出货明细'!A:A=A26)),'5.21出货明细'!J:J)} -> #N/A | F26: {=LOOKUP(1,0/(('5.21出货明细'!V:V=$H$5)*('5.21出货明细'!A:A=A26)),'5.21出货明细'!Z:Z)} -> #N/A | G26: =F26*D26 -> #N/A
A27: 4 | B27: {=LOOKUP(1,0/(('5.21出货明细'!V:V=$H$5)*('5.21出货明细'!A:A=A27)),'5.21出货明细'!D:D)} -> #N/A | C27: {=LOOKUP(1,0/(('5.21出货明细'!V:V=$H$5)*('5.21出货明细'!A:A=A27)),'5.21出货明细'!G:G&'5.21出货明细'!F:F)} -> #N/A | D27: {=LOOKUP(1,0/(('5.21出货明细'!V:V=$H$5)*('5.21出货明细'!A:A=A27)),'5.21出货明细'!K:K)} -> #N/A | E27: {=LOOKUP(1,0/(('5.21出货明细'!V:V=$H$5)*('5.21出货明细'!A:A=A27)),'5.21出货明细'!J:J)} -> #N/A | F27: {=LOOKUP(1,0/(('5.21出货明细'!V:V=$H$5)*('5.21出货明细'!A:A=A27)),'5.21出货明细'!Z:Z)} -> #N/A | G27: =F27*D27 -> #N/A
A28: 5 | B28: {=LOOKUP(1,0/(('5.21出货明细'!V:V=$H$5)*('5.21出货明细'!A:A=A28)),'5.21出货明细'!D:D)} -> #N/A | C28: {=LOOKUP(1,0/(('5.21出货明细'!V:V=$H$5)*('5.21出货明细'!A:A=A28)),'5.21出货明细'!G:G&'5.21出货明细'!F:F)} -> #N/A | D28: {=LOOKUP(1,0/(('5.21出货明细'!V:V=$H$5)*('5.21出货明细'!A:A=A28)),'5.21出货明细'!K:K)} -> #N/A | E28: {=LOOKUP(1,0/(('5.21出货明细'!V:V=$H$5)*('5.21出货明细'!A:A=A28)),'5.21出货明细'!J:J)} -> #N/A | F28: {=LOOKUP(1,0/(('5.21出货明细'!V:V=$H$5)*('5.21出货明细'!A:A=A28)),'5.21出货明细'!Z:Z)} -> #N/A | G28: =F28*D28 -> #N/A
A29: 6 | B29: {=LOOKUP(1,0/(('5.21出货明细'!V:V=$H$5)*('5.21出货明细'!A:A=A29)),'5.21出货明细'!D:D)} -> #N/A | C29: {=LOOKUP(1,0/(('5.21出货明细'!V:V=$H$5)*('5.21出货明细'!A:A=A29)),'5.21出货明细'!G:G&'5.21出货明细'!F:F)} -> #N/A | D29: {=LOOKUP(1,0/(('5.21出货明细'!V:V=$H$5)*('5.21出货明细'!A:A=A29)),'5.21出货明细'!K:K)} -> #N/A | E29: {=LOOKUP(1,0/(('5.21出货明细'!V:V=$H$5)*('5.21出货明细'!A:A=A29)),'5.21出货明细'!J:J)} -> #N/A | F29: {=LOOKUP(1,0/(('5.21出货明细'!V:V=$H$5)*('5.21出货明细'!A:A=A29)),'5.21出货明细'!Z:Z)} -> #N/A | G29: =F29*D29 -> #N/A
A30: 7 | B30: {=LOOKUP(1,0/(('5.21出货明细'!V:V=$H$5)*('5.21出货明细'!A:A=A30)),'5.21出货明细'!D:D)} -> #N/A | C30: {=LOOKUP(1,0/(('5.21出货明细'!V:V=$H$5)*('5.21出货明细'!A:A=A30)),'5.21出货明细'!G:G&'5.21出货明细'!F:F)} -> #N/A | D30: {=LOOKUP(1,0/(('5.21出货明细'!V:V=$H$5)*('5.21出货明细'!A:A=A30)),'5.21出货明细'!K:K)} -> #N/A | E30: {=LOOKUP(1,0/(('5.21出货明细'!V:V=$H$5)*('5.21出货明细'!A:A=A30)),'5.21出货明细'!J:J)} -> #N/A | F30: {=LOOKUP(1,0/(('5.21出货明细'!V:V=$H$5)*('5.21出货明细'!A:A=A30)),'5.21出货明细'!Z:Z)} -> #N/A | G30: =F30*D30 -> #N/A
A31: 8 | B31: {=LOOKUP(1,0/(('5.21出货明细'!V:V=$H$5)*('5.21出货明细'!A:A=A31)),'5.21出货明细'!D:D)} -> #N/A | C31: {=LOOKUP(1,0/(('5.21出货明细'!V:V=$H$5)*('5.21出货明细'!A:A=A31)),'5.21出货明细'!G:G&'5.21出货明细'!F:F)} -> #N/A | D31: {=LOOKUP(1,0/(('5.21出货明细'!V:V=$H$5)*('5.21出货明细'!A:A=A31)),'5.21出货明细'!K:K)} -> #N/A | E31: {=LOOKUP(1,0/(('5.21出货明细'!V:V=$H$5)*('5.21出货明细'!A:A=A31)),'5.21出货明细'!J:J)} -> #N/A | F31: {=LOOKUP(1,0/(('5.21出货明细'!V:V=$H$5)*('5.21出货明细'!A:A=A31)),'5.21出货明细'!Z:Z)} -> #N/A | G31: =F31*D31 -> #N/A
A32: 9 | B32: {=LOOKUP(1,0/(('5.21出货明细'!V:V=$H$5)*('5.21出货明细'!A:A=A32)),'5.21出货明细'!D:D)} -> #N/A | C32: {=LOOKUP(1,0/(('5.21出货明细'!V:V=$H$5)*('5.21出货明细'!A:A=A32)),'5.21出货明细'!G:G&'5.21出货明细'!F:F)} -> #N/A | D32: {=LOOKUP(1,0/(('5.21出货明细'!V:V=$H$5)*('5.21出货明细'!A:A=A32)),'5.21出货明细'!K:K)} -> #N/A | E32: {=LOOKUP(1,0/(('5.21出货明细'!V:V=$H$5)*('5.21出货明细'!A:A=A32)),'5.21出货明细'!J:J)} -> #N/A | F32: {=LOOKUP(1,0/(('5.21出货明细'!V:V=$H$5)*('5.21出货明细'!A:A=A32)),'5.21出货明细'!Z:Z)} -> #N/A | G32: =F32*D32 -> #N/A
A33: 10 | B33: {=LOOKUP(1,0/(('5.21出货明细'!V:V=$H$5)*('5.21出货明细'!A:A=A33)),'5.21出货明细'!D:D)} -> #N/A | C33: {=LOOKUP(1,0/(('5.21出货明细'!V:V=$H$5)*('5.21出货明细'!A:A=A33)),'5.21出货明细'!G:G&'5.21出货明细'!F:F)} -> #N/A | D33: {=LOOKUP(1,0/(('5.21出货明细'!V:V=$H$5)*('5.21出货明细'!A:A=A33)),'5.21出货明细'!K:K)} -> #N/A | E33: {=LOOKUP(1,0/(('5.21出货明细'!V:V=$H$5)*('5.21出货明细'!A:A=A33)),'5.21出货明细'!J:J)} -> #N/A | F33: {=LOOKUP(1,0/(('5.21出货明细'!V:V=$H$5)*('5.21出货明细'!A:A=A33)),'5.21出货明细'!Z:Z)} -> #N/A | G33: =F33*D33 -> #N/A
A34: 11 | B34: {=LOOKUP(1,0/(('5.21出货明细'!V:V=$H$5)*('5.21出货明细'!A:A=A34)),'5.21出货明细'!D:D)} -> #N/A | C34: {=LOOKUP(1,0/(('5.21出货明细'!V:V=$H$5)*('5.21出货明细'!A:A=A34)),'5.21出货明细'!G:G&'5.21出货明细'!F:F)} -> #N/A | D34: {=LOOKUP(1,0/(('5.21出货明细'!V:V=$H$5)*('5.21出货明细'!A:A=A34)),'5.21出货明细'!K:K)} -> #N/A | E34: {=LOOKUP(1,0/(('5.21出货明细'!V:V=$H$5)*('5.21出货明细'!A:A=A34)),'5.21出货明细'!J:J)} -> #N/A | F34: {=LOOKUP(1,0/(('5.21出货明细'!V:V=$H$5)*('5.21出货明细'!A:A=A34)),'5.21出货明细'!Z:Z)} -> #N/A | G34: =F34*D34 -> #N/A
A35: 12 | B35: {=LOOKUP(1,0/(('5.21出货明细'!V:V=$H$5)*('5.21出货明细'!A:A=A35)),'5.21出货明细'!D:D)} -> #N/A | C35: {=LOOKUP(1,0/(('5.21出货明细'!V:V=$H$5)*('5.21出货明细'!A:A=A35)),'5.21出货明细'!G:G&'5.21出货明细'!F:F)} -> #N/A | D35: {=LOOKUP(1,0/(('5.21出货明细'!V:V=$H$5)*('5.21出货明细'!A:A=A35)),'5.21出货明细'!K:K)} -> #N/A | E35: {=LOOKUP(1,0/(('5.21出货明细'!V:V=$H$5)*('5.21出货明细'!A:A=A35)),'5.21出货明细'!J:J)} -> #N/A | F35: {=LOOKUP(1,0/(('5.21出货明细'!V:V=$H$5)*('5.21出货明细'!A:A=A35)),'5.21出货明细'!Z:Z)} -> #N/A | G35: =F35*D35 -> #N/A
... A41: 18 | B41: {=LOOKUP(1,0/(('5.21出货明细'!V:V=$H$5)*('5.21出货明细'!A:A=A41)),'5.21出货明细'!D:D)} -> #N/A | C41: {=LOOKUP(1,0/(('5.21出货明细'!V:V=$H$5)*('5.21出货明细'!A:A=A41)),'5.21出货明细'!G:G&'5.21出货明细'!F:F)} -> #N/A | D41: {=LOOKUP(1,0/(('5.21出货明细'!V:V=$H$5)*('5.21出货明细'!A:A=A41)),'5.21出货明细'!K:K)} -> #N/A | E41: {=LOOKUP(1,0/(('5.21出货明细'!V:V=$H$5)*('5.21出货明细'!A:A=A41)),'5.21出货明细'!J:J)} -> #N/A | F41: {=LOOKUP(1,0/(('5.21出货明细'!V:V=$H$5)*('5.21出货明细'!A:A=A41)),'5.21出货明细'!Z:Z)} -> #N/A | G41: =F41*D41 -> #N/A
G42: =SUM(G24:G41) -> #N/A
B44: 交貨日期: | C44: BEFORE April.24,2026
B45: 1.成交价格术语：Terms: | C45: FOB IDSRG,Semarang
B46: 2.运输起讫： | C46: FROM SHENZHEN,CHINA TO ID (从中国深圳到印尼)
B47: 3.装运期： Shipment date: | C47: BEFORE May.1,2026 | E47: 运输方式： Transport: | G47: BY SEA
B48: 4.付款条件： Terms of payment: | C48: T/T
B49: 5.本合同共 2 份，自双方代表签字（盖章）之日生效。
B50: This contract is in TWO copies, effective since being signed / sealed by both parties.
B52: 买方: The buyers: | C52: 華登製品實業有限公司 ROYAL REGENT PRODUCTS INDUSTRIES LIMITED | D52: 卖方: The Sellers: | E52: 深圳市华胜益出口贸易有限公司 SHENZHEN HUASHENGYI EXPORT TRADING LIMITED
B53: 签字： Authorized signiture: | D53: 签字： Authorized signiture:
B56: 華登製品實業有限公司
B57: (ROYAL REGENT PRODUCTS INDUSTRIES LIMITED)
B58: 购销合同 Purchase Contract
B60: 买方: The Buyers: | C60: 華登製品實業有限公司 | G60: 合同编码： No.: | H60: RPIRRI260277
C61: ROYAL REGENT PRODUCTS INDUSTRIES LIMITED
C62: 九龍尖沙咀科学馆道1号康宏广场南座12楼07-08室
C63: Unit 07-08,12/F,Greenfield Tower,Concordia Plaza,No.1 Science Museum Road,Tsim Sha Tsui,Kowloon,Postal Code:999077,Hong Kong TEL: 00852-2425 0720 FAX: 00852-2424 3407 EMAIL: chloe@royalregenthk.com Attention: Ms Tang
G64: 签定日期： Date: | H64: =H9 -> 46076
B66: 卖方: The Sellers: | C66: 东莞市台聚印刷有限公司
C67: Dongguan Taiju Printing Co., Ltd.
C68: 东莞市台聚印刷有限公司 东莞市清溪镇浮岗环卫街一号 No.1, Fugang Environmental Sanitation Street, Qingxi Dongguan City TEL:13509004749 Email: taijuys@vip.163.com ATTN: Zhao HongBin | G68: 签定地点： Signed at: | H68: DONGGUAN
B70: The Consignee: | C70: PT. ROYAL REGENT INDONESIA
C71: KAWASAN INDUSTRI KENDAL, JL. WANAMARTA RAYA NO 33A & 35, BRANGSONG, BRANGSONG, KAB. KENDAL, JAWA TENGAH, 51371, INDONESIA
C72: Tel.: 62 895-3269-82429 Email: exim@royalregentid.com，exim2@royalregentid.com，exim3@royalregentid.com
C73: Attention: Novi Azka Tiurlan Putri Marpaung
B74: 经甲乙双方确认，根据下列条款订立本合同：
B75: The undersigned Sellers and Buyers have confirmed this contrasct in accordance with theterms and conditions stipulated below:
B77: 型 号 Item No. | C77: 品名描述 Names and Descriptions | D77: 數量 Quantities | E77: 單位 Unit | F77: 單價 Unit Price | G77: 金額 Amount | H77: 備註
F78: CIF IDSRG,Semarang
A79: 19 | B79: {=LOOKUP(1,0/(('5.21出货明细'!V:V=$H$60)*('5.21出货明细'!A:A=A79)),'5.21出货明细'!D:D)} -> #N/A | C79: {=LOOKUP(1,0/(('5.21出货明细'!V:V=$H$60)*('5.21出货明细'!A:A=A79)),'5.21出货明细'!G:G&'5.21出货明细'!F:F)} -> #N/A | D79: {=LOOKUP(1,0/(('5.21出货明细'!V:V=$H$60)*('5.21出货明细'!A:A=A79)),'5.21出货明细'!K:K)} -> #N/A | E79: {=LOOKUP(1,0/(('5.21出货明细'!V:V=$H$60)*('5.21出货明细'!A:A=A79)),'5.21出货明细'!J:J)} -> #N/A | F79: {=LOOKUP(1,0/(('5.21出货明细'!V:V=$H$60)*('5.21出货明细'!A:A=A79)),'5.21出货明细'!Z:Z)} -> #N/A | G79: =F79*D79 -> #N/A
A80: 20 | B80: {=LOOKUP(1,0/(('5.21出货明细'!V:V=$H$60)*('5.21出货明细'!A:A=A80)),'5.21出货明细'!D:D)} -> #N/A | C80: {=LOOKUP(1,0/(('5.21出货明细'!V:V=$H$60)*('5.21出货明细'!A:A=A80)),'5.21出货明细'!G:G&'5.21出货明细'!F:F)} -> #N/A | D80: {=LOOKUP(1,0/(('5.21出货明细'!V:V=$H$60)*('5.21出货明细'!A:A=A80)),'5.21出货明细'!K:K)} -> #N/A | E80: {=LOOKUP(1,0/(('5.21出货明细'!V:V=$H$60)*('5.21出货明细'!A:A=A80)),'5.21出货明细'!J:J)} -> #N/A | F80: {=LOOKUP(1,0/(('5.21出货明细'!V:V=$H$60)*('5.21出货明细'!A:A=A80)),'5.21出货明细'!Z:Z)} -> #N/A | G80: =F80*D80 -> #N/A
A81: 21 | B81: {=LOOKUP(1,0/(('5.21出货明细'!V:V=$H$60)*('5.21出货明细'!A:A=A81)),'5.21出货明细'!D:D)} -> #N/A | C81: {=LOOKUP(1,0/(('5.21出货明细'!V:V=$H$60)*('5.21出货明细'!A:A=A81)),'5.21出货明细'!G:G&'5.21出货明细'!F:F)} -> #N/A | D81: {=LOOKUP(1,0/(('5.21出货明细'!V:V=$H$60)*('5.21出货明细'!A:A=A81)),'5.21出货明细'!K:K)} -> #N/A | E81: {=LOOKUP(1,0/(('5.21出货明细'!V:V=$H$60)*('5.21出货明细'!A:A=A81)),'5.21出货明细'!J:J)} -> #N/A | F81: {=LOOKUP(1,0/(('5.21出货明细'!V:V=$H$60)*('5.21出货明细'!A:A=A81)),'5.21出货明细'!Z:Z)} -> #N/A | G81: =F81*D81 -> #N/A
A82: 22 | B82: {=LOOKUP(1,0/(('5.21出货明细'!V:V=$H$60)*('5.21出货明细'!A:A=A82)),'5.21出货明细'!D:D)} -> #N/A | C82: {=LOOKUP(1,0/(('5.21出货明细'!V:V=$H$60)*('5.21出货明细'!A:A=A82)),'5.21出货明细'!G:G&'5.21出货明细'!F:F)} -> #N/A | D82: {=LOOKUP(1,0/(('5.21出货明细'!V:V=$H$60)*('5.21出货明细'!A:A=A82)),'5.21出货明细'!K:K)} -> #N/A | E82: {=LOOKUP(1,0/(('5.21出货明细'!V:V=$H$60)*('5.21出货明细'!A:A=A82)),'5.21出货明细'!J:J)} -> #N/A | F82: {=LOOKUP(1,0/(('5.21出货明细'!V:V=$H$60)*('5.21出货明细'!A:A=A82)),'5.21出货明细'!Z:Z)} -> #N/A | G82: =F82*D82 -> #N/A
A83: 23 | B83: {=LOOKUP(1,0/(('5.21出货明细'!V:V=$H$60)*('5.21出货明细'!A:A=A83)),'5.21出货明细'!D:D)} -> #N/A | C83: {=LOOKUP(1,0/(('5.21出货明细'!V:V=$H$60)*('5.21出货明细'!A:A=A83)),'5.21出货明细'!G:G&'5.21出货明细'!F:F)} -> #N/A | D83: {=LOOKUP(1,0/(('5.21出货明细'!V:V=$H$60)*('5.21出货明细'!A:A=A83)),'5.21出货明细'!K:K)} -> #N/A | E83: {=LOOKUP(1,0/(('5.21出货明细'!V:V=$H$60)*('5.21出货明细'!A:A=A83)),'5.21出货明细'!J:J)} -> #N/A | F83: {=LOOKUP(1,0/(('5.21出货明细'!V:V=$H$60)*('5.21出货明细'!A:A=A83)),'5.21出货明细'!Z:Z)} -> #N/A | G83: =F83*D83 -> #N/A
A84: 24 | B84: {=LOOKUP(1,0/(('5.21出货明细'!V:V=$H$60)*('5.21出货明细'!A:A=A84)),'5.21出货明细'!D:D)} -> #N/A | C84: {=LOOKUP(1,0/(('5.21出货明细'!V:V=$H$60)*('5.21出货明细'!A:A=A84)),'5.21出货明细'!G:G&'5.21出货明细'!F:F)} -> #N/A | D84: {=LOOKUP(1,0/(('5.21出货明细'!V:V=$H$60)*('5.21出货明细'!A:A=A84)),'5.21出货明细'!K:K)} -> #N/A | E84: {=LOOKUP(1,0/(('5.21出货明细'!V:V=$H$60)*('5.21出货明细'!A:A=A84)),'5.21出货明细'!J:J)} -> #N/A | F84: {=LOOKUP(1,0/(('5.21出货明细'!V:V=$H$60)*('5.21出货明细'!A:A=A84)),'5.21出货明细'!Z:Z)} -> #N/A | G84: =F84*D84 -> #N/A
A85: 25 | B85: {=LOOKUP(1,0/(('5.21出货明细'!V:V=$H$60)*('5.21出货明细'!A:A=A85)),'5.21出货明细'!D:D)} -> #N/A | C85: {=LOOKUP(1,0/(('5.21出货明细'!V:V=$H$60)*('5.21出货明细'!A:A=A85)),'5.21出货明细'!G:G&'5.21出货明细'!F:F)} -> #N/A | D85: {=LOOKUP(1,0/(('5.21出货明细'!V:V=$H$60)*('5.21出货明细'!A:A=A85)),'5.21出货明细'!K:K)} -> #N/A | E85: {=LOOKUP(1,0/(('5.21出货明细'!V:V=$H$60)*('5.21出货明细'!A:A=A85)),'5.21出货明细'!J:J)} -> #N/A | F85: {=LOOKUP(1,0/(('5.21出货明细'!V:V=$H$60)*('5.21出货明细'!A:A=A85)),'5.21出货明细'!Z:Z)} -> #N/A | G85: =F85*D85 -> #N/A
A86: 26 | B86: {=LOOKUP(1,0/(('5.21出货明细'!V:V=$H$60)*('5.21出货明细'!A:A=A86)),'5.21出货明细'!D:D)} -> #N/A | C86: {=LOOKUP(1,0/(('5.21出货明细'!V:V=$H$60)*('5.21出货明细'!A:A=A86)),'5.21出货明细'!G:G&'5.21出货明细'!F:F)} -> #N/A | D86: {=LOOKUP(1,0/(('5.21出货明细'!V:V=$H$60)*('5.21出货明细'!A:A=A86)),'5.21出货明细'!K:K)} -> #N/A | E86: {=LOOKUP(1,0/(('5.21出货明细'!V:V=$H$60)*('5.21出货明细'!A:A=A86)),'5.21出货明细'!J:J)} -> #N/A | F86: {=LOOKUP(1,0/(('5.21出货明细'!V:V=$H$60)*('5.21出货明细'!A:A=A86)),'5.21出货明细'!Z:Z)} -> #N/A | G86: =F86*D86 -> #N/A
A87: 27 | B87: {=LOOKUP(1,0/(('5.21出货明细'!V:V=$H$60)*('5.21出货明细'!A:A=A87)),'5.21出货明细'!D:D)} -> #N/A | C87: {=LOOKUP(1,0/(('5.21出货明细'!V:V=$H$60)*('5.21出货明细'!A:A=A87)),'5.21出货明细'!G:G&'5.21出货明细'!F:F)} -> #N/A | D87: {=LOOKUP(1,0/(('5.21出货明细'!V:V=$H$60)*('5.21出货明细'!A:A=A87)),'5.21出货明细'!K:K)} -> #N/A | E87: {=LOOKUP(1,0/(('5.21出货明细'!V:V=$H$60)*('5.21出货明细'!A:A=A87)),'5.21出货明细'!J:J)} -> #N/A | F87: {=LOOKUP(1,0/(('5.21出货明细'!V:V=$H$60)*('5.21出货明细'!A:A=A87)),'5.21出货明细'!Z:Z)} -> #N/A | G87: =F87*D87 -> #N/A
A88: 28 | B88: {=LOOKUP(1,0/(('5.21出货明细'!V:V=$H$60)*('5.21出货明细'!A:A=A88)),'5.21出货明细'!D:D)} -> #N/A | C88: {=LOOKUP(1,0/(('5.21出货明细'!V:V=$H$60)*('5.21出货明细'!A:A=A88)),'5.21出货明细'!G:G&'5.21出货明细'!F:F)} -> #N/A | D88: {=LOOKUP(1,0/(('5.21出货明细'!V:V=$H$60)*('5.21出货明细'!A:A=A88)),'5.21出货明细'!K:K)} -> #N/A | E88: {=LOOKUP(1,0/(('5.21出货明细'!V:V=$H$60)*('5.21出货明细'!A:A=A88)),'5.21出货明细'!J:J)} -> #N/A | F88: {=LOOKUP(1,0/(('5.21出货明细'!V:V=$H$60)*('5.21出货明细'!A:A=A88)),'5.21出货明细'!Z:Z)} -> #N/A | G88: =F88*D88 -> #N/A
A89: 29 | B89: {=LOOKUP(1,0/(('5.21出货明细'!V:V=$H$60)*('5.21出货明细'!A:A=A89)),'5.21出货明细'!D:D)} -> #N/A | C89: {=LOOKUP(1,0/(('5.21出货明细'!V:V=$H$60)*('5.21出货明细'!A:A=A89)),'5.21出货明细'!G:G&'5.21出货明细'!F:F)} -> #N/A | D89: {=LOOKUP(1,0/(('5.21出货明细'!V:V=$H$60)*('5.21出货明细'!A:A=A89)),'5.21出货明细'!K:K)} -> #N/A | E89: {=LOOKUP(1,0/(('5.21出货明细'!V:V=$H$60)*('5.21出货明细'!A:A=A89)),'5.21出货明细'!J:J)} -> #N/A | F89: {=LOOKUP(1,0/(('5.21出货明细'!V:V=$H$60)*('5.21出货明细'!A:A=A89)),'5.21出货明细'!Z:Z)} -> #N/A | G89: =F89*D89 -> #N/A
G90: =SUM(G79:G89) -> #N/A
B92: 交貨日期: | C92: BEFORE April.24,2026
B93: 1.成交价格术语：Terms: | C93: CIF IDSRG,Semarang
B94: 2.运输起讫： | C94: FROM SHENZHEN,CHINA TO ID (从中国深圳到印尼)
B95: 3.装运期： Shipment date: | C95: BEFORE May.1,2026 | E95: 运输方式： Transport: | G95: BY SEA
B96: 4.付款条件： Terms of payment: | C96: T/T
B97: 5.本合同共 2 份，自双方代表签字（盖章）之日生效。
B98: This contract is in TWO copies, effective since being signed / sealed by both parties.
B100: 买方: The buyers: | C100: 華登製品實業有限公司 ROYAL REGENT PRODUCTS INDUSTRIES LIMITED | D100: 卖方: The Sellers: | E100: 东莞市台聚印刷有限公司 Dongguan Taiju Printing Co., Ltd.
B101: 签字： Authorized signiture: | D101: 签字： Authorized signiture:
B103: 華登製品實業有限公司
B104: (ROYAL REGENT PRODUCTS INDUSTRIES LIMITED)
B105: 购销合同 Purchase Contract
B107: 买方: The Buyers: | C107: 華登製品實業有限公司 | G107: 合同编码： No.: | H107: RPIRRI260278
C108: ROYAL REGENT PRODUCTS INDUSTRIES LIMITED
C109: 九龍尖沙咀科学馆道1号康宏广场南座12楼07-08室
C110: Unit 07-08,12/F,Greenfield Tower,Concordia Plaza,No.1 Science Museum Road,Tsim Sha Tsui,Kowloon,Postal Code:999077,Hong Kong TEL: 00852-2425 0720 FAX: 00852-2424 3407 EMAIL: chloe@royalregenthk.com Attention: Ms Tang
G111: 签定日期： Date: | H111: =H9 -> 46076
B113: 卖方: The Sellers: | C113: 东莞兴信塑胶制品有限公司
C114: Dong Guan Hanson Plastic Product Ltd.
C115: 广东省东莞省清溪镇上元村银坑路59号 Yin keng Road 59,Shangyuan Village, Qingxi Town, Dongguan City, Guangdong Province, Postal Code523640, China TEL:0769-87312864 EMAIL:luo@hanson2.com Attention: Mr Luo | G115: 签定地点： Signed at: | H115: DONGGUAN
B117: The Consignee: | C117: PT. ROYAL REGENT INDONESIA
C118: KAWASAN INDUSTRI KENDAL, JL. WANAMARTA RAYA NO 33A & 35, BRANGSONG, BRANGSONG, KAB. KENDAL, JAWA TENGAH, 51371, INDONESIA
C119: Tel.: 62 895-3269-82429 Email: exim@royalregentid.com，exim2@royalregentid.com，exim3@royalregentid.com
C120: Attention: Novi Azka Tiurlan Putri Marpaung
B121: 经甲乙双方确认，根据下列条款订立本合同：
B122: The undersigned Sellers and Buyers have confirmed this contrasct in accordance with theterms and conditions stipulated below:
B124: 型 号 Item No. | C124: 品名描述 Names and Descriptions | D124: 數量 Quantities | E124: 單位 Unit | F124: 單價 Unit Price | G124: 金額 Amount | H124: 備註
...

Sheet 实业发票
B1: 華登製品實業有限公司
B2: ROYAL REGENT PRODUCTS INDUSTRIES LIMITED
B3: Unit 07-08,12/F,Greenfield Tower,Concordia Plaza,No.1 Science Museum Road,Tsim Sha Tsui,Kowloon,Postal Code:999077,Hong Kong
B4: TEL: 00852-2425 0720 FAX: 00852-2424 3407 EMAIL: chloe@royalregenthk.com
B5: 商 业 发 票
B6: COMMERCIAL INVOICE
B8: 买方:
B9: The Buyers: M/S. | G9: 号码 No. | H9: PR202600276
B10: 華登製品實業有限公司
B11: Unit 07-08,12/F,Greenfield Tower,Concordia Plaza,No.1 Science Museum Road,Tsim Sha Tsui,Kowloon,Postal Code:999077,Hong Kong TEL: 00852-2425 0720 FAX: 00852-2424 3407 EMAIL: chloe@royalregenthk.com Attention: Ms Tang | G11: 日期 Date | H11: =实业合同!H9 -> 46076
B13: Consignee：M/S. | G13: 合同号 Contract No. | H13: =实业合同!H5 -> RPIRRI260276
B14: PT. ROYAL REGENT INDONESIA
B15: Tax ID: 61.146.021.3-513.000 KAWASAN INDUSTRI KENDAL, JL. WANAMARTA RAYA NO 33A & 35, BRANGSONG, BRANGSONG, KAB. KENDAL, JAWA TENGAH, 51371, INDONESIA
G16: 运输方式： | H16: BY SEA
B17: Tel.: 62 895-3269-82429 Email: exim@royalregentid.com，exim2@royalregentid.com，exim3@royalregentid.com
B18: Attention: Novi Azka Tiurlan Putri Marpaung
B19: 卖方:
B20: The Sellers: M/S.
B21: 深圳市华胜益出口贸易有限公司
B22: SHENZHEN HUASHENGYI EXPORT TRADING LIMITED
B23: 深圳市龙华区大浪街道龙胜社区龙胜综合服务大楼602 Room 602, Longsheng Comprehensive Service Building, Longsheng Community, Dalang Street, Longhua District, Shenzhen City,Postal Code518083, China TEL: 0755-27745367 Email: liuyan@hanson2.com ATTN: Peng yuqiang
B27: 装运口岸 From： | C27: SHENZHEN,CHINA(中国深圳) | F27: 目的地 To： | G27: Indonesia(印度尼西亚)
B28: 型 号 Item No. | C28: 品名描述 Names and Descriptions | D28: 单位 Unit | E28: HS Code | F28: 数 量 Quantities | G28: 单 价 Unit Price | H28: 总 值 Amount
G29: FOB IDSRG,Semarang
A30: 1 | B30: {=LOOKUP(1,0/(('5.21出货明细'!V:V=$H$13)*('5.21出货明细'!X:X=$H$9)*('5.21出货明细'!A:A=A30)),'5.21出货明细'!D:D)} -> #N/A | C30: {=LOOKUP(1,0/(('5.21出货明细'!V:V=$H$13)*('5.21出货明细'!X:X=$H$9)*('5.21出货明细'!A:A=A30)),'5.21出货明细'!G:G&'5.21出货明细'!F:F)} -> #N/A | D30: {=LOOKUP(1,0/(('5.21出货明细'!D:D=B30)*('5.21出货明细'!G:G&'5.21出货明细'!F:F=C30)),'5.21出货明细'!J:J)} -> #N/A | E30: {=LOOKUP(1,0/(('5.21出货明细'!D:D=B30)*('5.21出货明细'!G:G&'5.21出货明细'!F:F=C30)),'5.21出货明细'!C:C)} -> #N/A | F30: {=LOOKUP(1,0/(('5.21出货明细'!D:D=B30)*('5.21出货明细'!G:G&'5.21出货明细'!F:F=C30)),'5.21出货明细'!K:K)} -> #N/A | G30: {=LOOKUP(1,0/(('5.21出货明细'!D:D=B30)*('5.21出货明细'!G:G&'5.21出货明细'!F:F=C30)),'5.21出货明细'!Z:Z)} -> #N/A | H30: =G30*F30 -> #N/A
A31: 2 | B31: {=LOOKUP(1,0/(('5.21出货明细'!V:V=$H$13)*('5.21出货明细'!X:X=$H$9)*('5.21出货明细'!A:A=A31)),'5.21出货明细'!D:D)} -> #N/A | C31: {=LOOKUP(1,0/(('5.21出货明细'!V:V=$H$13)*('5.21出货明细'!X:X=$H$9)*('5.21出货明细'!A:A=A31)),'5.21出货明细'!G:G&'5.21出货明细'!F:F)} -> #N/A | D31: {=LOOKUP(1,0/(('5.21出货明细'!D:D=B31)*('5.21出货明细'!G:G&'5.21出货明细'!F:F=C31)),'5.21出货明细'!J:J)} -> #N/A | E31: {=LOOKUP(1,0/(('5.21出货明细'!D:D=B31)*('5.21出货明细'!G:G&'5.21出货明细'!F:F=C31)),'5.21出货明细'!C:C)} -> #N/A | F31: {=LOOKUP(1,0/(('5.21出货明细'!D:D=B31)*('5.21出货明细'!G:G&'5.21出货明细'!F:F=C31)),'5.21出货明细'!K:K)} -> #N/A | G31: {=LOOKUP(1,0/(('5.21出货明细'!D:D=B31)*('5.21出货明细'!G:G&'5.21出货明细'!F:F=C31)),'5.21出货明细'!Z:Z)} -> #N/A | H31: =G31*F31 -> #N/A
A32: 3 | B32: {=LOOKUP(1,0/(('5.21出货明细'!V:V=$H$13)*('5.21出货明细'!X:X=$H$9)*('5.21出货明细'!A:A=A32)),'5.21出货明细'!D:D)} -> #N/A | C32: {=LOOKUP(1,0/(('5.21出货明细'!V:V=$H$13)*('5.21出货明细'!X:X=$H$9)*('5.21出货明细'!A:A=A32)),'5.21出货明细'!G:G&'5.21出货明细'!F:F)} -> #N/A | D32: {=LOOKUP(1,0/(('5.21出货明细'!D:D=B32)*('5.21出货明细'!G:G&'5.21出货明细'!F:F=C32)),'5.21出货明细'!J:J)} -> #N/A | E32: {=LOOKUP(1,0/(('5.21出货明细'!D:D=B32)*('5.21出货明细'!G:G&'5.21出货明细'!F:F=C32)),'5.21出货明细'!C:C)} -> #N/A | F32: {=LOOKUP(1,0/(('5.21出货明细'!D:D=B32)*('5.21出货明细'!G:G&'5.21出货明细'!F:F=C32)),'5.21出货明细'!K:K)} -> #N/A | G32: {=LOOKUP(1,0/(('5.21出货明细'!D:D=B32)*('5.21出货明细'!G:G&'5.21出货明细'!F:F=C32)),'5.21出货明细'!Z:Z)} -> #N/A | H32: =G32*F32 -> #N/A
A33: 4 | B33: {=LOOKUP(1,0/(('5.21出货明细'!V:V=$H$13)*('5.21出货明细'!X:X=$H$9)*('5.21出货明细'!A:A=A33)),'5.21出货明细'!D:D)} -> #N/A | C33: {=LOOKUP(1,0/(('5.21出货明细'!V:V=$H$13)*('5.21出货明细'!X:X=$H$9)*('5.21出货明细'!A:A=A33)),'5.21出货明细'!G:G&'5.21出货明细'!F:F)} -> #N/A | D33: {=LOOKUP(1,0/(('5.21出货明细'!D:D=B33)*('5.21出货明细'!G:G&'5.21出货明细'!F:F=C33)),'5.21出货明细'!J:J)} -> #N/A | E33: {=LOOKUP(1,0/(('5.21出货明细'!D:D=B33)*('5.21出货明细'!G:G&'5.21出货明细'!F:F=C33)),'5.21出货明细'!C:C)} -> #N/A | F33: {=LOOKUP(1,0/(('5.21出货明细'!D:D=B33)*('5.21出货明细'!G:G&'5.21出货明细'!F:F=C33)),'5.21出货明细'!K:K)} -> #N/A | G33: {=LOOKUP(1,0/(('5.21出货明细'!D:D=B33)*('5.21出货明细'!G:G&'5.21出货明细'!F:F=C33)),'5.21出货明细'!Z:Z)} -> #N/A | H33: =G33*F33 -> #N/A
A34: 5 | B34: {=LOOKUP(1,0/(('5.21出货明细'!V:V=$H$13)*('5.21出货明细'!X:X=$H$9)*('5.21出货明细'!A:A=A34)),'5.21出货明细'!D:D)} -> #N/A | C34: {=LOOKUP(1,0/(('5.21出货明细'!V:V=$H$13)*('5.21出货明细'!X:X=$H$9)*('5.21出货明细'!A:A=A34)),'5.21出货明细'!G:G&'5.21出货明细'!F:F)} -> #N/A | D34: {=LOOKUP(1,0/(('5.21出货明细'!D:D=B34)*('5.21出货明细'!G:G&'5.21出货明细'!F:F=C34)),'5.21出货明细'!J:J)} -> #N/A | E34: {=LOOKUP(1,0/(('5.21出货明细'!D:D=B34)*('5.21出货明细'!G:G&'5.21出货明细'!F:F=C34)),'5.21出货明细'!C:C)} -> #N/A | F34: {=LOOKUP(1,0/(('5.21出货明细'!D:D=B34)*('5.21出货明细'!G:G&'5.21出货明细'!F:F=C34)),'5.21出货明细'!K:K)} -> #N/A | G34: {=LOOKUP(1,0/(('5.21出货明细'!D:D=B34)*('5.21出货明细'!G:G&'5.21出货明细'!F:F=C34)),'5.21出货明细'!Z:Z)} -> #N/A | H34: =G34*F34 -> #N/A
A35: 6 | B35: {=LOOKUP(1,0/(('5.21出货明细'!V:V=$H$13)*('5.21出货明细'!X:X=$H$9)*('5.21出货明细'!A:A=A35)),'5.21出货明细'!D:D)} -> #N/A | C35: {=LOOKUP(1,0/(('5.21出货明细'!V:V=$H$13)*('5.21出货明细'!X:X=$H$9)*('5.21出货明细'!A:A=A35)),'5.21出货明细'!G:G&'5.21出货明细'!F:F)} -> #N/A | D35: {=LOOKUP(1,0/(('5.21出货明细'!D:D=B35)*('5.21出货明细'!G:G&'5.21出货明细'!F:F=C35)),'5.21出货明细'!J:J)} -> #N/A | E35: {=LOOKUP(1,0/(('5.21出货明细'!D:D=B35)*('5.21出货明细'!G:G&'5.21出货明细'!F:F=C35)),'5.21出货明细'!C:C)} -> #N/A | F35: {=LOOKUP(1,0/(('5.21出货明细'!D:D=B35)*('5.21出货明细'!G:G&'5.21出货明细'!F:F=C35)),'5.21出货明细'!K:K)} -> #N/A | G35: {=LOOKUP(1,0/(('5.21出货明细'!D:D=B35)*('5.21出货明细'!G:G&'5.21出货明细'!F:F=C35)),'5.21出货明细'!Z:Z)} -> #N/A | H35: =G35*F35 -> #N/A
A36: 7 | B36: {=LOOKUP(1,0/(('5.21出货明细'!V:V=$H$13)*('5.21出货明细'!X:X=$H$9)*('5.21出货明细'!A:A=A36)),'5.21出货明细'!D:D)} -> #N/A | C36: {=LOOKUP(1,0/(('5.21出货明细'!V:V=$H$13)*('5.21出货明细'!X:X=$H$9)*('5.21出货明细'!A:A=A36)),'5.21出货明细'!G:G&'5.21出货明细'!F:F)} -> #N/A | D36: {=LOOKUP(1,0/(('5.21出货明细'!D:D=B36)*('5.21出货明细'!G:G&'5.21出货明细'!F:F=C36)),'5.21出货明细'!J:J)} -> #N/A | E36: {=LOOKUP(1,0/(('5.21出货明细'!D:D=B36)*('5.21出货明细'!G:G&'5.21出货明细'!F:F=C36)),'5.21出货明细'!C:C)} -> #N/A | F36: {=LOOKUP(1,0/(('5.21出货明细'!D:D=B36)*('5.21出货明细'!G:G&'5.21出货明细'!F:F=C36)),'5.21出货明细'!K:K)} -> #N/A | G36: {=LOOKUP(1,0/(('5.21出货明细'!D:D=B36)*('5.21出货明细'!G:G&'5.21出货明细'!F:F=C36)),'5.21出货明细'!Z:Z)} -> #N/A | H36: =G36*F36 -> #N/A
A37: 8 | B37: {=LOOKUP(1,0/(('5.21出货明细'!V:V=$H$13)*('5.21出货明细'!X:X=$H$9)*('5.21出货明细'!A:A=A37)),'5.21出货明细'!D:D)} -> #N/A | C37: {=LOOKUP(1,0/(('5.21出货明细'!V:V=$H$13)*('5.21出货明细'!X:X=$H$9)*('5.21出货明细'!A:A=A37)),'5.21出货明细'!G:G&'5.21出货明细'!F:F)} -> #N/A | D37: {=LOOKUP(1,0/(('5.21出货明细'!D:D=B37)*('5.21出货明细'!G:G&'5.21出货明细'!F:F=C37)),'5.21出货明细'!J:J)} -> #N/A | E37: {=LOOKUP(1,0/(('5.21出货明细'!D:D=B37)*('5.21出货明细'!G:G&'5.21出货明细'!F:F=C37)),'5.21出货明细'!C:C)} -> #N/A | F37: {=LOOKUP(1,0/(('5.21出货明细'!D:D=B37)*('5.21出货明细'!G:G&'5.21出货明细'!F:F=C37)),'5.21出货明细'!K:K)} -> #N/A | G37: {=LOOKUP(1,0/(('5.21出货明细'!D:D=B37)*('5.21出货明细'!G:G&'5.21出货明细'!F:F=C37)),'5.21出货明细'!Z:Z)} -> #N/A | H37: =G37*F37 -> #N/A
A38: 9 | B38: {=LOOKUP(1,0/(('5.21出货明细'!V:V=$H$13)*('5.21出货明细'!X:X=$H$9)*('5.21出货明细'!A:A=A38)),'5.21出货明细'!D:D)} -> #N/A | C38: {=LOOKUP(1,0/(('5.21出货明细'!V:V=$H$13)*('5.21出货明细'!X:X=$H$9)*('5.21出货明细'!A:A=A38)),'5.21出货明细'!G:G&'5.21出货明细'!F:F)} -> #N/A | D38: {=LOOKUP(1,0/(('5.21出货明细'!D:D=B38)*('5.21出货明细'!G:G&'5.21出货明细'!F:F=C38)),'5.21出货明细'!J:J)} -> #N/A | E38: {=LOOKUP(1,0/(('5.21出货明细'!D:D=B38)*('5.21出货明细'!G:G&'5.21出货明细'!F:F=C38)),'5.21出货明细'!C:C)} -> #N/A | F38: {=LOOKUP(1,0/(('5.21出货明细'!D:D=B38)*('5.21出货明细'!G:G&'5.21出货明细'!F:F=C38)),'5.21出货明细'!K:K)} -> #N/A | G38: {=LOOKUP(1,0/(('5.21出货明细'!D:D=B38)*('5.21出货明细'!G:G&'5.21出货明细'!F:F=C38)),'5.21出货明细'!Z:Z)} -> #N/A | H38: =G38*F38 -> #N/A
A39: 10 | B39: {=LOOKUP(1,0/(('5.21出货明细'!V:V=$H$13)*('5.21出货明细'!X:X=$H$9)*('5.21出货明细'!A:A=A39)),'5.21出货明细'!D:D)} -> #N/A | C39: {=LOOKUP(1,0/(('5.21出货明细'!V:V=$H$13)*('5.21出货明细'!X:X=$H$9)*('5.21出货明细'!A:A=A39)),'5.21出货明细'!G:G&'5.21出货明细'!F:F)} -> #N/A | D39: {=LOOKUP(1,0/(('5.21出货明细'!D:D=B39)*('5.21出货明细'!G:G&'5.21出货明细'!F:F=C39)),'5.21出货明细'!J:J)} -> #N/A | E39: {=LOOKUP(1,0/(('5.21出货明细'!D:D=B39)*('5.21出货明细'!G:G&'5.21出货明细'!F:F=C39)),'5.21出货明细'!C:C)} -> #N/A | F39: {=LOOKUP(1,0/(('5.21出货明细'!D:D=B39)*('5.21出货明细'!G:G&'5.21出货明细'!F:F=C39)),'5.21出货明细'!K:K)} -> #N/A | G39: {=LOOKUP(1,0/(('5.21出货明细'!D:D=B39)*('5.21出货明细'!G:G&'5.21出货明细'!F:F=C39)),'5.21出货明细'!Z:Z)} -> #N/A | H39: =G39*F39 -> #N/A
A40: 11 | B40: {=LOOKUP(1,0/(('5.21出货明细'!V:V=$H$13)*('5.21出货明细'!X:X=$H$9)*('5.21出货明细'!A:A=A40)),'5.21出货明细'!D:D)} -> #N/A | C40: {=LOOKUP(1,0/(('5.21出货明细'!V:V=$H$13)*('5.21出货明细'!X:X=$H$9)*('5.21出货明细'!A:A=A40)),'5.21出货明细'!G:G&'5.21出货明细'!F:F)} -> #N/A | D40: {=LOOKUP(1,0/(('5.21出货明细'!D:D=B40)*('5.21出货明细'!G:G&'5.21出货明细'!F:F=C40)),'5.21出货明细'!J:J)} -> #N/A | E40: {=LOOKUP(1,0/(('5.21出货明细'!D:D=B40)*('5.21出货明细'!G:G&'5.21出货明细'!F:F=C40)),'5.21出货明细'!C:C)} -> #N/A | F40: {=LOOKUP(1,0/(('5.21出货明细'!D:D=B40)*('5.21出货明细'!G:G&'5.21出货明细'!F:F=C40)),'5.21出货明细'!K:K)} -> #N/A | G40: {=LOOKUP(1,0/(('5.21出货明细'!D:D=B40)*('5.21出货明细'!G:G&'5.21出货明细'!F:F=C40)),'5.21出货明细'!Z:Z)} -> #N/A | H40: =G40*F40 -> #N/A
A41: 12 | B41: {=LOOKUP(1,0/(('5.21出货明细'!V:V=$H$13)*('5.21出货明细'!X:X=$H$9)*('5.21出货明细'!A:A=A41)),'5.21出货明细'!D:D)} -> #N/A | C41: {=LOOKUP(1,0/(('5.21出货明细'!V:V=$H$13)*('5.21出货明细'!X:X=$H$9)*('5.21出货明细'!A:A=A41)),'5.21出货明细'!G:G&'5.21出货明细'!F:F)} -> #N/A | D41: {=LOOKUP(1,0/(('5.21出货明细'!D:D=B41)*('5.21出货明细'!G:G&'5.21出货明细'!F:F=C41)),'5.21出货明细'!J:J)} -> #N/A | E41: {=LOOKUP(1,0/(('5.21出货明细'!D:D=B41)*('5.21出货明细'!G:G&'5.21出货明细'!F:F=C41)),'5.21出货明细'!C:C)} -> #N/A | F41: {=LOOKUP(1,0/(('5.21出货明细'!D:D=B41)*('5.21出货明细'!G:G&'5.21出货明细'!F:F=C41)),'5.21出货明细'!K:K)} -> #N/A | G41: {=LOOKUP(1,0/(('5.21出货明细'!D:D=B41)*('5.21出货明细'!G:G&'5.21出货明细'!F:F=C41)),'5.21出货明细'!Z:Z)} -> #N/A | H41: =G41*F41 -> #N/A
... A47: 18 | B47: {=LOOKUP(1,0/(('5.21出货明细'!V:V=$H$13)*('5.21出货明细'!X:X=$H$9)*('5.21出货明细'!A:A=A47)),'5.21出货明细'!D:D)} -> #N/A | C47: {=LOOKUP(1,0/(('5.21出货明细'!V:V=$H$13)*('5.21出货明细'!X:X=$H$9)*('5.21出货明细'!A:A=A47)),'5.21出货明细'!G:G&'5.21出货明细'!F:F)} -> #N/A | D47: {=LOOKUP(1,0/(('5.21出货明细'!D:D=B47)*('5.21出货明细'!G:G&'5.21出货明细'!F:F=C47)),'5.21出货明细'!J:J)} -> #N/A | E47: {=LOOKUP(1,0/(('5.21出货明细'!D:D=B47)*('5.21出货明细'!G:G&'5.21出货明细'!F:F=C47)),'5.21出货明细'!C:C)} -> #N/A | F47: {=LOOKUP(1,0/(('5.21出货明细'!D:D=B47)*('5.21出货明细'!G:G&'5.21出货明细'!F:F=C47)),'5.21出货明细'!K:K)} -> #N/A | G47: {=LOOKUP(1,0/(('5.21出货明细'!D:D=B47)*('5.21出货明细'!G:G&'5.21出货明细'!F:F=C47)),'5.21出货明细'!Z:Z)} -> #N/A | H47: =G47*F47 -> #N/A
F48: TOTAL: | G48: =SUM(H30:H47) -> #N/A
B49: 总值大写 Total Amount: | C49: =G48 -> #N/A
B50: Beneficiary name :Shenzhen Huashengyi Export Trading Limited Account number : 15668277360001(USD) 15353466270052 (RMB) 15602776290037 (HKD) Beneficiary Bank: Ping An Bank Co., Ltd Swift code : SZDBCNBSXXX | F50: Beneficiary：SHENZHEN HUASHENGYI EXPORT TRADING LIMITED
F52: Add: Room 602, Longsheng Comprehensive Service Building, Longsheng Community, Dalang Street, Longhua District, Shenzhen City
B55: 華登製品實業有限公司
B56: ROYAL REGENT PRODUCTS INDUSTRIES LIMITED
B57: Unit 07-08,12/F,Greenfield Tower,Concordia Plaza,No.1 Science Museum Road,Tsim Sha Tsui,Kowloon,Postal Code:999077,Hong Kong
B58: TEL: 00852-2425 0720 FAX: 00852-2424 3407 EMAIL: chloe@royalregenthk.com
B59: 商 业 发 票
B60: COMMERCIAL INVOICE
B62: 买方:
B63: The Buyers: M/S. | G63: 号码 No. | H63: PR202600277
B64: 華登製品實業有限公司
B65: Unit 07-08,12/F,Greenfield Tower,Concordia Plaza,No.1 Science Museum Road,Tsim Sha Tsui,Kowloon,Postal Code:999077,Hong Kong TEL: 00852-2425 0720 FAX: 00852-2424 3407 EMAIL: chloe@royalregenthk.com Attention: Ms Tang | G65: 日期 Date | H65: =实业合同!H9 -> 46076
B67: Consignee：M/S. | G67: 合同号 Contract No. | H67: =实业合同!H60 -> RPIRRI260277
B68: PT. ROYAL REGENT INDONESIA
B69: Tax ID: 61.146.021.3-513.000 KAWASAN INDUSTRI KENDAL, JL. WANAMARTA RAYA NO 33A & 35, BRANGSONG, BRANGSONG, KAB. KENDAL, JAWA TENGAH, 51371, INDONESIA
G70: 运输方式： | H70: BY SEA
B71: Tel.: 62 895-3269-82429 Email: exim@royalregentid.com，exim2@royalregentid.com，exim3@royalregentid.com
B72: Attention: Novi Azka Tiurlan Putri Marpaung
B73: 卖方:
B74: The Sellers: M/S.
B75: 东莞市台聚印刷有限公司
B76: Dongguan Taiju Printing Co., Ltd.
B77: 东莞市台聚印刷有限公司 东莞市清溪镇浮岗环卫街一号 No.1, Fugang Environmental Sanitation Street, Qingxi Dongguan City TEL:13509004749 Email: taijuys@vip.163.com ATTN: Zhao HongBin
B81: 装运口岸 From： | C81: SHENZHEN,CHINA(中国深圳) | F81: 目的地 To： | G81: Indonesia(印度尼西亚)
B82: 型 号 Item No. | C82: 品名描述 Names and Descriptions | D82: 单位 Unit | E82: HS Code | F82: 数 量 Quantities | G82: 单 价 Unit Price | H82: 总 值 Amount
G83: CIF IDSRG,Semarang
A84: 19 | B84: {=LOOKUP(1,0/(('5.21出货明细'!V:V=$H$67)*('5.21出货明细'!X:X=$H$63)*('5.21出货明细'!A:A=A84)),'5.21出货明细'!D:D)} -> #N/A | C84: {=LOOKUP(1,0/(('5.21出货明细'!V:V=$H$67)*('5.21出货明细'!X:X=$H$63)*('5.21出货明细'!A:A=A84)),'5.21出货明细'!G:G&'5.21出货明细'!F:F)} -> #N/A | D84: {=LOOKUP(1,0/(('5.21出货明细'!D:D=B84)*('5.21出货明细'!G:G&'5.21出货明细'!F:F=C84)),'5.21出货明细'!J:J)} -> #N/A | E84: {=LOOKUP(1,0/(('5.21出货明细'!D:D=B84)*('5.21出货明细'!G:G&'5.21出货明细'!F:F=C84)),'5.21出货明细'!C:C)} -> #N/A | F84: {=LOOKUP(1,0/(('5.21出货明细'!D:D=B84)*('5.21出货明细'!G:G&'5.21出货明细'!F:F=C84)),'5.21出货明细'!K:K)} -> #N/A | G84: {=LOOKUP(1,0/(('5.21出货明细'!D:D=B84)*('5.21出货明细'!G:G&'5.21出货明细'!F:F=C84)),'5.21出货明细'!Z:Z)} -> #N/A | H84: =G84*F84 -> #N/A
A85: 20 | B85: {=LOOKUP(1,0/(('5.21出货明细'!V:V=$H$67)*('5.21出货明细'!X:X=$H$63)*('5.21出货明细'!A:A=A85)),'5.21出货明细'!D:D)} -> #N/A | C85: {=LOOKUP(1,0/(('5.21出货明细'!V:V=$H$67)*('5.21出货明细'!X:X=$H$63)*('5.21出货明细'!A:A=A85)),'5.21出货明细'!G:G&'5.21出货明细'!F:F)} -> #N/A | D85: {=LOOKUP(1,0/(('5.21出货明细'!D:D=B85)*('5.21出货明细'!G:G&'5.21出货明细'!F:F=C85)),'5.21出货明细'!J:J)} -> #N/A | E85: {=LOOKUP(1,0/(('5.21出货明细'!D:D=B85)*('5.21出货明细'!G:G&'5.21出货明细'!F:F=C85)),'5.21出货明细'!C:C)} -> #N/A | F85: {=LOOKUP(1,0/(('5.21出货明细'!D:D=B85)*('5.21出货明细'!G:G&'5.21出货明细'!F:F=C85)),'5.21出货明细'!K:K)} -> #N/A | G85: {=LOOKUP(1,0/(('5.21出货明细'!D:D=B85)*('5.21出货明细'!G:G&'5.21出货明细'!F:F=C85)),'5.21出货明细'!Z:Z)} -> #N/A | H85: =G85*F85 -> #N/A
A86: 21 | B86: {=LOOKUP(1,0/(('5.21出货明细'!V:V=$H$67)*('5.21出货明细'!X:X=$H$63)*('5.21出货明细'!A:A=A86)),'5.21出货明细'!D:D)} -> #N/A | C86: {=LOOKUP(1,0/(('5.21出货明细'!V:V=$H$67)*('5.21出货明细'!X:X=$H$63)*('5.21出货明细'!A:A=A86)),'5.21出货明细'!G:G&'5.21出货明细'!F:F)} -> #N/A | D86: {=LOOKUP(1,0/(('5.21出货明细'!D:D=B86)*('5.21出货明细'!G:G&'5.21出货明细'!F:F=C86)),'5.21出货明细'!J:J)} -> #N/A | E86: {=LOOKUP(1,0/(('5.21出货明细'!D:D=B86)*('5.21出货明细'!G:G&'5.21出货明细'!F:F=C86)),'5.21出货明细'!C:C)} -> #N/A | F86: {=LOOKUP(1,0/(('5.21出货明细'!D:D=B86)*('5.21出货明细'!G:G&'5.21出货明细'!F:F=C86)),'5.21出货明细'!K:K)} -> #N/A | G86: {=LOOKUP(1,0/(('5.21出货明细'!D:D=B86)*('5.21出货明细'!G:G&'5.21出货明细'!F:F=C86)),'5.21出货明细'!Z:Z)} -> #N/A | H86: =G86*F86 -> #N/A
A87: 22 | B87: {=LOOKUP(1,0/(('5.21出货明细'!V:V=$H$67)*('5.21出货明细'!X:X=$H$63)*('5.21出货明细'!A:A=A87)),'5.21出货明细'!D:D)} -> #N/A | C87: {=LOOKUP(1,0/(('5.21出货明细'!V:V=$H$67)*('5.21出货明细'!X:X=$H$63)*('5.21出货明细'!A:A=A87)),'5.21出货明细'!G:G&'5.21出货明细'!F:F)} -> #N/A | D87: {=LOOKUP(1,0/(('5.21出货明细'!D:D=B87)*('5.21出货明细'!G:G&'5.21出货明细'!F:F=C87)),'5.21出货明细'!J:J)} -> #N/A | E87: {=LOOKUP(1,0/(('5.21出货明细'!D:D=B87)*('5.21出货明细'!G:G&'5.21出货明细'!F:F=C87)),'5.21出货明细'!C:C)} -> #N/A | F87: {=LOOKUP(1,0/(('5.21出货明细'!D:D=B87)*('5.21出货明细'!G:G&'5.21出货明细'!F:F=C87)),'5.21出货明细'!K:K)} -> #N/A | G87: {=LOOKUP(1,0/(('5.21出货明细'!D:D=B87)*('5.21出货明细'!G:G&'5.21出货明细'!F:F=C87)),'5.21出货明细'!Z:Z)} -> #N/A | H87: =G87*F87 -> #N/A
A88: 23 | B88: {=LOOKUP(1,0/(('5.21出货明细'!V:V=$H$67)*('5.21出货明细'!X:X=$H$63)*('5.21出货明细'!A:A=A88)),'5.21出货明细'!D:D)} -> #N/A | C88: {=LOOKUP(1,0/(('5.21出货明细'!V:V=$H$67)*('5.21出货明细'!X:X=$H$63)*('5.21出货明细'!A:A=A88)),'5.21出货明细'!G:G&'5.21出货明细'!F:F)} -> #N/A | D88: {=LOOKUP(1,0/(('5.21出货明细'!D:D=B88)*('5.21出货明细'!G:G&'5.21出货明细'!F:F=C88)),'5.21出货明细'!J:J)} -> #N/A | E88: {=LOOKUP(1,0/(('5.21出货明细'!D:D=B88)*('5.21出货明细'!G:G&'5.21出货明细'!F:F=C88)),'5.21出货明细'!C:C)} -> #N/A | F88: {=LOOKUP(1,0/(('5.21出货明细'!D:D=B88)*('5.21出货明细'!G:G&'5.21出货明细'!F:F=C88)),'5.21出货明细'!K:K)} -> #N/A | G88: {=LOOKUP(1,0/(('5.21出货明细'!D:D=B88)*('5.21出货明细'!G:G&'5.21出货明细'!F:F=C88)),'5.21出货明细'!Z:Z)} -> #N/A | H88: =G88*F88 -> #N/A
A89: 24 | B89: {=LOOKUP(1,0/(('5.21出货明细'!V:V=$H$67)*('5.21出货明细'!X:X=$H$63)*('5.21出货明细'!A:A=A89)),'5.21出货明细'!D:D)} -> #N/A | C89: {=LOOKUP(1,0/(('5.21出货明细'!V:V=$H$67)*('5.21出货明细'!X:X=$H$63)*('5.21出货明细'!A:A=A89)),'5.21出货明细'!G:G&'5.21出货明细'!F:F)} -> #N/A | D89: {=LOOKUP(1,0/(('5.21出货明细'!D:D=B89)*('5.21出货明细'!G:G&'5.21出货明细'!F:F=C89)),'5.21出货明细'!J:J)} -> #N/A | E89: {=LOOKUP(1,0/(('5.21出货明细'!D:D=B89)*('5.21出货明细'!G:G&'5.21出货明细'!F:F=C89)),'5.21出货明细'!C:C)} -> #N/A | F89: {=LOOKUP(1,0/(('5.21出货明细'!D:D=B89)*('5.21出货明细'!G:G&'5.21出货明细'!F:F=C89)),'5.21出货明细'!K:K)} -> #N/A | G89: {=LOOKUP(1,0/(('5.21出货明细'!D:D=B89)*('5.21出货明细'!G:G&'5.21出货明细'!F:F=C89)),'5.21出货明细'!Z:Z)} -> #N/A | H89: =G89*F89 -> #N/A
A90: 25 | B90: {=LOOKUP(1,0/(('5.21出货明细'!V:V=$H$67)*('5.21出货明细'!X:X=$H$63)*('5.21出货明细'!A:A=A90)),'5.21出货明细'!D:D)} -> #N/A | C90: {=LOOKUP(1,0/(('5.21出货明细'!V:V=$H$67)*('5.21出货明细'!X:X=$H$63)*('5.21出货明细'!A:A=A90)),'5.21出货明细'!G:G&'5.21出货明细'!F:F)} -> #N/A | D90: {=LOOKUP(1,0/(('5.21出货明细'!D:D=B90)*('5.21出货明细'!G:G&'5.21出货明细'!F:F=C90)),'5.21出货明细'!J:J)} -> #N/A | E90: {=LOOKUP(1,0/(('5.21出货明细'!D:D=B90)*('5.21出货明细'!G:G&'5.21出货明细'!F:F=C90)),'5.21出货明细'!C:C)} -> #N/A | F90: {=LOOKUP(1,0/(('5.21出货明细'!D:D=B90)*('5.21出货明细'!G:G&'5.21出货明细'!F:F=C90)),'5.21出货明细'!K:K)} -> #N/A | G90: {=LOOKUP(1,0/(('5.21出货明细'!D:D=B90)*('5.21出货明细'!G:G&'5.21出货明细'!F:F=C90)),'5.21出货明细'!Z:Z)} -> #N/A | H90: =G90*F90 -> #N/A
A91: 26 | B91: {=LOOKUP(1,0/(('5.21出货明细'!V:V=$H$67)*('5.21出货明细'!X:X=$H$63)*('5.21出货明细'!A:A=A91)),'5.21出货明细'!D:D)} -> #N/A | C91: {=LOOKUP(1,0/(('5.21出货明细'!V:V=$H$67)*('5.21出货明细'!X:X=$H$63)*('5.21出货明细'!A:A=A91)),'5.21出货明细'!G:G&'5.21出货明细'!F:F)} -> #N/A | D91: {=LOOKUP(1,0/(('5.21出货明细'!D:D=B91)*('5.21出货明细'!G:G&'5.21出货明细'!F:F=C91)),'5.21出货明细'!J:J)} -> #N/A | E91: {=LOOKUP(1,0/(('5.21出货明细'!D:D=B91)*('5.21出货明细'!G:G&'5.21出货明细'!F:F=C91)),'5.21出货明细'!C:C)} -> #N/A | F91: {=LOOKUP(1,0/(('5.21出货明细'!D:D=B91)*('5.21出货明细'!G:G&'5.21出货明细'!F:F=C91)),'5.21出货明细'!K:K)} -> #N/A | G91: {=LOOKUP(1,0/(('5.21出货明细'!D:D=B91)*('5.21出货明细'!G:G&'5.21出货明细'!F:F=C91)),'5.21出货明细'!Z:Z)} -> #N/A | H91: =G91*F91 -> #N/A
A92: 27 | B92: {=LOOKUP(1,0/(('5.21出货明细'!V:V=$H$67)*('5.21出货明细'!X:X=$H$63)*('5.21出货明细'!A:A=A92)),'5.21出货明细'!D:D)} -> #N/A | C92: {=LOOKUP(1,0/(('5.21出货明细'!V:V=$H$67)*('5.21出货明细'!X:X=$H$63)*('5.21出货明细'!A:A=A92)),'5.21出货明细'!G:G&'5.21出货明细'!F:F)} -> #N/A | D92: {=LOOKUP(1,0/(('5.21出货明细'!D:D=B92)*('5.21出货明细'!G:G&'5.21出货明细'!F:F=C92)),'5.21出货明细'!J:J)} -> #N/A | E92: {=LOOKUP(1,0/(('5.21出货明细'!D:D=B92)*('5.21出货明细'!G:G&'5.21出货明细'!F:F=C92)),'5.21出货明细'!C:C)} -> #N/A | F92: {=LOOKUP(1,0/(('5.21出货明细'!D:D=B92)*('5.21出货明细'!G:G&'5.21出货明细'!F:F=C92)),'5.21出货明细'!K:K)} -> #N/A | G92: {=LOOKUP(1,0/(('5.21出货明细'!D:D=B92)*('5.21出货明细'!G:G&'5.21出货明细'!F:F=C92)),'5.21出货明细'!Z:Z)} -> #N/A | H92: =G92*F92 -> #N/A
A93: 28 | B93: {=LOOKUP(1,0/(('5.21出货明细'!V:V=$H$67)*('5.21出货明细'!X:X=$H$63)*('5.21出货明细'!A:A=A93)),'5.21出货明细'!D:D)} -> #N/A | C93: {=LOOKUP(1,0/(('5.21出货明细'!V:V=$H$67)*('5.21出货明细'!X:X=$H$63)*('5.21出货明细'!A:A=A93)),'5.21出货明细'!G:G&'5.21出货明细'!F:F)} -> #N/A | D93: {=LOOKUP(1,0/(('5.21出货明细'!D:D=B93)*('5.21出货明细'!G:G&'5.21出货明细'!F:F=C93)),'5.21出货明细'!J:J)} -> #N/A | E93: {=LOOKUP(1,0/(('5.21出货明细'!D:D=B93)*('5.21出货明细'!G:G&'5.21出货明细'!F:F=C93)),'5.21出货明细'!C:C)} -> #N/A | F93: {=LOOKUP(1,0/(('5.21出货明细'!D:D=B93)*('5.21出货明细'!G:G&'5.21出货明细'!F:F=C93)),'5.21出货明细'!K:K)} -> #N/A | G93: {=LOOKUP(1,0/(('5.21出货明细'!D:D=B93)*('5.21出货明细'!G:G&'5.21出货明细'!F:F=C93)),'5.21出货明细'!Z:Z)} -> #N/A | H93: =G93*F93 -> #N/A
A94: 29 | B94: {=LOOKUP(1,0/(('5.21出货明细'!V:V=$H$67)*('5.21出货明细'!X:X=$H$63)*('5.21出货明细'!A:A=A94)),'5.21出货明细'!D:D)} -> #N/A | C94: {=LOOKUP(1,0/(('5.21出货明细'!V:V=$H$67)*('5.21出货明细'!X:X=$H$63)*('5.21出货明细'!A:A=A94)),'5.21出货明细'!G:G&'5.21出货明细'!F:F)} -> #N/A | D94: {=LOOKUP(1,0/(('5.21出货明细'!D:D=B94)*('5.21出货明细'!G:G&'5.21出货明细'!F:F=C94)),'5.21出货明细'!J:J)} -> #N/A | E94: {=LOOKUP(1,0/(('5.21出货明细'!D:D=B94)*('5.21出货明细'!G:G&'5.21出货明细'!F:F=C94)),'5.21出货明细'!C:C)} -> #N/A | F94: {=LOOKUP(1,0/(('5.21出货明细'!D:D=B94)*('5.21出货明细'!G:G&'5.21出货明细'!F:F=C94)),'5.21出货明细'!K:K)} -> #N/A | G94: {=LOOKUP(1,0/(('5.21出货明细'!D:D=B94)*('5.21出货明细'!G:G&'5.21出货明细'!F:F=C94)),'5.21出货明细'!Z:Z)} -> #N/A | H94: =G94*F94 -> #N/A
F95: TOTAL: | G95: =SUM(H84:H94) -> #N/A
B96: 总值大写 Total Amount: | C96: =G95 -> #N/A
B98: 華登製品實業有限公司
B99: ROYAL REGENT PRODUCTS INDUSTRIES LIMITED
B100: Unit 07-08,12/F,Greenfield Tower,Concordia Plaza,No.1 Science Museum Road,Tsim Sha Tsui,Kowloon,Postal Code:999077,Hong Kong
B101: TEL: 00852-2425 0720 FAX: 00852-2424 3407 EMAIL: chloe@royalregenthk.com
B102: 商 业 发 票
B103: COMMERCIAL INVOICE
B105: 买方:
B106: The Buyers: M/S. | G106: 号码 No. | H106: PR202600278
B107: 華登製品實業有限公司
B108: Unit 07-08,12/F,Greenfield Tower,Concordia Plaza,No.1 Science Museum Road,Tsim Sha Tsui,Kowloon,Postal Code:999077,Hong Kong TEL: 00852-2425 0720 FAX: 00852-2424 3407 EMAIL: chloe@royalregenthk.com Attention: Ms Tang | G108: 日期 Date | H108: =实业合同!H111 -> 46076
B110: Consignee：M/S. | G110: 合同号 Contract No. | H110: =实业合同!H107 -> RPIRRI260278
B111: PT. ROYAL REGENT INDONESIA
B112: Tax ID: 61.146.021.3-513.000 KAWASAN INDUSTRI KENDAL, JL. WANAMARTA RAYA NO 33A & 35, BRANGSONG, BRANGSONG, KAB. KENDAL, JAWA TENGAH, 51371, INDONESIA
G113: 运输方式： | H113: BY SEA
B114: Tel.: 62 895-3269-82429 Email: exim@royalregentid.com，exim2@royalregentid.com，exim3@royalregentid.com
B115: Attention: Novi Azka Tiurlan Putri Marpaung
B116: 卖方:
B117: The Sellers: M/S.
B118: 东莞兴信塑胶制品有限公司
B119: Dong Guan Hanson Plastic Product Ltd.
B120: 广东省东莞省清溪镇上元村银坑路59号 Yin keng Road 59,Shangyuan Village, Qingxi Town, Dongguan City, Guangdong Province, Postal Code523640, China TEL:0769-87312864 EMAIL:luo@hanson2.com Attention: Mr Luo
B122: 装运口岸 From： | C122: SHENZHEN,CHINA(中国深圳) | F122: 目的地 To： | G122: Indonesia(印度尼西亚)
...

Sheet 装箱单
A1: ROYAL REGENT PRODUCTS INDUSTRIES LIMITED
A2: Unit 07-08,12/F,Greenfield Tower,Concordia Plaza,No.1 Science Museum Road,Tsim Sha Tsui,Kowloon,Postal Code:999077,Hong Kong
A6: PACKING LIST
A8: 1 .Shipper: | D8: 2. Packing List Number | H8: 3. Page
A9: ROYAL REGENT PRODUCTS INDUSTRIES LIMITED Unit 07-08,12/F,Greenfield Tower,Concordia Plaza,No.1 Science Museum Road,Tsim Sha Tsui,Kowloon,Postal Code:999077,Hong Kong | D9: =实业发票!H9 -> PR202600276
D10: 4. Packing List Date
D11: 46134
A12: TEL: 00852-2425 0720 FAX: 00852-2424 3407 | D12: 5.PO# | H12: 6. OF#
A13: EMAIL: chloe@royalregenthk.com | D13: =实业合同!H5 -> RPIRRI260276
A14: Attention: Ms Tang
A15: 7. Consignee:
A16: PT. ROYAL REGENT INDONESIA | D16: 8. Container | H16: 9. Seal Number
A17: Tax ID: 61.146.021.3-513.000 | D17: BMOU6019197 | H17: EMCRZS9184
A18: KAWASAN INDUSTRI KENDAL, JL. WANAMARTA RAYA NO. 33A & 35,
A19: BRANGSONG, BRANGSONG, KAB. KENDAL, JAWA TENGAH, 51371,
A20: INDONESIA
A21: Tel.: 62 895-3269-82429
A22: Attention: Novi Azka Tiurlan Putri Marpaung
A23: Email: exim@royalregentid.com，exim2@royalregentid.com，exim3@royalregentid.com
A24: 序号 serial number | B24: 型 号 Item No. | C24: 品名描述 Names and Descriptions | D24: 数 量 Quantities | E24: 单位 Unit | F24: 数 量 Quantities | G24: 单位 Unit | H24: 毛重 Gross Weight Kgs | I24: 净重 Net Weight Kgs | J24: 箱数 Carton No. | K24: 立方数 CBM
A25: 1 | B25: {=LOOKUP(1,0/(('5.21出货明细'!X:X=$D$9)*('5.21出货明细'!A:A=A25)),'5.21出货明细'!D:D)} -> #N/A | C25: {=LOOKUP(1,0/(('5.21出货明细'!X:X=$D$9)*('5.21出货明细'!A:A=A25)),'5.21出货明细'!G:G&'5.21出货明细'!F:F)} -> #N/A | D25: {=LOOKUP(1,0/(('5.21出货明细'!X:X=$D$9)*('5.21出货明细'!A:A=A25)),'5.21出货明细'!K:K)} -> #N/A | E25: {=LOOKUP(1,0/(('5.21出货明细'!X:X=$D$9)*('5.21出货明细'!A:A=A25)),'5.21出货明细'!J:J)} -> #N/A | F25: {=LOOKUP(1,0/(('5.21出货明细'!X:X=$D$9)*('5.21出货明细'!A:A=A25)),'5.21出货明细'!L:L)} -> #N/A | G25: {=LOOKUP(1,0/(('5.21出货明细'!X:X=$D$9)*('5.21出货明细'!A:A=A25)),'5.21出货明细'!M:M)} -> #N/A | H25: {=LOOKUP(1,0/(('5.21出货明细'!X:X=$D$9)*('5.21出货明细'!A:A=A25)),'5.21出货明细'!P:P)} -> #N/A | I25: {=LOOKUP(1,0/(('5.21出货明细'!X:X=$D$9)*('5.21出货明细'!A:A=A25)),'5.21出货明细'!Q:Q)} -> #N/A | J25: {=LOOKUP(1,0/(('5.21出货明细'!X:X=$D$9)*('5.21出货明细'!A:A=A25)),'5.21出货明细'!AT:AT)} -> #N/A | K25: {=LOOKUP(1,0/(('5.21出货明细'!X:X=$D$9)*('5.21出货明细'!A:A=A25)),'5.21出货明细'!S:S)} -> #N/A
A26: 2 | B26: {=LOOKUP(1,0/(('5.21出货明细'!X:X=$D$9)*('5.21出货明细'!A:A=A26)),'5.21出货明细'!D:D)} -> #N/A | C26: {=LOOKUP(1,0/(('5.21出货明细'!X:X=$D$9)*('5.21出货明细'!A:A=A26)),'5.21出货明细'!G:G&'5.21出货明细'!F:F)} -> #N/A | D26: {=LOOKUP(1,0/(('5.21出货明细'!X:X=$D$9)*('5.21出货明细'!A:A=A26)),'5.21出货明细'!K:K)} -> #N/A | E26: {=LOOKUP(1,0/(('5.21出货明细'!X:X=$D$9)*('5.21出货明细'!A:A=A26)),'5.21出货明细'!J:J)} -> #N/A | F26: {=LOOKUP(1,0/(('5.21出货明细'!X:X=$D$9)*('5.21出货明细'!A:A=A26)),'5.21出货明细'!L:L)} -> #N/A | G26: {=LOOKUP(1,0/(('5.21出货明细'!X:X=$D$9)*('5.21出货明细'!A:A=A26)),'5.21出货明细'!M:M)} -> #N/A | H26: {=LOOKUP(1,0/(('5.21出货明细'!X:X=$D$9)*('5.21出货明细'!A:A=A26)),'5.21出货明细'!P:P)} -> #N/A | I26: {=LOOKUP(1,0/(('5.21出货明细'!X:X=$D$9)*('5.21出货明细'!A:A=A26)),'5.21出货明细'!Q:Q)} -> #N/A | J26: {=LOOKUP(1,0/(('5.21出货明细'!X:X=$D$9)*('5.21出货明细'!A:A=A26)),'5.21出货明细'!AT:AT)} -> #N/A | K26: {=LOOKUP(1,0/(('5.21出货明细'!X:X=$D$9)*('5.21出货明细'!A:A=A26)),'5.21出货明细'!S:S)} -> #N/A
A27: 3 | B27: {=LOOKUP(1,0/(('5.21出货明细'!X:X=$D$9)*('5.21出货明细'!A:A=A27)),'5.21出货明细'!D:D)} -> #N/A | C27: {=LOOKUP(1,0/(('5.21出货明细'!X:X=$D$9)*('5.21出货明细'!A:A=A27)),'5.21出货明细'!G:G&'5.21出货明细'!F:F)} -> #N/A | D27: {=LOOKUP(1,0/(('5.21出货明细'!X:X=$D$9)*('5.21出货明细'!A:A=A27)),'5.21出货明细'!K:K)} -> #N/A | E27: {=LOOKUP(1,0/(('5.21出货明细'!X:X=$D$9)*('5.21出货明细'!A:A=A27)),'5.21出货明细'!J:J)} -> #N/A | F27: {=LOOKUP(1,0/(('5.21出货明细'!X:X=$D$9)*('5.21出货明细'!A:A=A27)),'5.21出货明细'!L:L)} -> #N/A | G27: {=LOOKUP(1,0/(('5.21出货明细'!X:X=$D$9)*('5.21出货明细'!A:A=A27)),'5.21出货明细'!M:M)} -> #N/A | H27: {=LOOKUP(1,0/(('5.21出货明细'!X:X=$D$9)*('5.21出货明细'!A:A=A27)),'5.21出货明细'!P:P)} -> #N/A | I27: {=LOOKUP(1,0/(('5.21出货明细'!X:X=$D$9)*('5.21出货明细'!A:A=A27)),'5.21出货明细'!Q:Q)} -> #N/A | J27: {=LOOKUP(1,0/(('5.21出货明细'!X:X=$D$9)*('5.21出货明细'!A:A=A27)),'5.21出货明细'!AT:AT)} -> #N/A | K27: {=LOOKUP(1,0/(('5.21出货明细'!X:X=$D$9)*('5.21出货明细'!A:A=A27)),'5.21出货明细'!S:S)} -> #N/A
A28: 4 | B28: {=LOOKUP(1,0/(('5.21出货明细'!X:X=$D$9)*('5.21出货明细'!A:A=A28)),'5.21出货明细'!D:D)} -> #N/A | C28: {=LOOKUP(1,0/(('5.21出货明细'!X:X=$D$9)*('5.21出货明细'!A:A=A28)),'5.21出货明细'!G:G&'5.21出货明细'!F:F)} -> #N/A | D28: {=LOOKUP(1,0/(('5.21出货明细'!X:X=$D$9)*('5.21出货明细'!A:A=A28)),'5.21出货明细'!K:K)} -> #N/A | E28: {=LOOKUP(1,0/(('5.21出货明细'!X:X=$D$9)*('5.21出货明细'!A:A=A28)),'5.21出货明细'!J:J)} -> #N/A | F28: {=LOOKUP(1,0/(('5.21出货明细'!X:X=$D$9)*('5.21出货明细'!A:A=A28)),'5.21出货明细'!L:L)} -> #N/A | G28: {=LOOKUP(1,0/(('5.21出货明细'!X:X=$D$9)*('5.21出货明细'!A:A=A28)),'5.21出货明细'!M:M)} -> #N/A | H28: {=LOOKUP(1,0/(('5.21出货明细'!X:X=$D$9)*('5.21出货明细'!A:A=A28)),'5.21出货明细'!P:P)} -> #N/A | I28: {=LOOKUP(1,0/(('5.21出货明细'!X:X=$D$9)*('5.21出货明细'!A:A=A28)),'5.21出货明细'!Q:Q)} -> #N/A | J28: {=LOOKUP(1,0/(('5.21出货明细'!X:X=$D$9)*('5.21出货明细'!A:A=A28)),'5.21出货明细'!AT:AT)} -> #N/A | K28: {=LOOKUP(1,0/(('5.21出货明细'!X:X=$D$9)*('5.21出货明细'!A:A=A28)),'5.21出货明细'!S:S)} -> #N/A
A29: 5 | B29: {=LOOKUP(1,0/(('5.21出货明细'!X:X=$D$9)*('5.21出货明细'!A:A=A29)),'5.21出货明细'!D:D)} -> #N/A | C29: {=LOOKUP(1,0/(('5.21出货明细'!X:X=$D$9)*('5.21出货明细'!A:A=A29)),'5.21出货明细'!G:G&'5.21出货明细'!F:F)} -> #N/A | D29: {=LOOKUP(1,0/(('5.21出货明细'!X:X=$D$9)*('5.21出货明细'!A:A=A29)),'5.21出货明细'!K:K)} -> #N/A | E29: {=LOOKUP(1,0/(('5.21出货明细'!X:X=$D$9)*('5.21出货明细'!A:A=A29)),'5.21出货明细'!J:J)} -> #N/A | F29: {=LOOKUP(1,0/(('5.21出货明细'!X:X=$D$9)*('5.21出货明细'!A:A=A29)),'5.21出货明细'!L:L)} -> #N/A | G29: {=LOOKUP(1,0/(('5.21出货明细'!X:X=$D$9)*('5.21出货明细'!A:A=A29)),'5.21出货明细'!M:M)} -> #N/A | H29: {=LOOKUP(1,0/(('5.21出货明细'!X:X=$D$9)*('5.21出货明细'!A:A=A29)),'5.21出货明细'!P:P)} -> #N/A | I29: {=LOOKUP(1,0/(('5.21出货明细'!X:X=$D$9)*('5.21出货明细'!A:A=A29)),'5.21出货明细'!Q:Q)} -> #N/A | J29: {=LOOKUP(1,0/(('5.21出货明细'!X:X=$D$9)*('5.21出货明细'!A:A=A29)),'5.21出货明细'!AT:AT)} -> #N/A | K29: {=LOOKUP(1,0/(('5.21出货明细'!X:X=$D$9)*('5.21出货明细'!A:A=A29)),'5.21出货明细'!S:S)} -> #N/A
A30: 6 | B30: {=LOOKUP(1,0/(('5.21出货明细'!X:X=$D$9)*('5.21出货明细'!A:A=A30)),'5.21出货明细'!D:D)} -> #N/A | C30: {=LOOKUP(1,0/(('5.21出货明细'!X:X=$D$9)*('5.21出货明细'!A:A=A30)),'5.21出货明细'!G:G&'5.21出货明细'!F:F)} -> #N/A | D30: {=LOOKUP(1,0/(('5.21出货明细'!X:X=$D$9)*('5.21出货明细'!A:A=A30)),'5.21出货明细'!K:K)} -> #N/A | E30: {=LOOKUP(1,0/(('5.21出货明细'!X:X=$D$9)*('5.21出货明细'!A:A=A30)),'5.21出货明细'!J:J)} -> #N/A | F30: {=LOOKUP(1,0/(('5.21出货明细'!X:X=$D$9)*('5.21出货明细'!A:A=A30)),'5.21出货明细'!L:L)} -> #N/A | G30: {=LOOKUP(1,0/(('5.21出货明细'!X:X=$D$9)*('5.21出货明细'!A:A=A30)),'5.21出货明细'!M:M)} -> #N/A | H30: {=LOOKUP(1,0/(('5.21出货明细'!X:X=$D$9)*('5.21出货明细'!A:A=A30)),'5.21出货明细'!P:P)} -> #N/A | I30: {=LOOKUP(1,0/(('5.21出货明细'!X:X=$D$9)*('5.21出货明细'!A:A=A30)),'5.21出货明细'!Q:Q)} -> #N/A | J30: {=LOOKUP(1,0/(('5.21出货明细'!X:X=$D$9)*('5.21出货明细'!A:A=A30)),'5.21出货明细'!AT:AT)} -> #N/A | K30: {=LOOKUP(1,0/(('5.21出货明细'!X:X=$D$9)*('5.21出货明细'!A:A=A30)),'5.21出货明细'!S:S)} -> #N/A
A31: 7 | B31: {=LOOKUP(1,0/(('5.21出货明细'!X:X=$D$9)*('5.21出货明细'!A:A=A31)),'5.21出货明细'!D:D)} -> #N/A | C31: {=LOOKUP(1,0/(('5.21出货明细'!X:X=$D$9)*('5.21出货明细'!A:A=A31)),'5.21出货明细'!G:G&'5.21出货明细'!F:F)} -> #N/A | D31: {=LOOKUP(1,0/(('5.21出货明细'!X:X=$D$9)*('5.21出货明细'!A:A=A31)),'5.21出货明细'!K:K)} -> #N/A | E31: {=LOOKUP(1,0/(('5.21出货明细'!X:X=$D$9)*('5.21出货明细'!A:A=A31)),'5.21出货明细'!J:J)} -> #N/A | F31: {=LOOKUP(1,0/(('5.21出货明细'!X:X=$D$9)*('5.21出货明细'!A:A=A31)),'5.21出货明细'!L:L)} -> #N/A | G31: {=LOOKUP(1,0/(('5.21出货明细'!X:X=$D$9)*('5.21出货明细'!A:A=A31)),'5.21出货明细'!M:M)} -> #N/A | H31: {=LOOKUP(1,0/(('5.21出货明细'!X:X=$D$9)*('5.21出货明细'!A:A=A31)),'5.21出货明细'!P:P)} -> #N/A | I31: {=LOOKUP(1,0/(('5.21出货明细'!X:X=$D$9)*('5.21出货明细'!A:A=A31)),'5.21出货明细'!Q:Q)} -> #N/A | J31: {=LOOKUP(1,0/(('5.21出货明细'!X:X=$D$9)*('5.21出货明细'!A:A=A31)),'5.21出货明细'!AT:AT)} -> #N/A | K31: {=LOOKUP(1,0/(('5.21出货明细'!X:X=$D$9)*('5.21出货明细'!A:A=A31)),'5.21出货明细'!S:S)} -> #N/A
A32: 8 | B32: {=LOOKUP(1,0/(('5.21出货明细'!X:X=$D$9)*('5.21出货明细'!A:A=A32)),'5.21出货明细'!D:D)} -> #N/A | C32: {=LOOKUP(1,0/(('5.21出货明细'!X:X=$D$9)*('5.21出货明细'!A:A=A32)),'5.21出货明细'!G:G&'5.21出货明细'!F:F)} -> #N/A | D32: {=LOOKUP(1,0/(('5.21出货明细'!X:X=$D$9)*('5.21出货明细'!A:A=A32)),'5.21出货明细'!K:K)} -> #N/A | E32: {=LOOKUP(1,0/(('5.21出货明细'!X:X=$D$9)*('5.21出货明细'!A:A=A32)),'5.21出货明细'!J:J)} -> #N/A | F32: {=LOOKUP(1,0/(('5.21出货明细'!X:X=$D$9)*('5.21出货明细'!A:A=A32)),'5.21出货明细'!L:L)} -> #N/A | G32: {=LOOKUP(1,0/(('5.21出货明细'!X:X=$D$9)*('5.21出货明细'!A:A=A32)),'5.21出货明细'!M:M)} -> #N/A | H32: {=LOOKUP(1,0/(('5.21出货明细'!X:X=$D$9)*('5.21出货明细'!A:A=A32)),'5.21出货明细'!P:P)} -> #N/A | I32: {=LOOKUP(1,0/(('5.21出货明细'!X:X=$D$9)*('5.21出货明细'!A:A=A32)),'5.21出货明细'!Q:Q)} -> #N/A | J32: {=LOOKUP(1,0/(('5.21出货明细'!X:X=$D$9)*('5.21出货明细'!A:A=A32)),'5.21出货明细'!AT:AT)} -> #N/A | K32: {=LOOKUP(1,0/(('5.21出货明细'!X:X=$D$9)*('5.21出货明细'!A:A=A32)),'5.21出货明细'!S:S)} -> #N/A
A33: 9 | B33: {=LOOKUP(1,0/(('5.21出货明细'!X:X=$D$9)*('5.21出货明细'!A:A=A33)),'5.21出货明细'!D:D)} -> #N/A | C33: {=LOOKUP(1,0/(('5.21出货明细'!X:X=$D$9)*('5.21出货明细'!A:A=A33)),'5.21出货明细'!G:G&'5.21出货明细'!F:F)} -> #N/A | D33: {=LOOKUP(1,0/(('5.21出货明细'!X:X=$D$9)*('5.21出货明细'!A:A=A33)),'5.21出货明细'!K:K)} -> #N/A | E33: {=LOOKUP(1,0/(('5.21出货明细'!X:X=$D$9)*('5.21出货明细'!A:A=A33)),'5.21出货明细'!J:J)} -> #N/A | F33: {=LOOKUP(1,0/(('5.21出货明细'!X:X=$D$9)*('5.21出货明细'!A:A=A33)),'5.21出货明细'!L:L)} -> #N/A | G33: {=LOOKUP(1,0/(('5.21出货明细'!X:X=$D$9)*('5.21出货明细'!A:A=A33)),'5.21出货明细'!M:M)} -> #N/A | H33: {=LOOKUP(1,0/(('5.21出货明细'!X:X=$D$9)*('5.21出货明细'!A:A=A33)),'5.21出货明细'!P:P)} -> #N/A | I33: {=LOOKUP(1,0/(('5.21出货明细'!X:X=$D$9)*('5.21出货明细'!A:A=A33)),'5.21出货明细'!Q:Q)} -> #N/A | J33: {=LOOKUP(1,0/(('5.21出货明细'!X:X=$D$9)*('5.21出货明细'!A:A=A33)),'5.21出货明细'!AT:AT)} -> #N/A | K33: {=LOOKUP(1,0/(('5.21出货明细'!X:X=$D$9)*('5.21出货明细'!A:A=A33)),'5.21出货明细'!S:S)} -> #N/A
A34: 10 | B34: {=LOOKUP(1,0/(('5.21出货明细'!X:X=$D$9)*('5.21出货明细'!A:A=A34)),'5.21出货明细'!D:D)} -> #N/A | C34: {=LOOKUP(1,0/(('5.21出货明细'!X:X=$D$9)*('5.21出货明细'!A:A=A34)),'5.21出货明细'!G:G&'5.21出货明细'!F:F)} -> #N/A | D34: {=LOOKUP(1,0/(('5.21出货明细'!X:X=$D$9)*('5.21出货明细'!A:A=A34)),'5.21出货明细'!K:K)} -> #N/A | E34: {=LOOKUP(1,0/(('5.21出货明细'!X:X=$D$9)*('5.21出货明细'!A:A=A34)),'5.21出货明细'!J:J)} -> #N/A | F34: {=LOOKUP(1,0/(('5.21出货明细'!X:X=$D$9)*('5.21出货明细'!A:A=A34)),'5.21出货明细'!L:L)} -> #N/A | G34: {=LOOKUP(1,0/(('5.21出货明细'!X:X=$D$9)*('5.21出货明细'!A:A=A34)),'5.21出货明细'!M:M)} -> #N/A | H34: {=LOOKUP(1,0/(('5.21出货明细'!X:X=$D$9)*('5.21出货明细'!A:A=A34)),'5.21出货明细'!P:P)} -> #N/A | I34: {=LOOKUP(1,0/(('5.21出货明细'!X:X=$D$9)*('5.21出货明细'!A:A=A34)),'5.21出货明细'!Q:Q)} -> #N/A | J34: {=LOOKUP(1,0/(('5.21出货明细'!X:X=$D$9)*('5.21出货明细'!A:A=A34)),'5.21出货明细'!AT:AT)} -> #N/A | K34: {=LOOKUP(1,0/(('5.21出货明细'!X:X=$D$9)*('5.21出货明细'!A:A=A34)),'5.21出货明细'!S:S)} -> #N/A
A35: 11 | B35: {=LOOKUP(1,0/(('5.21出货明细'!X:X=$D$9)*('5.21出货明细'!A:A=A35)),'5.21出货明细'!D:D)} -> #N/A | C35: {=LOOKUP(1,0/(('5.21出货明细'!X:X=$D$9)*('5.21出货明细'!A:A=A35)),'5.21出货明细'!G:G&'5.21出货明细'!F:F)} -> #N/A | D35: {=LOOKUP(1,0/(('5.21出货明细'!X:X=$D$9)*('5.21出货明细'!A:A=A35)),'5.21出货明细'!K:K)} -> #N/A | E35: {=LOOKUP(1,0/(('5.21出货明细'!X:X=$D$9)*('5.21出货明细'!A:A=A35)),'5.21出货明细'!J:J)} -> #N/A | F35: {=LOOKUP(1,0/(('5.21出货明细'!X:X=$D$9)*('5.21出货明细'!A:A=A35)),'5.21出货明细'!L:L)} -> #N/A | G35: {=LOOKUP(1,0/(('5.21出货明细'!X:X=$D$9)*('5.21出货明细'!A:A=A35)),'5.21出货明细'!M:M)} -> #N/A | H35: {=LOOKUP(1,0/(('5.21出货明细'!X:X=$D$9)*('5.21出货明细'!A:A=A35)),'5.21出货明细'!P:P)} -> #N/A | I35: {=LOOKUP(1,0/(('5.21出货明细'!X:X=$D$9)*('5.21出货明细'!A:A=A35)),'5.21出货明细'!Q:Q)} -> #N/A | J35: {=LOOKUP(1,0/(('5.21出货明细'!X:X=$D$9)*('5.21出货明细'!A:A=A35)),'5.21出货明细'!AT:AT)} -> #N/A | K35: {=LOOKUP(1,0/(('5.21出货明细'!X:X=$D$9)*('5.21出货明细'!A:A=A35)),'5.21出货明细'!S:S)} -> #N/A
A36: 12 | B36: {=LOOKUP(1,0/(('5.21出货明细'!X:X=$D$9)*('5.21出货明细'!A:A=A36)),'5.21出货明细'!D:D)} -> #N/A | C36: {=LOOKUP(1,0/(('5.21出货明细'!X:X=$D$9)*('5.21出货明细'!A:A=A36)),'5.21出货明细'!G:G&'5.21出货明细'!F:F)} -> #N/A | D36: {=LOOKUP(1,0/(('5.21出货明细'!X:X=$D$9)*('5.21出货明细'!A:A=A36)),'5.21出货明细'!K:K)} -> #N/A | E36: {=LOOKUP(1,0/(('5.21出货明细'!X:X=$D$9)*('5.21出货明细'!A:A=A36)),'5.21出货明细'!J:J)} -> #N/A | F36: {=LOOKUP(1,0/(('5.21出货明细'!X:X=$D$9)*('5.21出货明细'!A:A=A36)),'5.21出货明细'!L:L)} -> #N/A | G36: {=LOOKUP(1,0/(('5.21出货明细'!X:X=$D$9)*('5.21出货明细'!A:A=A36)),'5.21出货明细'!M:M)} -> #N/A | H36: {=LOOKUP(1,0/(('5.21出货明细'!X:X=$D$9)*('5.21出货明细'!A:A=A36)),'5.21出货明细'!P:P)} -> #N/A | I36: {=LOOKUP(1,0/(('5.21出货明细'!X:X=$D$9)*('5.21出货明细'!A:A=A36)),'5.21出货明细'!Q:Q)} -> #N/A | J36: {=LOOKUP(1,0/(('5.21出货明细'!X:X=$D$9)*('5.21出货明细'!A:A=A36)),'5.21出货明细'!AT:AT)} -> #N/A | K36: {=LOOKUP(1,0/(('5.21出货明细'!X:X=$D$9)*('5.21出货明细'!A:A=A36)),'5.21出货明细'!S:S)} -> #N/A
... A42: 18 | B42: {=LOOKUP(1,0/(('5.21出货明细'!X:X=$D$9)*('5.21出货明细'!A:A=A42)),'5.21出货明细'!D:D)} -> #N/A | C42: {=LOOKUP(1,0/(('5.21出货明细'!X:X=$D$9)*('5.21出货明细'!A:A=A42)),'5.21出货明细'!G:G&'5.21出货明细'!F:F)} -> #N/A | D42: {=LOOKUP(1,0/(('5.21出货明细'!X:X=$D$9)*('5.21出货明细'!A:A=A42)),'5.21出货明细'!K:K)} -> #N/A | E42: {=LOOKUP(1,0/(('5.21出货明细'!X:X=$D$9)*('5.21出货明细'!A:A=A42)),'5.21出货明细'!J:J)} -> #N/A | F42: {=LOOKUP(1,0/(('5.21出货明细'!X:X=$D$9)*('5.21出货明细'!A:A=A42)),'5.21出货明细'!L:L)} -> #N/A | G42: {=LOOKUP(1,0/(('5.21出货明细'!X:X=$D$9)*('5.21出货明细'!A:A=A42)),'5.21出货明细'!M:M)} -> #N/A | H42: {=LOOKUP(1,0/(('5.21出货明细'!X:X=$D$9)*('5.21出货明细'!A:A=A42)),'5.21出货明细'!P:P)} -> #N/A | I42: {=LOOKUP(1,0/(('5.21出货明细'!X:X=$D$9)*('5.21出货明细'!A:A=A42)),'5.21出货明细'!Q:Q)} -> #N/A | J42: {=LOOKUP(1,0/(('5.21出货明细'!X:X=$D$9)*('5.21出货明细'!A:A=A42)),'5.21出货明细'!AT:AT)} -> #N/A | K42: {=LOOKUP(1,0/(('5.21出货明细'!X:X=$D$9)*('5.21出货明细'!A:A=A42)),'5.21出货明细'!S:S)} -> #N/A
D43: =SUM(D25:D42) -> #N/A | H43: =SUM(H25:H42) -> #N/A | I43: =SUM(I25:I42) -> #N/A | J43: =SUM(J25:J42) -> #N/A | K43: =SUM(K25:K42) -> #N/A
A46: ROYAL REGENT PRODUCTS INDUSTRIES LIMITED
A47: Unit 07-08,12/F,Greenfield Tower,Concordia Plaza,No.1 Science Museum Road,Tsim Sha Tsui,Kowloon,Postal Code:999077,Hong Kong
A51: PACKING LIST
A53: 1 .Shipper: | D53: 2. Packing List Number | H53: 3. Page
A54: ROYAL REGENT PRODUCTS INDUSTRIES LIMITED Unit 07-08,12/F,Greenfield Tower,Concordia Plaza,No.1 Science Museum Road,Tsim Sha Tsui,Kowloon,Postal Code:999077,Hong Kong | D54: =实业发票!H63 -> PR202600277
D55: 4. Packing List Date
D56: =D11 -> 46134
A57: TEL: 00852-2425 0720 FAX: 00852-2424 3407 | D57: 5.PO# | H57: 6. OF#
A58: EMAIL: chloe@royalregenthk.com | D58: =实业合同!H60 -> RPIRRI260277
A59: Attention: Ms Tang
A60: 7. Consignee:
A61: PT. ROYAL REGENT INDONESIA | D61: 8. Container | H61: 9. Seal Number
A62: Tax ID: 61.146.021.3-513.000 | D62: =D17 -> BMOU6019197 | H62: =H17 -> EMCRZS9184
A63: KAWASAN INDUSTRI KENDAL, JL. WANAMARTA RAYA NO. 33A & 35,
A64: BRANGSONG, BRANGSONG, KAB. KENDAL, JAWA TENGAH, 51371,
A65: INDONESIA
A66: Tel.: 62 895-3269-82429
A67: Attention: Novi Azka Tiurlan Putri Marpaung
A68: Email: exim@royalregentid.com，exim2@royalregentid.com，exim3@royalregentid.com
A69: 序号 serial number | B69: 型 号 Item No. | C69: 品名描述 Names and Descriptions | D69: 数 量 Quantities | E69: 单位 Unit | F69: 数 量 Quantities | G69: 单位 Unit | H69: 毛重 Gross Weight Kgs | I69: 净重 Net Weight Kgs | J69: 箱数 Carton No. | K69: 立方数 CBM
A70: 19 | B70: {=LOOKUP(1,0/(('5.21出货明细'!X:X=$D$54)*('5.21出货明细'!A:A=A70)),'5.21出货明细'!D:D)} -> #N/A | C70: {=LOOKUP(1,0/(('5.21出货明细'!X:X=$D$54)*('5.21出货明细'!A:A=A70)),'5.21出货明细'!G:G&'5.21出货明细'!F:F)} -> #N/A | D70: {=LOOKUP(1,0/(('5.21出货明细'!X:X=$D$54)*('5.21出货明细'!A:A=A70)),'5.21出货明细'!K:K)} -> #N/A | E70: {=LOOKUP(1,0/(('5.21出货明细'!X:X=$D$54)*('5.21出货明细'!A:A=A70)),'5.21出货明细'!J:J)} -> #N/A | F70: {=LOOKUP(1,0/(('5.21出货明细'!X:X=$D$54)*('5.21出货明细'!A:A=A70)),'5.21出货明细'!L:L)} -> #N/A | G70: {=LOOKUP(1,0/(('5.21出货明细'!X:X=$D$54)*('5.21出货明细'!A:A=A70)),'5.21出货明细'!M:M)} -> #N/A | H70: {=LOOKUP(1,0/(('5.21出货明细'!X:X=$D$54)*('5.21出货明细'!A:A=A70)),'5.21出货明细'!P:P)} -> #N/A | I70: {=LOOKUP(1,0/(('5.21出货明细'!X:X=$D$54)*('5.21出货明细'!A:A=A70)),'5.21出货明细'!Q:Q)} -> #N/A | J70: {=LOOKUP(1,0/(('5.21出货明细'!X:X=$D$54)*('5.21出货明细'!A:A=A70)),'5.21出货明细'!AT:AT)} -> #N/A | K70: {=LOOKUP(1,0/(('5.21出货明细'!X:X=$D$54)*('5.21出货明细'!A:A=A70)),'5.21出货明细'!S:S)} -> #N/A
A71: 20 | B71: {=LOOKUP(1,0/(('5.21出货明细'!X:X=$D$54)*('5.21出货明细'!A:A=A71)),'5.21出货明细'!D:D)} -> #N/A | C71: {=LOOKUP(1,0/(('5.21出货明细'!X:X=$D$54)*('5.21出货明细'!A:A=A71)),'5.21出货明细'!G:G&'5.21出货明细'!F:F)} -> #N/A | D71: {=LOOKUP(1,0/(('5.21出货明细'!X:X=$D$54)*('5.21出货明细'!A:A=A71)),'5.21出货明细'!K:K)} -> #N/A | E71: {=LOOKUP(1,0/(('5.21出货明细'!X:X=$D$54)*('5.21出货明细'!A:A=A71)),'5.21出货明细'!J:J)} -> #N/A | F71: {=LOOKUP(1,0/(('5.21出货明细'!X:X=$D$54)*('5.21出货明细'!A:A=A71)),'5.21出货明细'!L:L)} -> #N/A | G71: {=LOOKUP(1,0/(('5.21出货明细'!X:X=$D$54)*('5.21出货明细'!A:A=A71)),'5.21出货明细'!M:M)} -> #N/A | H71: {=LOOKUP(1,0/(('5.21出货明细'!X:X=$D$54)*('5.21出货明细'!A:A=A71)),'5.21出货明细'!P:P)} -> #N/A | I71: {=LOOKUP(1,0/(('5.21出货明细'!X:X=$D$54)*('5.21出货明细'!A:A=A71)),'5.21出货明细'!Q:Q)} -> #N/A | J71: {=LOOKUP(1,0/(('5.21出货明细'!X:X=$D$54)*('5.21出货明细'!A:A=A71)),'5.21出货明细'!AT:AT)} -> #N/A | K71: {=LOOKUP(1,0/(('5.21出货明细'!X:X=$D$54)*('5.21出货明细'!A:A=A71)),'5.21出货明细'!S:S)} -> #N/A
A72: 21 | B72: {=LOOKUP(1,0/(('5.21出货明细'!X:X=$D$54)*('5.21出货明细'!A:A=A72)),'5.21出货明细'!D:D)} -> #N/A | C72: {=LOOKUP(1,0/(('5.21出货明细'!X:X=$D$54)*('5.21出货明细'!A:A=A72)),'5.21出货明细'!G:G&'5.21出货明细'!F:F)} -> #N/A | D72: {=LOOKUP(1,0/(('5.21出货明细'!X:X=$D$54)*('5.21出货明细'!A:A=A72)),'5.21出货明细'!K:K)} -> #N/A | E72: {=LOOKUP(1,0/(('5.21出货明细'!X:X=$D$54)*('5.21出货明细'!A:A=A72)),'5.21出货明细'!J:J)} -> #N/A | F72: {=LOOKUP(1,0/(('5.21出货明细'!X:X=$D$54)*('5.21出货明细'!A:A=A72)),'5.21出货明细'!L:L)} -> #N/A | G72: {=LOOKUP(1,0/(('5.21出货明细'!X:X=$D$54)*('5.21出货明细'!A:A=A72)),'5.21出货明细'!M:M)} -> #N/A | H72: {=LOOKUP(1,0/(('5.21出货明细'!X:X=$D$54)*('5.21出货明细'!A:A=A72)),'5.21出货明细'!P:P)} -> #N/A | I72: {=LOOKUP(1,0/(('5.21出货明细'!X:X=$D$54)*('5.21出货明细'!A:A=A72)),'5.21出货明细'!Q:Q)} -> #N/A | J72: {=LOOKUP(1,0/(('5.21出货明细'!X:X=$D$54)*('5.21出货明细'!A:A=A72)),'5.21出货明细'!AT:AT)} -> #N/A | K72: {=LOOKUP(1,0/(('5.21出货明细'!X:X=$D$54)*('5.21出货明细'!A:A=A72)),'5.21出货明细'!S:S)} -> #N/A
A73: 22 | B73: {=LOOKUP(1,0/(('5.21出货明细'!X:X=$D$54)*('5.21出货明细'!A:A=A73)),'5.21出货明细'!D:D)} -> #N/A | C73: {=LOOKUP(1,0/(('5.21出货明细'!X:X=$D$54)*('5.21出货明细'!A:A=A73)),'5.21出货明细'!G:G&'5.21出货明细'!F:F)} -> #N/A | D73: {=LOOKUP(1,0/(('5.21出货明细'!X:X=$D$54)*('5.21出货明细'!A:A=A73)),'5.21出货明细'!K:K)} -> #N/A | E73: {=LOOKUP(1,0/(('5.21出货明细'!X:X=$D$54)*('5.21出货明细'!A:A=A73)),'5.21出货明细'!J:J)} -> #N/A | F73: {=LOOKUP(1,0/(('5.21出货明细'!X:X=$D$54)*('5.21出货明细'!A:A=A73)),'5.21出货明细'!L:L)} -> #N/A | G73: {=LOOKUP(1,0/(('5.21出货明细'!X:X=$D$54)*('5.21出货明细'!A:A=A73)),'5.21出货明细'!M:M)} -> #N/A | H73: {=LOOKUP(1,0/(('5.21出货明细'!X:X=$D$54)*('5.21出货明细'!A:A=A73)),'5.21出货明细'!P:P)} -> #N/A | I73: {=LOOKUP(1,0/(('5.21出货明细'!X:X=$D$54)*('5.21出货明细'!A:A=A73)),'5.21出货明细'!Q:Q)} -> #N/A | J73: {=LOOKUP(1,0/(('5.21出货明细'!X:X=$D$54)*('5.21出货明细'!A:A=A73)),'5.21出货明细'!AT:AT)} -> #N/A | K73: {=LOOKUP(1,0/(('5.21出货明细'!X:X=$D$54)*('5.21出货明细'!A:A=A73)),'5.21出货明细'!S:S)} -> #N/A
A74: 23 | B74: {=LOOKUP(1,0/(('5.21出货明细'!X:X=$D$54)*('5.21出货明细'!A:A=A74)),'5.21出货明细'!D:D)} -> #N/A | C74: {=LOOKUP(1,0/(('5.21出货明细'!X:X=$D$54)*('5.21出货明细'!A:A=A74)),'5.21出货明细'!G:G&'5.21出货明细'!F:F)} -> #N/A | D74: {=LOOKUP(1,0/(('5.21出货明细'!X:X=$D$54)*('5.21出货明细'!A:A=A74)),'5.21出货明细'!K:K)} -> #N/A | E74: {=LOOKUP(1,0/(('5.21出货明细'!X:X=$D$54)*('5.21出货明细'!A:A=A74)),'5.21出货明细'!J:J)} -> #N/A | F74: {=LOOKUP(1,0/(('5.21出货明细'!X:X=$D$54)*('5.21出货明细'!A:A=A74)),'5.21出货明细'!L:L)} -> #N/A | G74: {=LOOKUP(1,0/(('5.21出货明细'!X:X=$D$54)*('5.21出货明细'!A:A=A74)),'5.21出货明细'!M:M)} -> #N/A | H74: {=LOOKUP(1,0/(('5.21出货明细'!X:X=$D$54)*('5.21出货明细'!A:A=A74)),'5.21出货明细'!P:P)} -> #N/A | I74: {=LOOKUP(1,0/(('5.21出货明细'!X:X=$D$54)*('5.21出货明细'!A:A=A74)),'5.21出货明细'!Q:Q)} -> #N/A | J74: {=LOOKUP(1,0/(('5.21出货明细'!X:X=$D$54)*('5.21出货明细'!A:A=A74)),'5.21出货明细'!AT:AT)} -> #N/A | K74: {=LOOKUP(1,0/(('5.21出货明细'!X:X=$D$54)*('5.21出货明细'!A:A=A74)),'5.21出货明细'!S:S)} -> #N/A
A75: 24 | B75: {=LOOKUP(1,0/(('5.21出货明细'!X:X=$D$54)*('5.21出货明细'!A:A=A75)),'5.21出货明细'!D:D)} -> #N/A | C75: {=LOOKUP(1,0/(('5.21出货明细'!X:X=$D$54)*('5.21出货明细'!A:A=A75)),'5.21出货明细'!G:G&'5.21出货明细'!F:F)} -> #N/A | D75: {=LOOKUP(1,0/(('5.21出货明细'!X:X=$D$54)*('5.21出货明细'!A:A=A75)),'5.21出货明细'!K:K)} -> #N/A | E75: {=LOOKUP(1,0/(('5.21出货明细'!X:X=$D$54)*('5.21出货明细'!A:A=A75)),'5.21出货明细'!J:J)} -> #N/A | F75: {=LOOKUP(1,0/(('5.21出货明细'!X:X=$D$54)*('5.21出货明细'!A:A=A75)),'5.21出货明细'!L:L)} -> #N/A | G75: {=LOOKUP(1,0/(('5.21出货明细'!X:X=$D$54)*('5.21出货明细'!A:A=A75)),'5.21出货明细'!M:M)} -> #N/A | H75: {=LOOKUP(1,0/(('5.21出货明细'!X:X=$D$54)*('5.21出货明细'!A:A=A75)),'5.21出货明细'!P:P)} -> #N/A | I75: {=LOOKUP(1,0/(('5.21出货明细'!X:X=$D$54)*('5.21出货明细'!A:A=A75)),'5.21出货明细'!Q:Q)} -> #N/A | J75: {=LOOKUP(1,0/(('5.21出货明细'!X:X=$D$54)*('5.21出货明细'!A:A=A75)),'5.21出货明细'!AT:AT)} -> #N/A | K75: {=LOOKUP(1,0/(('5.21出货明细'!X:X=$D$54)*('5.21出货明细'!A:A=A75)),'5.21出货明细'!S:S)} -> #N/A
A76: 25 | B76: {=LOOKUP(1,0/(('5.21出货明细'!X:X=$D$54)*('5.21出货明细'!A:A=A76)),'5.21出货明细'!D:D)} -> #N/A | C76: {=LOOKUP(1,0/(('5.21出货明细'!X:X=$D$54)*('5.21出货明细'!A:A=A76)),'5.21出货明细'!G:G&'5.21出货明细'!F:F)} -> #N/A | D76: {=LOOKUP(1,0/(('5.21出货明细'!X:X=$D$54)*('5.21出货明细'!A:A=A76)),'5.21出货明细'!K:K)} -> #N/A | E76: {=LOOKUP(1,0/(('5.21出货明细'!X:X=$D$54)*('5.21出货明细'!A:A=A76)),'5.21出货明细'!J:J)} -> #N/A | F76: {=LOOKUP(1,0/(('5.21出货明细'!X:X=$D$54)*('5.21出货明细'!A:A=A76)),'5.21出货明细'!L:L)} -> #N/A | G76: {=LOOKUP(1,0/(('5.21出货明细'!X:X=$D$54)*('5.21出货明细'!A:A=A76)),'5.21出货明细'!M:M)} -> #N/A | H76: {=LOOKUP(1,0/(('5.21出货明细'!X:X=$D$54)*('5.21出货明细'!A:A=A76)),'5.21出货明细'!P:P)} -> #N/A | I76: {=LOOKUP(1,0/(('5.21出货明细'!X:X=$D$54)*('5.21出货明细'!A:A=A76)),'5.21出货明细'!Q:Q)} -> #N/A | J76: {=LOOKUP(1,0/(('5.21出货明细'!X:X=$D$54)*('5.21出货明细'!A:A=A76)),'5.21出货明细'!AT:AT)} -> #N/A | K76: {=LOOKUP(1,0/(('5.21出货明细'!X:X=$D$54)*('5.21出货明细'!A:A=A76)),'5.21出货明细'!S:S)} -> #N/A
A77: 26 | B77: {=LOOKUP(1,0/(('5.21出货明细'!X:X=$D$54)*('5.21出货明细'!A:A=A77)),'5.21出货明细'!D:D)} -> #N/A | C77: {=LOOKUP(1,0/(('5.21出货明细'!X:X=$D$54)*('5.21出货明细'!A:A=A77)),'5.21出货明细'!G:G&'5.21出货明细'!F:F)} -> #N/A | D77: {=LOOKUP(1,0/(('5.21出货明细'!X:X=$D$54)*('5.21出货明细'!A:A=A77)),'5.21出货明细'!K:K)} -> #N/A | E77: {=LOOKUP(1,0/(('5.21出货明细'!X:X=$D$54)*('5.21出货明细'!A:A=A77)),'5.21出货明细'!J:J)} -> #N/A | F77: {=LOOKUP(1,0/(('5.21出货明细'!X:X=$D$54)*('5.21出货明细'!A:A=A77)),'5.21出货明细'!L:L)} -> #N/A | G77: {=LOOKUP(1,0/(('5.21出货明细'!X:X=$D$54)*('5.21出货明细'!A:A=A77)),'5.21出货明细'!M:M)} -> #N/A | H77: {=LOOKUP(1,0/(('5.21出货明细'!X:X=$D$54)*('5.21出货明细'!A:A=A77)),'5.21出货明细'!P:P)} -> #N/A | I77: {=LOOKUP(1,0/(('5.21出货明细'!X:X=$D$54)*('5.21出货明细'!A:A=A77)),'5.21出货明细'!Q:Q)} -> #N/A | J77: {=LOOKUP(1,0/(('5.21出货明细'!X:X=$D$54)*('5.21出货明细'!A:A=A77)),'5.21出货明细'!AT:AT)} -> #N/A | K77: {=LOOKUP(1,0/(('5.21出货明细'!X:X=$D$54)*('5.21出货明细'!A:A=A77)),'5.21出货明细'!S:S)} -> #N/A
A78: 27 | B78: {=LOOKUP(1,0/(('5.21出货明细'!X:X=$D$54)*('5.21出货明细'!A:A=A78)),'5.21出货明细'!D:D)} -> #N/A | C78: {=LOOKUP(1,0/(('5.21出货明细'!X:X=$D$54)*('5.21出货明细'!A:A=A78)),'5.21出货明细'!G:G&'5.21出货明细'!F:F)} -> #N/A | D78: {=LOOKUP(1,0/(('5.21出货明细'!X:X=$D$54)*('5.21出货明细'!A:A=A78)),'5.21出货明细'!K:K)} -> #N/A | E78: {=LOOKUP(1,0/(('5.21出货明细'!X:X=$D$54)*('5.21出货明细'!A:A=A78)),'5.21出货明细'!J:J)} -> #N/A | F78: {=LOOKUP(1,0/(('5.21出货明细'!X:X=$D$54)*('5.21出货明细'!A:A=A78)),'5.21出货明细'!L:L)} -> #N/A | G78: {=LOOKUP(1,0/(('5.21出货明细'!X:X=$D$54)*('5.21出货明细'!A:A=A78)),'5.21出货明细'!M:M)} -> #N/A | H78: {=LOOKUP(1,0/(('5.21出货明细'!X:X=$D$54)*('5.21出货明细'!A:A=A78)),'5.21出货明细'!P:P)} -> #N/A | I78: {=LOOKUP(1,0/(('5.21出货明细'!X:X=$D$54)*('5.21出货明细'!A:A=A78)),'5.21出货明细'!Q:Q)} -> #N/A | J78: {=LOOKUP(1,0/(('5.21出货明细'!X:X=$D$54)*('5.21出货明细'!A:A=A78)),'5.21出货明细'!AT:AT)} -> #N/A | K78: {=LOOKUP(1,0/(('5.21出货明细'!X:X=$D$54)*('5.21出货明细'!A:A=A78)),'5.21出货明细'!S:S)} -> #N/A
A79: 28 | B79: {=LOOKUP(1,0/(('5.21出货明细'!X:X=$D$54)*('5.21出货明细'!A:A=A79)),'5.21出货明细'!D:D)} -> #N/A | C79: {=LOOKUP(1,0/(('5.21出货明细'!X:X=$D$54)*('5.21出货明细'!A:A=A79)),'5.21出货明细'!G:G&'5.21出货明细'!F:F)} -> #N/A | D79: {=LOOKUP(1,0/(('5.21出货明细'!X:X=$D$54)*('5.21出货明细'!A:A=A79)),'5.21出货明细'!K:K)} -> #N/A | E79: {=LOOKUP(1,0/(('5.21出货明细'!X:X=$D$54)*('5.21出货明细'!A:A=A79)),'5.21出货明细'!J:J)} -> #N/A | F79: {=LOOKUP(1,0/(('5.21出货明细'!X:X=$D$54)*('5.21出货明细'!A:A=A79)),'5.21出货明细'!L:L)} -> #N/A | G79: {=LOOKUP(1,0/(('5.21出货明细'!X:X=$D$54)*('5.21出货明细'!A:A=A79)),'5.21出货明细'!M:M)} -> #N/A | H79: {=LOOKUP(1,0/(('5.21出货明细'!X:X=$D$54)*('5.21出货明细'!A:A=A79)),'5.21出货明细'!P:P)} -> #N/A | I79: {=LOOKUP(1,0/(('5.21出货明细'!X:X=$D$54)*('5.21出货明细'!A:A=A79)),'5.21出货明细'!Q:Q)} -> #N/A | J79: {=LOOKUP(1,0/(('5.21出货明细'!X:X=$D$54)*('5.21出货明细'!A:A=A79)),'5.21出货明细'!AT:AT)} -> #N/A | K79: {=LOOKUP(1,0/(('5.21出货明细'!X:X=$D$54)*('5.21出货明细'!A:A=A79)),'5.21出货明细'!S:S)} -> #N/A
A80: 29 | B80: {=LOOKUP(1,0/(('5.21出货明细'!X:X=$D$54)*('5.21出货明细'!A:A=A80)),'5.21出货明细'!D:D)} -> #N/A | C80: {=LOOKUP(1,0/(('5.21出货明细'!X:X=$D$54)*('5.21出货明细'!A:A=A80)),'5.21出货明细'!G:G&'5.21出货明细'!F:F)} -> #N/A | D80: {=LOOKUP(1,0/(('5.21出货明细'!X:X=$D$54)*('5.21出货明细'!A:A=A80)),'5.21出货明细'!K:K)} -> #N/A | E80: {=LOOKUP(1,0/(('5.21出货明细'!X:X=$D$54)*('5.21出货明细'!A:A=A80)),'5.21出货明细'!J:J)} -> #N/A | F80: {=LOOKUP(1,0/(('5.21出货明细'!X:X=$D$54)*('5.21出货明细'!A:A=A80)),'5.21出货明细'!L:L)} -> #N/A | G80: {=LOOKUP(1,0/(('5.21出货明细'!X:X=$D$54)*('5.21出货明细'!A:A=A80)),'5.21出货明细'!M:M)} -> #N/A | H80: {=LOOKUP(1,0/(('5.21出货明细'!X:X=$D$54)*('5.21出货明细'!A:A=A80)),'5.21出货明细'!P:P)} -> #N/A | I80: {=LOOKUP(1,0/(('5.21出货明细'!X:X=$D$54)*('5.21出货明细'!A:A=A80)),'5.21出货明细'!Q:Q)} -> #N/A | J80: {=LOOKUP(1,0/(('5.21出货明细'!X:X=$D$54)*('5.21出货明细'!A:A=A80)),'5.21出货明细'!AT:AT)} -> #N/A | K80: {=LOOKUP(1,0/(('5.21出货明细'!X:X=$D$54)*('5.21出货明细'!A:A=A80)),'5.21出货明细'!S:S)} -> #N/A
D81: =SUM(D70:D80) -> #N/A | H81: =SUM(H70:H80) -> #N/A | I81: =SUM(I70:I80) -> #N/A | J81: =SUM(J70:J80) -> #N/A | K81: =SUM(K70:K80) -> #N/A
A84: ROYAL REGENT PRODUCTS INDUSTRIES LIMITED
A85: Unit 07-08,12/F,Greenfield Tower,Concordia Plaza,No.1 Science Museum Road,Tsim Sha Tsui,Kowloon,Postal Code:999077,Hong Kong
A89: PACKING LIST
A91: 1 .Shipper: | D91: 2. Packing List Number | H91: 3. Page
A92: ROYAL REGENT PRODUCTS INDUSTRIES LIMITED Unit 07-08,12/F,Greenfield Tower,Concordia Plaza,No.1 Science Museum Road,Tsim Sha Tsui,Kowloon,Postal Code:999077,Hong Kong | D92: =实业发票!H106 -> PR202600278
D93: 4. Packing List Date
D94: =D11 -> 46134
A95: TEL: 00852-2425 0720 FAX: 00852-2424 3407 | D95: 5.PO# | H95: 6. OF#
A96: EMAIL: chloe@royalregenthk.com | D96: =实业合同!H107 -> RPIRRI260278
A97: Attention: Ms Tang
A98: 7. Consignee:
A99: PT. ROYAL REGENT INDONESIA | D99: 8. Container | H99: 9. Seal Number
A100: Tax ID: 61.146.021.3-513.000 | D100: =D17 -> BMOU6019197 | H100: =H17 -> EMCRZS9184
A101: KAWASAN INDUSTRI KENDAL, JL. WANAMARTA RAYA NO. 33A & 35,
A102: BRANGSONG, BRANGSONG, KAB. KENDAL, JAWA TENGAH, 51371,
A103: INDONESIA
A104: Tel.: 62 895-3269-82429
A105: Attention: Novi Azka Tiurlan Putri Marpaung
A106: Email: exim@royalregentid.com，exim2@royalregentid.com，exim3@royalregentid.com
A107: 序号 serial number | B107: 型 号 Item No. | C107: 品名描述 Names and Descriptions | D107: 数 量 Quantities | E107: 单位 Unit | F107: 数 量 Quantities | G107: 单位 Unit | H107: 毛重 Gross Weight Kgs | I107: 净重 Net Weight Kgs | J107: 箱数 Carton No. | K107: 立方数 CBM
A108: 30 | B108: {=LOOKUP(1,0/(('5.21出货明细'!X:X=$D$92)*('5.21出货明细'!A:A=A108)),'5.21出货明细'!D:D)} -> #N/A | C108: {=LOOKUP(1,0/(('5.21出货明细'!X:X=$D$92)*('5.21出货明细'!A:A=A108)),'5.21出货明细'!G:G&'5.21出货明细'!F:F)} -> #N/A | D108: {=LOOKUP(1,0/(('5.21出货明细'!X:X=$D$92)*('5.21出货明细'!A:A=A108)),'5.21出货明细'!K:K)} -> #N/A | E108: {=LOOKUP(1,0/(('5.21出货明细'!X:X=$D$92)*('5.21出货明细'!A:A=A108)),'5.21出货明细'!J:J)} -> #N/A | F108: {=LOOKUP(1,0/(('5.21出货明细'!X:X=$D$92)*('5.21出货明细'!A:A=A108)),'5.21出货明细'!L:L)} -> #N/A | G108: {=LOOKUP(1,0/(('5.21出货明细'!X:X=$D$92)*('5.21出货明细'!A:A=A108)),'5.21出货明细'!M:M)} -> #N/A | H108: {=LOOKUP(1,0/(('5.21出货明细'!X:X=$D$92)*('5.21出货明细'!A:A=A108)),'5.21出货明细'!P:P)} -> #N/A | I108: {=LOOKUP(1,0/(('5.21出货明细'!X:X=$D$92)*('5.21出货明细'!A:A=A108)),'5.21出货明细'!Q:Q)} -> #N/A | J108: {=LOOKUP(1,0/(('5.21出货明细'!X:X=$D$92)*('5.21出货明细'!A:A=A108)),'5.21出货明细'!AT:AT)} -> #N/A | K108: {=LOOKUP(1,0/(('5.21出货明细'!X:X=$D$92)*('5.21出货明细'!A:A=A108)),'5.21出货明细'!S:S)} -> #N/A
A109: 31 | B109: {=LOOKUP(1,0/(('5.21出货明细'!X:X=$D$92)*('5.21出货明细'!A:A=A109)),'5.21出货明细'!D:D)} -> #N/A | C109: {=LOOKUP(1,0/(('5.21出货明细'!X:X=$D$92)*('5.21出货明细'!A:A=A109)),'5.21出货明细'!G:G&'5.21出货明细'!F:F)} -> #N/A | D109: {=LOOKUP(1,0/(('5.21出货明细'!X:X=$D$92)*('5.21出货明细'!A:A=A109)),'5.21出货明细'!K:K)} -> #N/A | E109: {=LOOKUP(1,0/(('5.21出货明细'!X:X=$D$92)*('5.21出货明细'!A:A=A109)),'5.21出货明细'!J:J)} -> #N/A | F109: {=LOOKUP(1,0/(('5.21出货明细'!X:X=$D$92)*('5.21出货明细'!A:A=A109)),'5.21出货明细'!L:L)} -> #N/A | G109: {=LOOKUP(1,0/(('5.21出货明细'!X:X=$D$92)*('5.21出货明细'!A:A=A109)),'5.21出货明细'!M:M)} -> #N/A | H109: {=LOOKUP(1,0/(('5.21出货明细'!X:X=$D$92)*('5.21出货明细'!A:A=A109)),'5.21出货明细'!P:P)} -> #N/A | I109: {=LOOKUP(1,0/(('5.21出货明细'!X:X=$D$92)*('5.21出货明细'!A:A=A109)),'5.21出货明细'!Q:Q)} -> #N/A | J109: {=LOOKUP(1,0/(('5.21出货明细'!X:X=$D$92)*('5.21出货明细'!A:A=A109)),'5.21出货明细'!AT:AT)} -> #N/A | K109: {=LOOKUP(1,0/(('5.21出货明细'!X:X=$D$92)*('5.21出货明细'!A:A=A109)),'5.21出货明细'!S:S)} -> #N/A
A110: 32 | B110: {=LOOKUP(1,0/(('5.21出货明细'!X:X=$D$92)*('5.21出货明细'!A:A=A110)),'5.21出货明细'!D:D)} -> #N/A | C110: {=LOOKUP(1,0/(('5.21出货明细'!X:X=$D$92)*('5.21出货明细'!A:A=A110)),'5.21出货明细'!G:G&'5.21出货明细'!F:F)} -> #N/A | D110: {=LOOKUP(1,0/(('5.21出货明细'!X:X=$D$92)*('5.21出货明细'!A:A=A110)),'5.21出货明细'!K:K)} -> #N/A | E110: {=LOOKUP(1,0/(('5.21出货明细'!X:X=$D$92)*('5.21出货明细'!A:A=A110)),'5.21出货明细'!J:J)} -> #N/A | F110: {=LOOKUP(1,0/(('5.21出货明细'!X:X=$D$92)*('5.21出货明细'!A:A=A110)),'5.21出货明细'!L:L)} -> #N/A | G110: {=LOOKUP(1,0/(('5.21出货明细'!X:X=$D$92)*('5.21出货明细'!A:A=A110)),'5.21出货明细'!M:M)} -> #N/A | H110: {=LOOKUP(1,0/(('5.21出货明细'!X:X=$D$92)*('5.21出货明细'!A:A=A110)),'5.21出货明细'!P:P)} -> #N/A | I110: {=LOOKUP(1,0/(('5.21出货明细'!X:X=$D$92)*('5.21出货明细'!A:A=A110)),'5.21出货明细'!Q:Q)} -> #N/A | J110: {=LOOKUP(1,0/(('5.21出货明细'!X:X=$D$92)*('5.21出货明细'!A:A=A110)),'5.21出货明细'!AT:AT)} -> #N/A | K110: {=LOOKUP(1,0/(('5.21出货明细'!X:X=$D$92)*('5.21出货明细'!A:A=A110)),'5.21出货明细'!S:S)} -> #N/A
A111: 33 | B111: {=LOOKUP(1,0/(('5.21出货明细'!X:X=$D$92)*('5.21出货明细'!A:A=A111)),'5.21出货明细'!D:D)} -> #N/A | C111: {=LOOKUP(1,0/(('5.21出货明细'!X:X=$D$92)*('5.21出货明细'!A:A=A111)),'5.21出货明细'!G:G&'5.21出货明细'!F:F)} -> #N/A | D111: {=LOOKUP(1,0/(('5.21出货明细'!X:X=$D$92)*('5.21出货明细'!A:A=A111)),'5.21出货明细'!K:K)} -> #N/A | E111: {=LOOKUP(1,0/(('5.21出货明细'!X:X=$D$92)*('5.21出货明细'!A:A=A111)),'5.21出货明细'!J:J)} -> #N/A | F111: {=LOOKUP(1,0/(('5.21出货明细'!X:X=$D$92)*('5.21出货明细'!A:A=A111)),'5.21出货明细'!L:L)} -> #N/A | G111: {=LOOKUP(1,0/(('5.21出货明细'!X:X=$D$92)*('5.21出货明细'!A:A=A111)),'5.21出货明细'!M:M)} -> #N/A | H111: {=LOOKUP(1,0/(('5.21出货明细'!X:X=$D$92)*('5.21出货明细'!A:A=A111)),'5.21出货明细'!P:P)} -> #N/A | I111: {=LOOKUP(1,0/(('5.21出货明细'!X:X=$D$92)*('5.21出货明细'!A:A=A111)),'5.21出货明细'!Q:Q)} -> #N/A | J111: {=LOOKUP(1,0/(('5.21出货明细'!X:X=$D$92)*('5.21出货明细'!A:A=A111)),'5.21出货明细'!AT:AT)} -> #N/A | K111: {=LOOKUP(1,0/(('5.21出货明细'!X:X=$D$92)*('5.21出货明细'!A:A=A111)),'5.21出货明细'!S:S)} -> #N/A
A112: 34 | B112: {=LOOKUP(1,0/(('5.21出货明细'!X:X=$D$92)*('5.21出货明细'!A:A=A112)),'5.21出货明细'!D:D)} -> #N/A | C112: {=LOOKUP(1,0/(('5.21出货明细'!X:X=$D$92)*('5.21出货明细'!A:A=A112)),'5.21出货明细'!G:G&'5.21出货明细'!F:F)} -> #N/A | D112: {=LOOKUP(1,0/(('5.21出货明细'!X:X=$D$92)*('5.21出货明细'!A:A=A112)),'5.21出货明细'!K:K)} -> #N/A | E112: {=LOOKUP(1,0/(('5.21出货明细'!X:X=$D$92)*('5.21出货明细'!A:A=A112)),'5.21出货明细'!J:J)} -> #N/A | F112: {=LOOKUP(1,0/(('5.21出货明细'!X:X=$D$92)*('5.21出货明细'!A:A=A112)),'5.21出货明细'!L:L)} -> #N/A | G112: {=LOOKUP(1,0/(('5.21出货明细'!X:X=$D$92)*('5.21出货明细'!A:A=A112)),'5.21出货明细'!M:M)} -> #N/A | H112: {=LOOKUP(1,0/(('5.21出货明细'!X:X=$D$92)*('5.21出货明细'!A:A=A112)),'5.21出货明细'!P:P)} -> #N/A | I112: {=LOOKUP(1,0/(('5.21出货明细'!X:X=$D$92)*('5.21出货明细'!A:A=A112)),'5.21出货明细'!Q:Q)} -> #N/A | J112: {=LOOKUP(1,0/(('5.21出货明细'!X:X=$D$92)*('5.21出货明细'!A:A=A112)),'5.21出货明细'!AT:AT)} -> #N/A | K112: {=LOOKUP(1,0/(('5.21出货明细'!X:X=$D$92)*('5.21出货明细'!A:A=A112)),'5.21出货明细'!S:S)} -> #N/A
A113: 35 | B113: {=LOOKUP(1,0/(('5.21出货明细'!X:X=$D$92)*('5.21出货明细'!A:A=A113)),'5.21出货明细'!D:D)} -> #N/A | C113: {=LOOKUP(1,0/(('5.21出货明细'!X:X=$D$92)*('5.21出货明细'!A:A=A113)),'5.21出货明细'!G:G&'5.21出货明细'!F:F)} -> #N/A | D113: {=LOOKUP(1,0/(('5.21出货明细'!X:X=$D$92)*('5.21出货明细'!A:A=A113)),'5.21出货明细'!K:K)} -> #N/A | E113: {=LOOKUP(1,0/(('5.21出货明细'!X:X=$D$92)*('5.21出货明细'!A:A=A113)),'5.21出货明细'!J:J)} -> #N/A | F113: {=LOOKUP(1,0/(('5.21出货明细'!X:X=$D$92)*('5.21出货明细'!A:A=A113)),'5.21出货明细'!L:L)} -> #N/A | G113: {=LOOKUP(1,0/(('5.21出货明细'!X:X=$D$92)*('5.21出货明细'!A:A=A113)),'5.21出货明细'!M:M)} -> #N/A | H113: {=LOOKUP(1,0/(('5.21出货明细'!X:X=$D$92)*('5.21出货明细'!A:A=A113)),'5.21出货明细'!P:P)} -> #N/A | I113: {=LOOKUP(1,0/(('5.21出货明细'!X:X=$D$92)*('5.21出货明细'!A:A=A113)),'5.21出货明细'!Q:Q)} -> #N/A | J113: {=LOOKUP(1,0/(('5.21出货明细'!X:X=$D$92)*('5.21出货明细'!A:A=A113)),'5.21出货明细'!AT:AT)} -> #N/A | K113: {=LOOKUP(1,0/(('5.21出货明细'!X:X=$D$92)*('5.21出货明细'!A:A=A113)),'5.21出货明细'!S:S)} -> #N/A
A114: 36 | B114: {=LOOKUP(1,0/(('5.21出货明细'!X:X=$D$92)*('5.21出货明细'!A:A=A114)),'5.21出货明细'!D:D)} -> #N/A | C114: {=LOOKUP(1,0/(('5.21出货明细'!X:X=$D$92)*('5.21出货明细'!A:A=A114)),'5.21出货明细'!G:G&'5.21出货明细'!F:F)} -> #N/A | D114: {=LOOKUP(1,0/(('5.21出货明细'!X:X=$D$92)*('5.21出货明细'!A:A=A114)),'5.21出货明细'!K:K)} -> #N/A | E114: {=LOOKUP(1,0/(('5.21出货明细'!X:X=$D$92)*('5.21出货明细'!A:A=A114)),'5.21出货明细'!J:J)} -> #N/A | F114: {=LOOKUP(1,0/(('5.21出货明细'!X:X=$D$92)*('5.21出货明细'!A:A=A114)),'5.21出货明细'!L:L)} -> #N/A | G114: {=LOOKUP(1,0/(('5.21出货明细'!X:X=$D$92)*('5.21出货明细'!A:A=A114)),'5.21出货明细'!M:M)} -> #N/A | H114: {=LOOKUP(1,0/(('5.21出货明细'!X:X=$D$92)*('5.21出货明细'!A:A=A114)),'5.21出货明细'!P:P)} -> #N/A | I114: {=LOOKUP(1,0/(('5.21出货明细'!X:X=$D$92)*('5.21出货明细'!A:A=A114)),'5.21出货明细'!Q:Q)} -> #N/A | J114: {=LOOKUP(1,0/(('5.21出货明细'!X:X=$D$92)*('5.21出货明细'!A:A=A114)),'5.21出货明细'!AT:AT)} -> #N/A | K114: {=LOOKUP(1,0/(('5.21出货明细'!X:X=$D$92)*('5.21出货明细'!A:A=A114)),'5.21出货明细'!S:S)} -> #N/A
A115: 37 | B115: {=LOOKUP(1,0/(('5.21出货明细'!X:X=$D$92)*('5.21出货明细'!A:A=A115)),'5.21出货明细'!D:D)} -> #N/A | C115: {=LOOKUP(1,0/(('5.21出货明细'!X:X=$D$92)*('5.21出货明细'!A:A=A115)),'5.21出货明细'!G:G&'5.21出货明细'!F:F)} -> #N/A | D115: {=LOOKUP(1,0/(('5.21出货明细'!X:X=$D$92)*('5.21出货明细'!A:A=A115)),'5.21出货明细'!K:K)} -> #N/A | E115: {=LOOKUP(1,0/(('5.21出货明细'!X:X=$D$92)*('5.21出货明细'!A:A=A115)),'5.21出货明细'!J:J)} -> #N/A | F115: {=LOOKUP(1,0/(('5.21出货明细'!X:X=$D$92)*('5.21出货明细'!A:A=A115)),'5.21出货明细'!L:L)} -> #N/A | G115: {=LOOKUP(1,0/(('5.21出货明细'!X:X=$D$92)*('5.21出货明细'!A:A=A115)),'5.21出货明细'!M:M)} -> #N/A | H115: {=LOOKUP(1,0/(('5.21出货明细'!X:X=$D$92)*('5.21出货明细'!A:A=A115)),'5.21出货明细'!P:P)} -> #N/A | I115: {=LOOKUP(1,0/(('5.21出货明细'!X:X=$D$92)*('5.21出货明细'!A:A=A115)),'5.21出货明细'!Q:Q)} -> #N/A | J115: {=LOOKUP(1,0/(('5.21出货明细'!X:X=$D$92)*('5.21出货明细'!A:A=A115)),'5.21出货明细'!AT:AT)} -> #N/A | K115: {=LOOKUP(1,0/(('5.21出货明细'!X:X=$D$92)*('5.21出货明细'!A:A=A115)),'5.21出货明细'!S:S)} -> #N/A
A116: 38 | B116: {=LOOKUP(1,0/(('5.21出货明细'!X:X=$D$92)*('5.21出货明细'!A:A=A116)),'5.21出货明细'!D:D)} -> #N/A | C116: {=LOOKUP(1,0/(('5.21出货明细'!X:X=$D$92)*('5.21出货明细'!A:A=A116)),'5.21出货明细'!G:G&'5.21出货明细'!F:F)} -> #N/A | D116: {=LOOKUP(1,0/(('5.21出货明细'!X:X=$D$92)*('5.21出货明细'!A:A=A116)),'5.21出货明细'!K:K)} -> #N/A | E116: {=LOOKUP(1,0/(('5.21出货明细'!X:X=$D$92)*('5.21出货明细'!A:A=A116)),'5.21出货明细'!J:J)} -> #N/A | F116: {=LOOKUP(1,0/(('5.21出货明细'!X:X=$D$92)*('5.21出货明细'!A:A=A116)),'5.21出货明细'!L:L)} -> #N/A | G116: {=LOOKUP(1,0/(('5.21出货明细'!X:X=$D$92)*('5.21出货明细'!A:A=A116)),'5.21出货明细'!M:M)} -> #N/A | H116: {=LOOKUP(1,0/(('5.21出货明细'!X:X=$D$92)*('5.21出货明细'!A:A=A116)),'5.21出货明细'!P:P)} -> #N/A | I116: {=LOOKUP(1,0/(('5.21出货明细'!X:X=$D$92)*('5.21出货明细'!A:A=A116)),'5.21出货明细'!Q:Q)} -> #N/A | J116: {=LOOKUP(1,0/(('5.21出货明细'!X:X=$D$92)*('5.21出货明细'!A:A=A116)),'5.21出货明细'!AT:AT)} -> #N/A | K116: {=LOOKUP(1,0/(('5.21出货明细'!X:X=$D$92)*('5.21出货明细'!A:A=A116)),'5.21出货明细'!S:S)} -> #N/A
A117: 39 | B117: {=LOOKUP(1,0/(('5.21出货明细'!X:X=$D$92)*('5.21出货明细'!A:A=A117)),'5.21出货明细'!D:D)} -> #N/A | C117: {=LOOKUP(1,0/(('5.21出货明细'!X:X=$D$92)*('5.21出货明细'!A:A=A117)),'5.21出货明细'!G:G&'5.21出货明细'!F:F)} -> #N/A | D117: {=LOOKUP(1,0/(('5.21出货明细'!X:X=$D$92)*('5.21出货明细'!A:A=A117)),'5.21出货明细'!K:K)} -> #N/A | E117: {=LOOKUP(1,0/(('5.21出货明细'!X:X=$D$92)*('5.21出货明细'!A:A=A117)),'5.21出货明细'!J:J)} -> #N/A | F117: {=LOOKUP(1,0/(('5.21出货明细'!X:X=$D$92)*('5.21出货明细'!A:A=A117)),'5.21出货明细'!L:L)} -> #N/A | G117: {=LOOKUP(1,0/(('5.21出货明细'!X:X=$D$92)*('5.21出货明细'!A:A=A117)),'5.21出货明细'!M:M)} -> #N/A | H117: {=LOOKUP(1,0/(('5.21出货明细'!X:X=$D$92)*('5.21出货明细'!A:A=A117)),'5.21出货明细'!P:P)} -> #N/A | I117: {=LOOKUP(1,0/(('5.21出货明细'!X:X=$D$92)*('5.21出货明细'!A:A=A117)),'5.21出货明细'!Q:Q)} -> #N/A | J117: {=LOOKUP(1,0/(('5.21出货明细'!X:X=$D$92)*('5.21出货明细'!A:A=A117)),'5.21出货明细'!AT:AT)} -> #N/A | K117: {=LOOKUP(1,0/(('5.21出货明细'!X:X=$D$92)*('5.21出货明细'!A:A=A117)),'5.21出货明细'!S:S)} -> #N/A
A118: 40 | B118: {=LOOKUP(1,0/(('5.21出货明细'!X:X=$D$92)*('5.21出货明细'!A:A=A118)),'5.21出货明细'!D:D)} -> #N/A | C118: {=LOOKUP(1,0/(('5.21出货明细'!X:X=$D$92)*('5.21出货明细'!A:A=A118)),'5.21出货明细'!G:G&'5.21出货明细'!F:F)} -> #N/A | D118: {=LOOKUP(1,0/(('5.21出货明细'!X:X=$D$92)*('5.21出货明细'!A:A=A118)),'5.21出货明细'!K:K)} -> #N/A | E118: {=LOOKUP(1,0/(('5.21出货明细'!X:X=$D$92)*('5.21出货明细'!A:A=A118)),'5.21出货明细'!J:J)} -> #N/A | F118: {=LOOKUP(1,0/(('5.21出货明细'!X:X=$D$92)*('5.21出货明细'!A:A=A118)),'5.21出货明细'!L:L)} -> #N/A | G118: {=LOOKUP(1,0/(('5.21出货明细'!X:X=$D$92)*('5.21出货明细'!A:A=A118)),'5.21出货明细'!M:M)} -> #N/A | H118: {=LOOKUP(1,0/(('5.21出货明细'!X:X=$D$92)*('5.21出货明细'!A:A=A118)),'5.21出货明细'!P:P)} -> #N/A | I118: {=LOOKUP(1,0/(('5.21出货明细'!X:X=$D$92)*('5.21出货明细'!A:A=A118)),'5.21出货明细'!Q:Q)} -> #N/A | J118: {=LOOKUP(1,0/(('5.21出货明细'!X:X=$D$92)*('5.21出货明细'!A:A=A118)),'5.21出货明细'!AT:AT)} -> #N/A | K118: {=LOOKUP(1,0/(('5.21出货明细'!X:X=$D$92)*('5.21出货明细'!A:A=A118)),'5.21出货明细'!S:S)} -> #N/A
A119: 41 | B119: {=LOOKUP(1,0/(('5.21出货明细'!X:X=$D$92)*('5.21出货明细'!A:A=A119)),'5.21出货明细'!D:D)} -> #N/A | C119: {=LOOKUP(1,0/(('5.21出货明细'!X:X=$D$92)*('5.21出货明细'!A:A=A119)),'5.21出货明细'!G:G&'5.21出货明细'!F:F)} -> #N/A | D119: {=LOOKUP(1,0/(('5.21出货明细'!X:X=$D$92)*('5.21出货明细'!A:A=A119)),'5.21出货明细'!K:K)} -> #N/A | E119: {=LOOKUP(1,0/(('5.21出货明细'!X:X=$D$92)*('5.21出货明细'!A:A=A119)),'5.21出货明细'!J:J)} -> #N/A | F119: {=LOOKUP(1,0/(('5.21出货明细'!X:X=$D$92)*('5.21出货明细'!A:A=A119)),'5.21出货明细'!L:L)} -> #N/A | G119: {=LOOKUP(1,0/(('5.21出货明细'!X:X=$D$92)*('5.21出货明细'!A:A=A119)),'5.21出货明细'!M:M)} -> #N/A | H119: {=LOOKUP(1,0/(('5.21出货明细'!X:X=$D$92)*('5.21出货明细'!A:A=A119)),'5.21出货明细'!P:P)} -> #N/A | I119: {=LOOKUP(1,0/(('5.21出货明细'!X:X=$D$92)*('5.21出货明细'!A:A=A119)),'5.21出货明细'!Q:Q)} -> #N/A | J119: {=LOOKUP(1,0/(('5.21出货明细'!X:X=$D$92)*('5.21出货明细'!A:A=A119)),'5.21出货明细'!AT:AT)} -> #N/A | K119: {=LOOKUP(1,0/(('5.21出货明细'!X:X=$D$92)*('5.21出货明细'!A:A=A119)),'5.21出货明细'!S:S)} -> #N/A
D120: =SUM(D108:D119) -> #N/A | H120: =SUM(H108:H119) -> #N/A | I120: =SUM(I108:I119) -> #N/A | J120: =SUM(J108:J119) -> #N/A | K120: =SUM(K108:K119) -> #N/A
A123: ROYAL REGENT PRODUCTS INDUSTRIES LIMITED
...

Sheet 5.21出货明细
A3: 序号 serial number | B3: 中国HSCODE （China） | C3: 印尼HS CODE (Indonesia) | D3: 货号 Item No. | E3: 套公式名称栏 | F3: 产品中文名称 Chinese name of the product | G3: 产品英文名称 English name of the product | H3: 规格 specification | I3: 类别 kategori | J3: 单位 Unit | K3: 送货KG重量 Quantity | L3: 送货数量 Product quantity | M3: 单位 Unit | N3: 采购单价（换成港币） Purchase price | O3: 采购金额Purchase Amount | P3: 毛重总重 Total Gross weight（KGM） | Q3: 净重总重Total Net weight（KGM） | R3: 立方数/每箱CBM/Per carton | S3: 总立方数Total CBM | T3: 图片 Picture | U3: 产品用途 product use | V3: 合同号码 Contract No. | W3: 合同日期 Date of contract | X3: 发票号 Invoice No. | Y3: 发票日期 Date of Invoice | Z3: 发票单价 Unit price on invoice | AA3: 金额 Invoice amount | AB3: 发票合计金额Invoice total amount | AC3: 柜号 Container No. | AD3: 走柜日期 Shipping date | AE3: 提单号 Bl No. | AF3: 预计到港日期 ETA PORT | AG3: 实际到厂日期 Actual arrival date | AH3: Vessel Name/Voyage No. | AI3: 总集装箱运费金额（中国运费） Total Container Freight Amount (China's Freight) | AJ3: 货运代理运输费用 Forwarder Transportation Costs (Indonesia Freight) | AK3: Actual freight for product | AL3: 供应商 Supplier | AM3: 采购单日期 Date of purchase order | AN3: 采购单号 PO No. | AO3: 采购单价 Purchase price | AP3: 采购金额Purchase Amount | AQ3: 采购总额 Total Amount | AR3: 报关出口公司 | AS3: 提单抬头 | AT3: 箱数 Carton No. | AU3: 每箱数量 | AV3: 卡板 | AW3: 长 Length | AX3: 宽 Width | AY3: 高 Height | AZ3: 物料编码 | BA3: 使用部门 | BB3: 每箱重量 | BC3: 单个毛重 | BD3: 单个净重 | BE3: 备注
A4: 1 | B4: 9503009000 | C4: 392690 | D4: 721262-V2 | F4: 玩具配件包装扣 | G4: Plastic toy accessory packaging buckle | I4: 塑胶 | J4: KGM | K4: =52*2.03+1.74 -> 107.3 | L4: 111000 | M4: PCS | P4: =2.24*52+1.95 -> 118.43 | Q4: =K4 -> 107.3 | R4: =AW4*AX4*AY4/28316.75*0.0283 -> 0.010681628 | S4: =ROUND(R4*AT4,2) -> 0.57 | U4: 产品配件 | V4: RPIRRI260152 | W4: 46048 | X4: PR202600152 | Y4: 46048 | Z4: =AO4 -> 11 | AA4: =K4*Z4 -> 1180.3 | AL4: 华登（河源）玩具制品有限公司 | AM4: 46153 | AN4: E260420-06 | AO4: 11 | AP4: =AO4*K4 -> 1180.3 | AR4: 华登（河源）玩具制品有限公司 | AS4: 華登製品實業有限公司 | AT4: 53 | AU4: 2100pcs*52箱 1800pcs*1箱 | AW4: 27 | AX4: 14.5 | AY4: 27.3 | BB4: 2.24kg*52箱 1.95kg*1箱 | BC4: 0.001066 | BD4: =0.97/1000 -> 0.00097
A5: 2 | B5: 9503009000 | C5: 392690 | D5: 721262-V2 | F5: 玩具配件绑片 | G5: Plastic toy accessory binding pieces | I5: 塑胶 | J5: KGM | K5: =4.63*10 -> 46.3 | L5: 35000 | M5: PCS | P5: =5.01*10 -> 50.1 | Q5: =K5 -> 46.3 | R5: =AW5*AX5*AY5/28316.75*0.0283 -> 0.044220877 | S5: =ROUND(R5*AT5,2) -> 0.44 | U5: 产品配件 | V5: RPIRRI260152 | W5: 46048 | X5: PR202600152 | Y5: 46048 | Z5: =AO5 -> 5 | AA5: =K5*Z5 -> 231.5 | AL5: 华登（河源）玩具制品有限公司 | AM5: 46153 | AN5: E260420-06 | AO5: 5 | AP5: =AO5*K5 -> 231.5 | AR5: 华登（河源）玩具制品有限公司 | AS5: 華登製品實業有限公司 | AT5: 10 | AU5: 3500pcs | AW5: 53 | AX5: 28.3 | AY5: 29.5 | BB5: 5.01 | BC5: 0.001431 | BD5: =1.3/1000 -> 0.0013

Sheet 商品汇总表
A1: 商品编号 | B1: 商品名称 | D1: 货物品名及规格
A2: 8483409090 | B2: 0.37KW减速电机 | D2: 1|0|电磁感应定律|工业生产用|台成|YSF-71MI-4
A3: 8483409090 | B3: 0.55KW减速电机 | D3: 1|0|电磁感应定律|工业生产用|台成|YSF-80MI-4
A4: 5806109000 | B4: 1 1/2"黑色婴儿魔术贴（勾面） | D4: 0|0|织造方法：机织，起绒方式：绳绒|尼龙100%|幅宽：4-6
A5: 5806109000 | B5: 1 1/2"黑色婴儿魔术贴（毛面） | D5: 0|0|织造方法：机织，起绒方式：绳绒|尼龙100%|幅宽：4-6
A6: 5808100000 | B6: 1"黑色涤纶带PANTONE Black C（100Y/卷） | D6: 0|0|成卷|100%涤纶|
A7: 5808100000 | B7: 1"绿色树叶花边3500C | D7: 0|0|成卷|100%涤纶|
A8: 5808100000 | B8: 1.25"黑色半圆花边 | D8: 0|0|成卷|100%涤纶|
A9: 5806109000 | B9: 1.5"黑色魔术贴（勾） | D9: 0|0|织造方法：机织，起绒方式：绳绒|尼龙100%|幅宽：4-6
A10: 5806109000 | B10: 1.5"黑色魔术贴（毛） | D10: 0|0|织造方法：机织，起绒方式：绳绒|尼龙100%|幅宽：4-6
A11: 5806320000 | B11: 1.6CM白色背胶魔术贴
A12: 5808100000 | B12: 1/2"黑色丝带PANTONE Black 6 C（50Y/卷） | D12: 0|0|成卷|100%涤纶|
A13: 5806320000 | B13: 1/4"白色普通棉带（700Y/卷） | D13: 0|0|成卷|100%涤纶|
A14: 5808100000 | B14: 1/4"白色丈根（100Y/卷） | D14: 0|0|织造方法：机织，经编|涤纶100%|幅宽：63
A15: 5806320000 | B15: 1/4"粉色丝带PANTONE 1905 C | D15: 0|0|成卷|100%涤纶|
A16: 5808100000 | B16: 1/4"黑色涤纶带PANTONE Black 6 C（100Y/卷） | D16: 0|0|成卷|100%涤纶|
A17: 5808100000 | B17: 1/4"黑色色丁丝带（25Y/卷） | D17: 0|0|成卷|100%涤纶|
A18: 5808100000 | B18: 1/4"黑色丝带PANTONE Black 6 C（25Y/卷 | D18: 0|0|成卷|100%涤纶|
A19: 5808100000 | B19: 1/4"黑色丈根（100Y/卷） | D19: 0|0|织造方法：机织，经编|涤纶100%|幅宽：63
A20: 5808100000 | B20: 1/4"黄色色丁丝带PANTONE 144 C（25Y/卷） | D20: 0|0|成卷|100%涤纶|
A21: 5808100000 | B21: 1/4"金色葱带（200Y/卷） | D21: 0|0|成卷|100%涤纶|
A22: 5806320000 | B22: 1/4"蓝色丝带PANTONE 2146 C | D22: 0|0|成卷|100%涤纶|
A23: 5808100000 | B23: 1/4"绿色丝带PANTONE 3500 C | D23: 0|0|成卷|100%涤纶|
A24: 5808100090 | B24: 1/8"白色丈根
A25: 5808100000 | B25: 1/8"黑色丈根（145Y/卷） | D25: 0|0|成卷|涤纶+橡胶|
A26: 5806109000 | B26: 2"白色魔术贴（勾） | D26: 0|0|织造方法：机织，起绒方式：绳绒|尼龙100%|幅宽：4-6
A27: 5806109000 | B27: 2"白色魔术贴（毛） | D27: 0|0|织造方法：机织，起绒方式：绳绒|尼龙100%|幅宽：4-6
A28: 5806109000 | B28: 2"黑色魔术贴（勾） | D28: 0|0|织造方法：机织，起绒方式：绳绒|尼龙100%|幅宽：4-6
A29: 5806109000 | B29: 2"黑色魔术贴（毛） | D29: 0|0|织造方法：机织，起绒方式：绳绒|尼龙100%|幅宽：4-6
A30: 5808100000 | B30: 2"黑色针织松紧 | D30: 0|0|成卷|100%涤纶|
A31: 8479899990 | B31: 2.6自动螺丝机 | D31: 1|0|工业装螺丝用|自动筛选出不合格的螺丝|ANSHUN|AS-900
A32: 4819100000 | B32: 20155371-GEN发光飞碟彩卡 | D32: 0|0|瓦楞纸制|可折叠
A33: 4819100000 | B33: 20156724 GEN 红色彩卡 | D33: 0|0|瓦楞纸制|可折叠
A34: 4819100000 | B34: 20156733 GML 黄色彩卡 | D34: 0|0|瓦楞纸制|可折叠
A35: 4819100000 | B35: 20156801 GEN 红色彩卡 | D35: 0|0|瓦楞纸制|可折叠
A36: 4819100000 | B36: 20156803 GEN彩卡 | D36: 0|0|瓦楞纸制|可折叠
... A163: 9503009000 | B163: LED灯板 | D163: 0|0|玩具生产用|发音器零件|无牌||
A164: 8480790000 | B164: Logo 模具
A165: 8480790000 | B165: Logo底模
A166: 4819100000 | B166: NTL 狼崽彩盒 | D166: 0|0|瓦楞纸制|可折叠
A167: 4819100000 | B167: NTL 狼崽内卡 | D167: 0|0|瓦楞纸制|可折叠
A168: 3926909090 | B168: OPP带 | D168: 0|0|装配玩具生产用|塑胶料制|无牌|无型号||
A169: 3923210000 | B169: OPP胶带 | D169: 0|0|装配玩具生产用|塑胶料制|无牌|无型号
A170: 7318159090 | B170: PB螺丝 | D170: 0|0|铁制|353MPa|无牌|1008|2.0mm-4.0mm
A171: 7318159090 | B171: PB螺丝2.6*6PB | D171: 0|0|铁制|353MPa|无牌|1008|2.0mm-4.0mm
A172: 7318159090 | B172: PB螺丝2.6*8PB | D172: 0|0|铁制|353MPa|无牌|1008|2.0mm-4.0mm
A173: 7326909000 | B173: PCBA电子板测试架 | D173: 0|0|装配玩具用,非工业用|钢铁制|冲压
A174: 8480790000 | B174: PCBA电子板装配打螺丝底模 | D174: 0|0|生产用|塑胶|无牌|无型号|五金+塑胶|使用型模，装配产品
A175: 9031809090 | B175: PCB万能测试架 | D175: 0|0|生产用|检测出电路板的电气导通性能|测试和验证电子电路板功能|无牌|无型号
A176: 4821100000 | B176: PDQ盒-FSC | D176: 0|0|纸制|印制|53*43*12
A177: 3923210000 | B177: PE 光身胶袋 | D177: 0|0|玩具包装生产用|PE料制|无牌|无型号||
... A208: 3923900000 | B208: 杯吸塑 | D208: 0|0|装配玩具生产用|塑胶料制|无牌|无型号||
A209: 7326909000 | B209: 杯子试气保压测试夹具
A210: 4819200000 | B210: 背部加强卡 | D210: 0|0|瓦楞纸制|可折叠||
A211: 3926909090 | B211: 泵杆密封圈 | D211: 0|0|装配玩具生产用|塑胶料制|无牌|无型号||
A212: 9405390000 | B212: 变压器3.5V6W带AG13遥控器5条灯串线共90灯 | D212: 0|0|塑料和LED灯珠|提供照明|无牌
A213: 4821100000 | B213: 标签 | D213: 0|0|纸制|印制|76x20
A214: 4819100000 | B214: 冰淇淋三明治纸盒 | D214: 0|0|瓦楞纸制|可折叠
A215: 8480790000 | B215: 饼干 模具
A216: 8480790000 | B216: 饼干底模
A217: 9403200000 | B217: 不锈钢餐桌 | D217: 1|0|不锈钢架+面板|员工用餐用|无牌|规格：200cm* 135cm*76cm
A218: 7326909000 | B218: 不锈钢浮球阀 | D218: 0|0|生产用|钢铁|冲压
A219: 9403100000 | B219: 不锈钢工作台1 | D219: 0|0|不锈钢|是|无品牌|200*140*75CM|
A220: 9403100000 | B220: 不锈钢工作台2 | D220: 0|0|不锈钢|是|无品牌|90*70*75|
A221: 8311100000 | B221: 不锈钢焊条 | D221: 1|0|电弧焊|硬质合金|焊条|以焊剂为芯|宏旺达|HWD-308
A222: 4202129000 | B222: 布袋 | D222: 0|0|小手布袋|纺织物|无牌|104125-01
A223: 8203200090 | B223: 布缝钳 | D223: 0|0|工业用|不锈钢|无牌|无型号
A224: 5906101000 | B224: 布基胶 | D224: 0|0|机织|橡胶|是|是|宽20mm*长50M
A225: 7326909000 | B225: 布鲁伊超声模底模夹具 | D225: 0|0|装配玩具用,非工业用|钢铁制|冲压
A226: 7326909000 | B226: 布鲁伊超声模上模夹具 | D226: 0|0|装配玩具用,非工业用|钢铁制|冲压
A227: 8471605000 | B227: 裁片扫描仪 | D227: 1|0|咔咻激光|KDBY-6650
A228: 4819200000 | B228: 彩盒 | D228: 0|0|瓦楞纸制|可折叠||
... A245: 7326909000 | B245: 超声机振子夹具 | D245: 0|0|装配玩具用,非工业用|钢铁制|冲压
A246: 7326909000 | B246: 超声模具
A247: 8208101100 | B247: 车床刀具 | D247: 1|0|金属加工用|合金钢|否|SP|MWLNR1616H08
A248: 8208109000 | B248: 车床刀片 | D248: 1|0|金属加工用|合金钢|否|鹰啄|WNMG080404-MUS D112S
A249: 7326909000 | B249: 车底板冲压夹具 | D249: 0|0|玩具生产用,非工业用|不锈钢制|冲压|
A250: 8480790000 | B250: 车底电池片压型模 | D250: 0|0|生产用|塑胶|无牌|无型号|五金+塑胶|使用型模，装配产品
A251: 4819200000 | B251: 车底加固咭 | D251: 0|0|瓦楞纸制|可折叠||
A252: 8480790000 | B252: 车底装压六角螺母手啤模 | D252: 0|0|生产用|塑胶|无牌|无型号|五金+塑胶|使用型模，装配产品
A253: 8480790000 | B253: 车顶灯热烫夹具 | D253: 0|0|生产用|塑胶|无牌|无型号|五金+塑胶|使用型模，装配产品
A254: 8480790000 | B254: 车顶装配打螺丝底模 | D254: 0|0|生产用|塑胶|无牌|无型号|五金+塑胶|使用型模，装配产品
A255: 7326909000 | B255: 车轮螺丝盖打胶水夹具 | D255: 0|0|装配玩具用,非工业用|钢铁制|冲压
A256: 8480790000 | B256: 车身底电池箱电池片压型摸 | D256: 0|0|生产用|塑胶|无牌|无型号|五金+塑胶|使用型模，装配产品
A257: 8480790000 | B257: 车身配车底打螺丝底模 | D257: 0|0|生产用|塑胶|无牌|无型号|五金+塑胶|使用型模，装配产品
A258: 732690900 | B258: 车身配前铲臂窝钉冲压气啤夹具 | D258: 0|0|装配玩具用,非工业用|钢铁制|冲压,五金配件
... A274: 9503009000 | B274: 尺码粒 | D274: 0|0|塑胶件尺码夹|无牌
A275: 7326909000 | B275: 齿轮打铁轴模具
A276: 8504409999 | B276: 充电机 | D276: 0|0|工业用|600W|无牌|无型号
A277: 8414909090 | B277: 储气罐 | D277: 0|0|压缩气体|无牌|无型号|Q345R钢
A278: 8451500000 | B278: 伺服电剪 | D278: 1|0|工业用|JK-T5D|JACK
A279: 8480790000 | B279: 打PCBA电子板/打驾驶室盖螺丝底模 | D279: 0|0|生产用|塑胶|无牌|无型号|五金+塑胶|使用型模，装配产品
A280: 8480790000 | B280: 打pcb螺丝/打驾驶室顶螺丝底模 | D280: 0|0|生产用|塑胶|无牌|无型号|五金+塑胶|使用型模，装配产品
A281: 8480790000 | B281: 打电池门螺丝底模 | D281: 0|0|生产用|塑胶|无牌|无型号|五金+塑胶|使用型模，装配产品
A282: 8480790000 | B282: 大边模 | D282: 0|0|生产用|塑胶|无牌|无型号|五金+塑胶|使用型模，装配产品
A283: 8467920000 | B283: 大号抛光头 | D283: 0|0|通用于气动打磨机|无品牌|无型号
A284: 8480790000 | B284: 大夹模 | D284: 0|0|生产用|塑胶|无牌|无型号|五金+塑胶|使用型模，装配产品
A285: 3926901000 | B285: 大夹子 | D285: 0|0|装配玩具生产用|塑胶料制|无牌|无型号||
A286: 8213000000 | B286: 大剪刀 | D286: 1|0|工业裁缝用|合金钢|剑龙|无型号
A287: 9603302090 | B287: 大毛笔 | D287: 0|0|工业用上颜色|木头、猪毛
...

Sheet 发票
B1: 深圳市华胜益出口贸易有限公司
B2: TEL : 0760-86120185
B3: INVOICE | I3: =80-33 -> 47 | J3: =司机资料!A1&司机资料!B1 -> 订舱号：237891915 | M3: =司机资料!E1&司机资料!F1
B5: 合同号 | E5: =司机资料!B2 -> MAGU2543655 | G5: Date: | H5: 45619 | J5: 清溪柜
B7: 唛头 | C7: 商品编号 | D7: 商品名称 | E7: 货物品名及规格 | F7: 数量 | G7: 数量单位 | H7: 单价/RMB | I7: 总价/RMB
J8: 毛重 | K8: 净重 | L8: 件数 | M8: 件数单位
B9: 1 | C9: =_xlfn.XLOOKUP(D9,商品汇总表!$B:$B,商品汇总表!$A:$A,"") -> #N/A | D9: {=LOOKUP(1,0/(('5.21出货明细'!AR:AR=$D$27)*('5.21出货明细'!A:A=B9)),'5.21出货明细'!E:E)} -> #N/A | E9: =_xlfn.XLOOKUP(D9,商品汇总表!$B:$B,商品汇总表!$D:$D,"") -> #N/A | F9: {=_xlfn.LET(_xlpm.数组,B9&D9,_xlpm.源数组,'5.21出货明细'!$A:$A&'5.21出货明细'!$E:$E,_xlpm.原单位,_xlfn.XLOOKUP(_xlpm.数组,_xlpm.源数组,'5.21出货明细'!$J:$J,""),_xlfn.HSTACK(_xlfn.XLOOKUP(_xlpm.数组,_xlpm.源数组,'5.21出货明细'!$K:$K,""),_xlfn.XLOOKUP(_xlpm.原单位,单位对照!$A:$A,单位对照!$B:$B,_xlpm.原单位),_xlfn.XLOOKUP(_xlpm.数组,_xlpm.源数组,'5.21出货明细'!$Z:$Z,""),_xlfn.XLOOKUP(_xlpm.数组,_xlpm.源数组,'5.21出货明细'!$AA:$AA,""),_xlfn.XLOOKUP(_xlpm.数组,_xlpm.源数组,'5.21出货明细'!$P:$P,""),_xlfn.XLOOKUP(_xlpm.数组,_xlpm.源数组,'5.21出货明细'!$Q:$Q,""),_xlfn.XLOOKUP(_xlpm.数组,_xlpm.源数组,'5.21出货明细'!$AT:$AT,"")))} -> #N/A | M9: 箱
B10: 2 | C10: =_xlfn.XLOOKUP(D10,商品汇总表!$B:$B,商品汇总表!$A:$A,"") -> #N/A | D10: {=LOOKUP(1,0/(('5.21出货明细'!AR:AR=$D$27)*('5.21出货明细'!A:A=B10)),'5.21出货明细'!E:E)} -> #N/A | E10: =_xlfn.XLOOKUP(D10,商品汇总表!$B:$B,商品汇总表!$D:$D,"") -> #N/A | F10: {=_xlfn.LET(_xlpm.数组,B10&D10,_xlpm.源数组,'5.21出货明细'!$A:$A&'5.21出货明细'!$E:$E,_xlpm.原单位,_xlfn.XLOOKUP(_xlpm.数组,_xlpm.源数组,'5.21出货明细'!$J:$J,""),_xlfn.HSTACK(_xlfn.XLOOKUP(_xlpm.数组,_xlpm.源数组,'5.21出货明细'!$K:$K,""),_xlfn.XLOOKUP(_xlpm.原单位,单位对照!$A:$A,单位对照!$B:$B,_xlpm.原单位),_xlfn.XLOOKUP(_xlpm.数组,_xlpm.源数组,'5.21出货明细'!$Z:$Z,""),_xlfn.XLOOKUP(_xlpm.数组,_xlpm.源数组,'5.21出货明细'!$AA:$AA,""),_xlfn.XLOOKUP(_xlpm.数组,_xlpm.源数组,'5.21出货明细'!$P:$P,""),_xlfn.XLOOKUP(_xlpm.数组,_xlpm.源数组,'5.21出货明细'!$Q:$Q,""),_xlfn.XLOOKUP(_xlpm.数组,_xlpm.源数组,'5.21出货明细'!$AT:$AT,"")))} -> #N/A | M10: 箱
B11: 3 | C11: =_xlfn.XLOOKUP(D11,商品汇总表!$B:$B,商品汇总表!$A:$A,"") -> #N/A | D11: {=LOOKUP(1,0/(('5.21出货明细'!AR:AR=$D$27)*('5.21出货明细'!A:A=B11)),'5.21出货明细'!E:E)} -> #N/A | E11: =_xlfn.XLOOKUP(D11,商品汇总表!$B:$B,商品汇总表!$D:$D,"") -> #N/A | F11: {=_xlfn.LET(_xlpm.数组,B11&D11,_xlpm.源数组,'5.21出货明细'!$A:$A&'5.21出货明细'!$E:$E,_xlpm.原单位,_xlfn.XLOOKUP(_xlpm.数组,_xlpm.源数组,'5.21出货明细'!$J:$J,""),_xlfn.HSTACK(_xlfn.XLOOKUP(_xlpm.数组,_xlpm.源数组,'5.21出货明细'!$K:$K,""),_xlfn.XLOOKUP(_xlpm.原单位,单位对照!$A:$A,单位对照!$B:$B,_xlpm.原单位),_xlfn.XLOOKUP(_xlpm.数组,_xlpm.源数组,'5.21出货明细'!$Z:$Z,""),_xlfn.XLOOKUP(_xlpm.数组,_xlpm.源数组,'5.21出货明细'!$AA:$AA,""),_xlfn.XLOOKUP(_xlpm.数组,_xlpm.源数组,'5.21出货明细'!$P:$P,""),_xlfn.XLOOKUP(_xlpm.数组,_xlpm.源数组,'5.21出货明细'!$Q:$Q,""),_xlfn.XLOOKUP(_xlpm.数组,_xlpm.源数组,'5.21出货明细'!$AT:$AT,"")))} -> #N/A | M11: 箱
B12: 4 | C12: =_xlfn.XLOOKUP(D12,商品汇总表!$B:$B,商品汇总表!$A:$A,"") -> #N/A | D12: {=LOOKUP(1,0/(('5.21出货明细'!AR:AR=$D$27)*('5.21出货明细'!A:A=B12)),'5.21出货明细'!E:E)} -> #N/A | E12: =_xlfn.XLOOKUP(D12,商品汇总表!$B:$B,商品汇总表!$D:$D,"") -> #N/A | F12: {=_xlfn.LET(_xlpm.数组,B12&D12,_xlpm.源数组,'5.21出货明细'!$A:$A&'5.21出货明细'!$E:$E,_xlpm.原单位,_xlfn.XLOOKUP(_xlpm.数组,_xlpm.源数组,'5.21出货明细'!$J:$J,""),_xlfn.HSTACK(_xlfn.XLOOKUP(_xlpm.数组,_xlpm.源数组,'5.21出货明细'!$K:$K,""),_xlfn.XLOOKUP(_xlpm.原单位,单位对照!$A:$A,单位对照!$B:$B,_xlpm.原单位),_xlfn.XLOOKUP(_xlpm.数组,_xlpm.源数组,'5.21出货明细'!$Z:$Z,""),_xlfn.XLOOKUP(_xlpm.数组,_xlpm.源数组,'5.21出货明细'!$AA:$AA,""),_xlfn.XLOOKUP(_xlpm.数组,_xlpm.源数组,'5.21出货明细'!$P:$P,""),_xlfn.XLOOKUP(_xlpm.数组,_xlpm.源数组,'5.21出货明细'!$Q:$Q,""),_xlfn.XLOOKUP(_xlpm.数组,_xlpm.源数组,'5.21出货明细'!$AT:$AT,"")))} -> #N/A | M12: 箱
B13: 5 | C13: =_xlfn.XLOOKUP(D13,商品汇总表!$B:$B,商品汇总表!$A:$A,"") -> #N/A | D13: {=LOOKUP(1,0/(('5.21出货明细'!AR:AR=$D$27)*('5.21出货明细'!A:A=B13)),'5.21出货明细'!E:E)} -> #N/A | E13: =_xlfn.XLOOKUP(D13,商品汇总表!$B:$B,商品汇总表!$D:$D,"") -> #N/A | F13: {=_xlfn.LET(_xlpm.数组,B13&D13,_xlpm.源数组,'5.21出货明细'!$A:$A&'5.21出货明细'!$E:$E,_xlpm.原单位,_xlfn.XLOOKUP(_xlpm.数组,_xlpm.源数组,'5.21出货明细'!$J:$J,""),_xlfn.HSTACK(_xlfn.XLOOKUP(_xlpm.数组,_xlpm.源数组,'5.21出货明细'!$K:$K,""),_xlfn.XLOOKUP(_xlpm.原单位,单位对照!$A:$A,单位对照!$B:$B,_xlpm.原单位),_xlfn.XLOOKUP(_xlpm.数组,_xlpm.源数组,'5.21出货明细'!$Z:$Z,""),_xlfn.XLOOKUP(_xlpm.数组,_xlpm.源数组,'5.21出货明细'!$AA:$AA,""),_xlfn.XLOOKUP(_xlpm.数组,_xlpm.源数组,'5.21出货明细'!$P:$P,""),_xlfn.XLOOKUP(_xlpm.数组,_xlpm.源数组,'5.21出货明细'!$Q:$Q,""),_xlfn.XLOOKUP(_xlpm.数组,_xlpm.源数组,'5.21出货明细'!$AT:$AT,"")))} -> #N/A | M13: 箱
B14: 6 | C14: =_xlfn.XLOOKUP(D14,商品汇总表!$B:$B,商品汇总表!$A:$A,"") -> #N/A | D14: {=LOOKUP(1,0/(('5.21出货明细'!AR:AR=$D$27)*('5.21出货明细'!A:A=B14)),'5.21出货明细'!E:E)} -> #N/A | E14: =_xlfn.XLOOKUP(D14,商品汇总表!$B:$B,商品汇总表!$D:$D,"") -> #N/A | F14: {=_xlfn.LET(_xlpm.数组,B14&D14,_xlpm.源数组,'5.21出货明细'!$A:$A&'5.21出货明细'!$E:$E,_xlpm.原单位,_xlfn.XLOOKUP(_xlpm.数组,_xlpm.源数组,'5.21出货明细'!$J:$J,""),_xlfn.HSTACK(_xlfn.XLOOKUP(_xlpm.数组,_xlpm.源数组,'5.21出货明细'!$K:$K,""),_xlfn.XLOOKUP(_xlpm.原单位,单位对照!$A:$A,单位对照!$B:$B,_xlpm.原单位),_xlfn.XLOOKUP(_xlpm.数组,_xlpm.源数组,'5.21出货明细'!$Z:$Z,""),_xlfn.XLOOKUP(_xlpm.数组,_xlpm.源数组,'5.21出货明细'!$AA:$AA,""),_xlfn.XLOOKUP(_xlpm.数组,_xlpm.源数组,'5.21出货明细'!$P:$P,""),_xlfn.XLOOKUP(_xlpm.数组,_xlpm.源数组,'5.21出货明细'!$Q:$Q,""),_xlfn.XLOOKUP(_xlpm.数组,_xlpm.源数组,'5.21出货明细'!$AT:$AT,"")))} -> #N/A | M14: 箱
B15: 7 | C15: =_xlfn.XLOOKUP(D15,商品汇总表!$B:$B,商品汇总表!$A:$A,"") -> #N/A | D15: {=LOOKUP(1,0/(('5.21出货明细'!AR:AR=$D$27)*('5.21出货明细'!A:A=B15)),'5.21出货明细'!E:E)} -> #N/A | E15: =_xlfn.XLOOKUP(D15,商品汇总表!$B:$B,商品汇总表!$D:$D,"") -> #N/A | F15: {=_xlfn.LET(_xlpm.数组,B15&D15,_xlpm.源数组,'5.21出货明细'!$A:$A&'5.21出货明细'!$E:$E,_xlpm.原单位,_xlfn.XLOOKUP(_xlpm.数组,_xlpm.源数组,'5.21出货明细'!$J:$J,""),_xlfn.HSTACK(_xlfn.XLOOKUP(_xlpm.数组,_xlpm.源数组,'5.21出货明细'!$K:$K,""),_xlfn.XLOOKUP(_xlpm.原单位,单位对照!$A:$A,单位对照!$B:$B,_xlpm.原单位),_xlfn.XLOOKUP(_xlpm.数组,_xlpm.源数组,'5.21出货明细'!$Z:$Z,""),_xlfn.XLOOKUP(_xlpm.数组,_xlpm.源数组,'5.21出货明细'!$AA:$AA,""),_xlfn.XLOOKUP(_xlpm.数组,_xlpm.源数组,'5.21出货明细'!$P:$P,""),_xlfn.XLOOKUP(_xlpm.数组,_xlpm.源数组,'5.21出货明细'!$Q:$Q,""),_xlfn.XLOOKUP(_xlpm.数组,_xlpm.源数组,'5.21出货明细'!$AT:$AT,"")))} -> #N/A | M15: 箱
B16: 8 | C16: =_xlfn.XLOOKUP(D16,商品汇总表!$B:$B,商品汇总表!$A:$A,"") -> #N/A | D16: {=LOOKUP(1,0/(('5.21出货明细'!AR:AR=$D$27)*('5.21出货明细'!A:A=B16)),'5.21出货明细'!E:E)} -> #N/A | E16: =_xlfn.XLOOKUP(D16,商品汇总表!$B:$B,商品汇总表!$D:$D,"") -> #N/A | F16: {=_xlfn.LET(_xlpm.数组,B16&D16,_xlpm.源数组,'5.21出货明细'!$A:$A&'5.21出货明细'!$E:$E,_xlpm.原单位,_xlfn.XLOOKUP(_xlpm.数组,_xlpm.源数组,'5.21出货明细'!$J:$J,""),_xlfn.HSTACK(_xlfn.XLOOKUP(_xlpm.数组,_xlpm.源数组,'5.21出货明细'!$K:$K,""),_xlfn.XLOOKUP(_xlpm.原单位,单位对照!$A:$A,单位对照!$B:$B,_xlpm.原单位),_xlfn.XLOOKUP(_xlpm.数组,_xlpm.源数组,'5.21出货明细'!$Z:$Z,""),_xlfn.XLOOKUP(_xlpm.数组,_xlpm.源数组,'5.21出货明细'!$AA:$AA,""),_xlfn.XLOOKUP(_xlpm.数组,_xlpm.源数组,'5.21出货明细'!$P:$P,""),_xlfn.XLOOKUP(_xlpm.数组,_xlpm.源数组,'5.21出货明细'!$Q:$Q,""),_xlfn.XLOOKUP(_xlpm.数组,_xlpm.源数组,'5.21出货明细'!$AT:$AT,"")))} -> #N/A | M16: 箱
B17: 9 | C17: =_xlfn.XLOOKUP(D17,商品汇总表!$B:$B,商品汇总表!$A:$A,"") -> #N/A | D17: {=LOOKUP(1,0/(('5.21出货明细'!AR:AR=$D$27)*('5.21出货明细'!A:A=B17)),'5.21出货明细'!E:E)} -> #N/A | E17: =_xlfn.XLOOKUP(D17,商品汇总表!$B:$B,商品汇总表!$D:$D,"") -> #N/A | F17: {=_xlfn.LET(_xlpm.数组,B17&D17,_xlpm.源数组,'5.21出货明细'!$A:$A&'5.21出货明细'!$E:$E,_xlpm.原单位,_xlfn.XLOOKUP(_xlpm.数组,_xlpm.源数组,'5.21出货明细'!$J:$J,""),_xlfn.HSTACK(_xlfn.XLOOKUP(_xlpm.数组,_xlpm.源数组,'5.21出货明细'!$K:$K,""),_xlfn.XLOOKUP(_xlpm.原单位,单位对照!$A:$A,单位对照!$B:$B,_xlpm.原单位),_xlfn.XLOOKUP(_xlpm.数组,_xlpm.源数组,'5.21出货明细'!$Z:$Z,""),_xlfn.XLOOKUP(_xlpm.数组,_xlpm.源数组,'5.21出货明细'!$AA:$AA,""),_xlfn.XLOOKUP(_xlpm.数组,_xlpm.源数组,'5.21出货明细'!$P:$P,""),_xlfn.XLOOKUP(_xlpm.数组,_xlpm.源数组,'5.21出货明细'!$Q:$Q,""),_xlfn.XLOOKUP(_xlpm.数组,_xlpm.源数组,'5.21出货明细'!$AT:$AT,"")))} -> #N/A | M17: 箱
B18: 10 | C18: =_xlfn.XLOOKUP(D18,商品汇总表!$B:$B,商品汇总表!$A:$A,"") -> #N/A | D18: {=LOOKUP(1,0/(('5.21出货明细'!AR:AR=$D$27)*('5.21出货明细'!A:A=B18)),'5.21出货明细'!E:E)} -> #N/A | E18: =_xlfn.XLOOKUP(D18,商品汇总表!$B:$B,商品汇总表!$D:$D,"") -> #N/A | F18: {=_xlfn.LET(_xlpm.数组,B18&D18,_xlpm.源数组,'5.21出货明细'!$A:$A&'5.21出货明细'!$E:$E,_xlpm.原单位,_xlfn.XLOOKUP(_xlpm.数组,_xlpm.源数组,'5.21出货明细'!$J:$J,""),_xlfn.HSTACK(_xlfn.XLOOKUP(_xlpm.数组,_xlpm.源数组,'5.21出货明细'!$K:$K,""),_xlfn.XLOOKUP(_xlpm.原单位,单位对照!$A:$A,单位对照!$B:$B,_xlpm.原单位),_xlfn.XLOOKUP(_xlpm.数组,_xlpm.源数组,'5.21出货明细'!$Z:$Z,""),_xlfn.XLOOKUP(_xlpm.数组,_xlpm.源数组,'5.21出货明细'!$AA:$AA,""),_xlfn.XLOOKUP(_xlpm.数组,_xlpm.源数组,'5.21出货明细'!$P:$P,""),_xlfn.XLOOKUP(_xlpm.数组,_xlpm.源数组,'5.21出货明细'!$Q:$Q,""),_xlfn.XLOOKUP(_xlpm.数组,_xlpm.源数组,'5.21出货明细'!$AT:$AT,"")))} -> #N/A | M18: 箱
B19: 11 | C19: =_xlfn.XLOOKUP(D19,商品汇总表!$B:$B,商品汇总表!$A:$A,"") -> #N/A | D19: {=LOOKUP(1,0/(('5.21出货明细'!AR:AR=$D$27)*('5.21出货明细'!A:A=B19)),'5.21出货明细'!E:E)} -> #N/A | E19: =_xlfn.XLOOKUP(D19,商品汇总表!$B:$B,商品汇总表!$D:$D,"") -> #N/A | F19: {=_xlfn.LET(_xlpm.数组,B19&D19,_xlpm.源数组,'5.21出货明细'!$A:$A&'5.21出货明细'!$E:$E,_xlpm.原单位,_xlfn.XLOOKUP(_xlpm.数组,_xlpm.源数组,'5.21出货明细'!$J:$J,""),_xlfn.HSTACK(_xlfn.XLOOKUP(_xlpm.数组,_xlpm.源数组,'5.21出货明细'!$K:$K,""),_xlfn.XLOOKUP(_xlpm.原单位,单位对照!$A:$A,单位对照!$B:$B,_xlpm.原单位),_xlfn.XLOOKUP(_xlpm.数组,_xlpm.源数组,'5.21出货明细'!$Z:$Z,""),_xlfn.XLOOKUP(_xlpm.数组,_xlpm.源数组,'5.21出货明细'!$AA:$AA,""),_xlfn.XLOOKUP(_xlpm.数组,_xlpm.源数组,'5.21出货明细'!$P:$P,""),_xlfn.XLOOKUP(_xlpm.数组,_xlpm.源数组,'5.21出货明细'!$Q:$Q,""),_xlfn.XLOOKUP(_xlpm.数组,_xlpm.源数组,'5.21出货明细'!$AT:$AT,"")))} -> #N/A | M19: 箱
B20: 12 | C20: =_xlfn.XLOOKUP(D20,商品汇总表!$B:$B,商品汇总表!$A:$A,"") -> #N/A | D20: {=LOOKUP(1,0/(('5.21出货明细'!AR:AR=$D$27)*('5.21出货明细'!A:A=B20)),'5.21出货明细'!E:E)} -> #N/A | E20: =_xlfn.XLOOKUP(D20,商品汇总表!$B:$B,商品汇总表!$D:$D,"") -> #N/A | F20: {=_xlfn.LET(_xlpm.数组,B20&D20,_xlpm.源数组,'5.21出货明细'!$A:$A&'5.21出货明细'!$E:$E,_xlpm.原单位,_xlfn.XLOOKUP(_xlpm.数组,_xlpm.源数组,'5.21出货明细'!$J:$J,""),_xlfn.HSTACK(_xlfn.XLOOKUP(_xlpm.数组,_xlpm.源数组,'5.21出货明细'!$K:$K,""),_xlfn.XLOOKUP(_xlpm.原单位,单位对照!$A:$A,单位对照!$B:$B,_xlpm.原单位),_xlfn.XLOOKUP(_xlpm.数组,_xlpm.源数组,'5.21出货明细'!$Z:$Z,""),_xlfn.XLOOKUP(_xlpm.数组,_xlpm.源数组,'5.21出货明细'!$AA:$AA,""),_xlfn.XLOOKUP(_xlpm.数组,_xlpm.源数组,'5.21出货明细'!$P:$P,""),_xlfn.XLOOKUP(_xlpm.数组,_xlpm.源数组,'5.21出货明细'!$Q:$Q,""),_xlfn.XLOOKUP(_xlpm.数组,_xlpm.源数组,'5.21出货明细'!$AT:$AT,"")))} -> #N/A | M20: 箱
... B26: 18 | C26: =_xlfn.XLOOKUP(D26,商品汇总表!$B:$B,商品汇总表!$A:$A,"") -> #N/A | D26: {=LOOKUP(1,0/(('5.21出货明细'!AR:AR=$D$27)*('5.21出货明细'!A:A=B26)),'5.21出货明细'!E:E)} -> #N/A | E26: =_xlfn.XLOOKUP(D26,商品汇总表!$B:$B,商品汇总表!$D:$D,"") -> #N/A | F26: {=_xlfn.LET(_xlpm.数组,B26&D26,_xlpm.源数组,'5.21出货明细'!$A:$A&'5.21出货明细'!$E:$E,_xlpm.原单位,_xlfn.XLOOKUP(_xlpm.数组,_xlpm.源数组,'5.21出货明细'!$J:$J,""),_xlfn.HSTACK(_xlfn.XLOOKUP(_xlpm.数组,_xlpm.源数组,'5.21出货明细'!$K:$K,""),_xlfn.XLOOKUP(_xlpm.原单位,单位对照!$A:$A,单位对照!$B:$B,_xlpm.原单位),_xlfn.XLOOKUP(_xlpm.数组,_xlpm.源数组,'5.21出货明细'!$Z:$Z,""),_xlfn.XLOOKUP(_xlpm.数组,_xlpm.源数组,'5.21出货明细'!$AA:$AA,""),_xlfn.XLOOKUP(_xlpm.数组,_xlpm.源数组,'5.21出货明细'!$P:$P,""),_xlfn.XLOOKUP(_xlpm.数组,_xlpm.源数组,'5.21出货明细'!$Q:$Q,""),_xlfn.XLOOKUP(_xlpm.数组,_xlpm.源数组,'5.21出货明细'!$AT:$AT,"")))} -> #N/A | M26: 箱
D27: 深圳市华胜益出口贸易有限公司 | F27: =SUM(F9:F9) -> #N/A | I27: =SUM(I9:I26) -> 0 | J27: =SUM(J9:J26) -> 0 | K27: =SUM(K9:K26) -> 0 | L27: =SUM(L9:L26) -> 0
B28: 19 | C28: =_xlfn.XLOOKUP(D28,商品汇总表!$B:$B,商品汇总表!$A:$A,"") -> #N/A | D28: {=LOOKUP(1,0/(('5.21出货明细'!AR:AR=$D$39)*('5.21出货明细'!A:A=B28)),'5.21出货明细'!E:E)} -> #N/A | E28: =_xlfn.XLOOKUP(D28,商品汇总表!$B:$B,商品汇总表!$D:$D,"") -> #N/A | F28: {=_xlfn.LET(_xlpm.数组,B28&D28,_xlpm.源数组,'5.21出货明细'!$A:$A&'5.21出货明细'!$E:$E,_xlpm.原单位,_xlfn.XLOOKUP(_xlpm.数组,_xlpm.源数组,'5.21出货明细'!$J:$J,""),_xlfn.HSTACK(_xlfn.XLOOKUP(_xlpm.数组,_xlpm.源数组,'5.21出货明细'!$K:$K,""),_xlfn.XLOOKUP(_xlpm.原单位,单位对照!$A:$A,单位对照!$B:$B,_xlpm.原单位),_xlfn.XLOOKUP(_xlpm.数组,_xlpm.源数组,'5.21出货明细'!$Z:$Z,""),_xlfn.XLOOKUP(_xlpm.数组,_xlpm.源数组,'5.21出货明细'!$AA:$AA,""),_xlfn.XLOOKUP(_xlpm.数组,_xlpm.源数组,'5.21出货明细'!$P:$P,""),_xlfn.XLOOKUP(_xlpm.数组,_xlpm.源数组,'5.21出货明细'!$Q:$Q,""),_xlfn.XLOOKUP(_xlpm.数组,_xlpm.源数组,'5.21出货明细'!$AT:$AT,"")))} -> #N/A | M28: 箱
B29: 20 | C29: =_xlfn.XLOOKUP(D29,商品汇总表!$B:$B,商品汇总表!$A:$A,"") -> #N/A | D29: {=LOOKUP(1,0/(('5.21出货明细'!AR:AR=$D$39)*('5.21出货明细'!A:A=B29)),'5.21出货明细'!E:E)} -> #N/A | E29: =_xlfn.XLOOKUP(D29,商品汇总表!$B:$B,商品汇总表!$D:$D,"") -> #N/A | F29: {=_xlfn.LET(_xlpm.数组,B29&D29,_xlpm.源数组,'5.21出货明细'!$A:$A&'5.21出货明细'!$E:$E,_xlpm.原单位,_xlfn.XLOOKUP(_xlpm.数组,_xlpm.源数组,'5.21出货明细'!$J:$J,""),_xlfn.HSTACK(_xlfn.XLOOKUP(_xlpm.数组,_xlpm.源数组,'5.21出货明细'!$K:$K,""),_xlfn.XLOOKUP(_xlpm.原单位,单位对照!$A:$A,单位对照!$B:$B,_xlpm.原单位),_xlfn.XLOOKUP(_xlpm.数组,_xlpm.源数组,'5.21出货明细'!$Z:$Z,""),_xlfn.XLOOKUP(_xlpm.数组,_xlpm.源数组,'5.21出货明细'!$AA:$AA,""),_xlfn.XLOOKUP(_xlpm.数组,_xlpm.源数组,'5.21出货明细'!$P:$P,""),_xlfn.XLOOKUP(_xlpm.数组,_xlpm.源数组,'5.21出货明细'!$Q:$Q,""),_xlfn.XLOOKUP(_xlpm.数组,_xlpm.源数组,'5.21出货明细'!$AT:$AT,"")))} -> #N/A | M29: 箱
B30: 21 | C30: =_xlfn.XLOOKUP(D30,商品汇总表!$B:$B,商品汇总表!$A:$A,"") -> #N/A | D30: {=LOOKUP(1,0/(('5.21出货明细'!AR:AR=$D$39)*('5.21出货明细'!A:A=B30)),'5.21出货明细'!E:E)} -> #N/A | E30: =_xlfn.XLOOKUP(D30,商品汇总表!$B:$B,商品汇总表!$D:$D,"") -> #N/A | F30: {=_xlfn.LET(_xlpm.数组,B30&D30,_xlpm.源数组,'5.21出货明细'!$A:$A&'5.21出货明细'!$E:$E,_xlpm.原单位,_xlfn.XLOOKUP(_xlpm.数组,_xlpm.源数组,'5.21出货明细'!$J:$J,""),_xlfn.HSTACK(_xlfn.XLOOKUP(_xlpm.数组,_xlpm.源数组,'5.21出货明细'!$K:$K,""),_xlfn.XLOOKUP(_xlpm.原单位,单位对照!$A:$A,单位对照!$B:$B,_xlpm.原单位),_xlfn.XLOOKUP(_xlpm.数组,_xlpm.源数组,'5.21出货明细'!$Z:$Z,""),_xlfn.XLOOKUP(_xlpm.数组,_xlpm.源数组,'5.21出货明细'!$AA:$AA,""),_xlfn.XLOOKUP(_xlpm.数组,_xlpm.源数组,'5.21出货明细'!$P:$P,""),_xlfn.XLOOKUP(_xlpm.数组,_xlpm.源数组,'5.21出货明细'!$Q:$Q,""),_xlfn.XLOOKUP(_xlpm.数组,_xlpm.源数组,'5.21出货明细'!$AT:$AT,"")))} -> #N/A | M30: 箱
B31: 22 | C31: =_xlfn.XLOOKUP(D31,商品汇总表!$B:$B,商品汇总表!$A:$A,"") -> #N/A | D31: {=LOOKUP(1,0/(('5.21出货明细'!AR:AR=$D$39)*('5.21出货明细'!A:A=B31)),'5.21出货明细'!E:E)} -> #N/A | E31: =_xlfn.XLOOKUP(D31,商品汇总表!$B:$B,商品汇总表!$D:$D,"") -> #N/A | F31: {=_xlfn.LET(_xlpm.数组,B31&D31,_xlpm.源数组,'5.21出货明细'!$A:$A&'5.21出货明细'!$E:$E,_xlpm.原单位,_xlfn.XLOOKUP(_xlpm.数组,_xlpm.源数组,'5.21出货明细'!$J:$J,""),_xlfn.HSTACK(_xlfn.XLOOKUP(_xlpm.数组,_xlpm.源数组,'5.21出货明细'!$K:$K,""),_xlfn.XLOOKUP(_xlpm.原单位,单位对照!$A:$A,单位对照!$B:$B,_xlpm.原单位),_xlfn.XLOOKUP(_xlpm.数组,_xlpm.源数组,'5.21出货明细'!$Z:$Z,""),_xlfn.XLOOKUP(_xlpm.数组,_xlpm.源数组,'5.21出货明细'!$AA:$AA,""),_xlfn.XLOOKUP(_xlpm.数组,_xlpm.源数组,'5.21出货明细'!$P:$P,""),_xlfn.XLOOKUP(_xlpm.数组,_xlpm.源数组,'5.21出货明细'!$Q:$Q,""),_xlfn.XLOOKUP(_xlpm.数组,_xlpm.源数组,'5.21出货明细'!$AT:$AT,"")))} -> #N/A | M31: 箱
B32: 23 | C32: =_xlfn.XLOOKUP(D32,商品汇总表!$B:$B,商品汇总表!$A:$A,"") -> #N/A | D32: {=LOOKUP(1,0/(('5.21出货明细'!AR:AR=$D$39)*('5.21出货明细'!A:A=B32)),'5.21出货明细'!E:E)} -> #N/A | E32: =_xlfn.XLOOKUP(D32,商品汇总表!$B:$B,商品汇总表!$D:$D,"") -> #N/A | F32: {=_xlfn.LET(_xlpm.数组,B32&D32,_xlpm.源数组,'5.21出货明细'!$A:$A&'5.21出货明细'!$E:$E,_xlpm.原单位,_xlfn.XLOOKUP(_xlpm.数组,_xlpm.源数组,'5.21出货明细'!$J:$J,""),_xlfn.HSTACK(_xlfn.XLOOKUP(_xlpm.数组,_xlpm.源数组,'5.21出货明细'!$K:$K,""),_xlfn.XLOOKUP(_xlpm.原单位,单位对照!$A:$A,单位对照!$B:$B,_xlpm.原单位),_xlfn.XLOOKUP(_xlpm.数组,_xlpm.源数组,'5.21出货明细'!$Z:$Z,""),_xlfn.XLOOKUP(_xlpm.数组,_xlpm.源数组,'5.21出货明细'!$AA:$AA,""),_xlfn.XLOOKUP(_xlpm.数组,_xlpm.源数组,'5.21出货明细'!$P:$P,""),_xlfn.XLOOKUP(_xlpm.数组,_xlpm.源数组,'5.21出货明细'!$Q:$Q,""),_xlfn.XLOOKUP(_xlpm.数组,_xlpm.源数组,'5.21出货明细'!$AT:$AT,"")))} -> #N/A | M32: 箱
B33: 24 | C33: =_xlfn.XLOOKUP(D33,商品汇总表!$B:$B,商品汇总表!$A:$A,"") -> #N/A | D33: {=LOOKUP(1,0/(('5.21出货明细'!AR:AR=$D$39)*('5.21出货明细'!A:A=B33)),'5.21出货明细'!E:E)} -> #N/A | E33: =_xlfn.XLOOKUP(D33,商品汇总表!$B:$B,商品汇总表!$D:$D,"") -> #N/A | F33: {=_xlfn.LET(_xlpm.数组,B33&D33,_xlpm.源数组,'5.21出货明细'!$A:$A&'5.21出货明细'!$E:$E,_xlpm.原单位,_xlfn.XLOOKUP(_xlpm.数组,_xlpm.源数组,'5.21出货明细'!$J:$J,""),_xlfn.HSTACK(_xlfn.XLOOKUP(_xlpm.数组,_xlpm.源数组,'5.21出货明细'!$K:$K,""),_xlfn.XLOOKUP(_xlpm.原单位,单位对照!$A:$A,单位对照!$B:$B,_xlpm.原单位),_xlfn.XLOOKUP(_xlpm.数组,_xlpm.源数组,'5.21出货明细'!$Z:$Z,""),_xlfn.XLOOKUP(_xlpm.数组,_xlpm.源数组,'5.21出货明细'!$AA:$AA,""),_xlfn.XLOOKUP(_xlpm.数组,_xlpm.源数组,'5.21出货明细'!$P:$P,""),_xlfn.XLOOKUP(_xlpm.数组,_xlpm.源数组,'5.21出货明细'!$Q:$Q,""),_xlfn.XLOOKUP(_xlpm.数组,_xlpm.源数组,'5.21出货明细'!$AT:$AT,"")))} -> #N/A | M33: 箱
B34: 25 | C34: =_xlfn.XLOOKUP(D34,商品汇总表!$B:$B,商品汇总表!$A:$A,"") -> #N/A | D34: {=LOOKUP(1,0/(('5.21出货明细'!AR:AR=$D$39)*('5.21出货明细'!A:A=B34)),'5.21出货明细'!E:E)} -> #N/A | E34: =_xlfn.XLOOKUP(D34,商品汇总表!$B:$B,商品汇总表!$D:$D,"") -> #N/A | F34: {=_xlfn.LET(_xlpm.数组,B34&D34,_xlpm.源数组,'5.21出货明细'!$A:$A&'5.21出货明细'!$E:$E,_xlpm.原单位,_xlfn.XLOOKUP(_xlpm.数组,_xlpm.源数组,'5.21出货明细'!$J:$J,""),_xlfn.HSTACK(_xlfn.XLOOKUP(_xlpm.数组,_xlpm.源数组,'5.21出货明细'!$K:$K,""),_xlfn.XLOOKUP(_xlpm.原单位,单位对照!$A:$A,单位对照!$B:$B,_xlpm.原单位),_xlfn.XLOOKUP(_xlpm.数组,_xlpm.源数组,'5.21出货明细'!$Z:$Z,""),_xlfn.XLOOKUP(_xlpm.数组,_xlpm.源数组,'5.21出货明细'!$AA:$AA,""),_xlfn.XLOOKUP(_xlpm.数组,_xlpm.源数组,'5.21出货明细'!$P:$P,""),_xlfn.XLOOKUP(_xlpm.数组,_xlpm.源数组,'5.21出货明细'!$Q:$Q,""),_xlfn.XLOOKUP(_xlpm.数组,_xlpm.源数组,'5.21出货明细'!$AT:$AT,"")))} -> #N/A | M34: 箱
B35: 26 | C35: =_xlfn.XLOOKUP(D35,商品汇总表!$B:$B,商品汇总表!$A:$A,"") -> #N/A | D35: {=LOOKUP(1,0/(('5.21出货明细'!AR:AR=$D$39)*('5.21出货明细'!A:A=B35)),'5.21出货明细'!E:E)} -> #N/A | E35: =_xlfn.XLOOKUP(D35,商品汇总表!$B:$B,商品汇总表!$D:$D,"") -> #N/A | F35: {=_xlfn.LET(_xlpm.数组,B35&D35,_xlpm.源数组,'5.21出货明细'!$A:$A&'5.21出货明细'!$E:$E,_xlpm.原单位,_xlfn.XLOOKUP(_xlpm.数组,_xlpm.源数组,'5.21出货明细'!$J:$J,""),_xlfn.HSTACK(_xlfn.XLOOKUP(_xlpm.数组,_xlpm.源数组,'5.21出货明细'!$K:$K,""),_xlfn.XLOOKUP(_xlpm.原单位,单位对照!$A:$A,单位对照!$B:$B,_xlpm.原单位),_xlfn.XLOOKUP(_xlpm.数组,_xlpm.源数组,'5.21出货明细'!$Z:$Z,""),_xlfn.XLOOKUP(_xlpm.数组,_xlpm.源数组,'5.21出货明细'!$AA:$AA,""),_xlfn.XLOOKUP(_xlpm.数组,_xlpm.源数组,'5.21出货明细'!$P:$P,""),_xlfn.XLOOKUP(_xlpm.数组,_xlpm.源数组,'5.21出货明细'!$Q:$Q,""),_xlfn.XLOOKUP(_xlpm.数组,_xlpm.源数组,'5.21出货明细'!$AT:$AT,"")))} -> #N/A | M35: 箱
B36: 27 | C36: =_xlfn.XLOOKUP(D36,商品汇总表!$B:$B,商品汇总表!$A:$A,"") -> #N/A | D36: {=LOOKUP(1,0/(('5.21出货明细'!AR:AR=$D$39)*('5.21出货明细'!A:A=B36)),'5.21出货明细'!E:E)} -> #N/A | E36: =_xlfn.XLOOKUP(D36,商品汇总表!$B:$B,商品汇总表!$D:$D,"") -> #N/A | F36: {=_xlfn.LET(_xlpm.数组,B36&D36,_xlpm.源数组,'5.21出货明细'!$A:$A&'5.21出货明细'!$E:$E,_xlpm.原单位,_xlfn.XLOOKUP(_xlpm.数组,_xlpm.源数组,'5.21出货明细'!$J:$J,""),_xlfn.HSTACK(_xlfn.XLOOKUP(_xlpm.数组,_xlpm.源数组,'5.21出货明细'!$K:$K,""),_xlfn.XLOOKUP(_xlpm.原单位,单位对照!$A:$A,单位对照!$B:$B,_xlpm.原单位),_xlfn.XLOOKUP(_xlpm.数组,_xlpm.源数组,'5.21出货明细'!$Z:$Z,""),_xlfn.XLOOKUP(_xlpm.数组,_xlpm.源数组,'5.21出货明细'!$AA:$AA,""),_xlfn.XLOOKUP(_xlpm.数组,_xlpm.源数组,'5.21出货明细'!$P:$P,""),_xlfn.XLOOKUP(_xlpm.数组,_xlpm.源数组,'5.21出货明细'!$Q:$Q,""),_xlfn.XLOOKUP(_xlpm.数组,_xlpm.源数组,'5.21出货明细'!$AT:$AT,"")))} -> #N/A | M36: 箱
B37: 28 | C37: =_xlfn.XLOOKUP(D37,商品汇总表!$B:$B,商品汇总表!$A:$A,"") -> #N/A | D37: {=LOOKUP(1,0/(('5.21出货明细'!AR:AR=$D$39)*('5.21出货明细'!A:A=B37)),'5.21出货明细'!E:E)} -> #N/A | E37: =_xlfn.XLOOKUP(D37,商品汇总表!$B:$B,商品汇总表!$D:$D,"") -> #N/A | F37: {=_xlfn.LET(_xlpm.数组,B37&D37,_xlpm.源数组,'5.21出货明细'!$A:$A&'5.21出货明细'!$E:$E,_xlpm.原单位,_xlfn.XLOOKUP(_xlpm.数组,_xlpm.源数组,'5.21出货明细'!$J:$J,""),_xlfn.HSTACK(_xlfn.XLOOKUP(_xlpm.数组,_xlpm.源数组,'5.21出货明细'!$K:$K,""),_xlfn.XLOOKUP(_xlpm.原单位,单位对照!$A:$A,单位对照!$B:$B,_xlpm.原单位),_xlfn.XLOOKUP(_xlpm.数组,_xlpm.源数组,'5.21出货明细'!$Z:$Z,""),_xlfn.XLOOKUP(_xlpm.数组,_xlpm.源数组,'5.21出货明细'!$AA:$AA,""),_xlfn.XLOOKUP(_xlpm.数组,_xlpm.源数组,'5.21出货明细'!$P:$P,""),_xlfn.XLOOKUP(_xlpm.数组,_xlpm.源数组,'5.21出货明细'!$Q:$Q,""),_xlfn.XLOOKUP(_xlpm.数组,_xlpm.源数组,'5.21出货明细'!$AT:$AT,"")))} -> #N/A | M37: 箱
B38: 29 | C38: =_xlfn.XLOOKUP(D38,商品汇总表!$B:$B,商品汇总表!$A:$A,"") -> #N/A | D38: {=LOOKUP(1,0/(('5.21出货明细'!AR:AR=$D$39)*('5.21出货明细'!A:A=B38)),'5.21出货明细'!E:E)} -> #N/A | E38: =_xlfn.XLOOKUP(D38,商品汇总表!$B:$B,商品汇总表!$D:$D,"") -> #N/A | F38: {=_xlfn.LET(_xlpm.数组,B38&D38,_xlpm.源数组,'5.21出货明细'!$A:$A&'5.21出货明细'!$E:$E,_xlpm.原单位,_xlfn.XLOOKUP(_xlpm.数组,_xlpm.源数组,'5.21出货明细'!$J:$J,""),_xlfn.HSTACK(_xlfn.XLOOKUP(_xlpm.数组,_xlpm.源数组,'5.21出货明细'!$K:$K,""),_xlfn.XLOOKUP(_xlpm.原单位,单位对照!$A:$A,单位对照!$B:$B,_xlpm.原单位),_xlfn.XLOOKUP(_xlpm.数组,_xlpm.源数组,'5.21出货明细'!$Z:$Z,""),_xlfn.XLOOKUP(_xlpm.数组,_xlpm.源数组,'5.21出货明细'!$AA:$AA,""),_xlfn.XLOOKUP(_xlpm.数组,_xlpm.源数组,'5.21出货明细'!$P:$P,""),_xlfn.XLOOKUP(_xlpm.数组,_xlpm.源数组,'5.21出货明细'!$Q:$Q,""),_xlfn.XLOOKUP(_xlpm.数组,_xlpm.源数组,'5.21出货明细'!$AT:$AT,"")))} -> #N/A | M38: 箱
D39: 东莞市台聚印刷有限公司 | F39: =SUM(F28:F38) -> #N/A | I39: =SUM(I28:I38) -> 0 | J39: =SUM(J28:J38) -> 0 | K39: =SUM(K28:K38) -> 0 | L39: =SUM(L28:L38) -> 0
B40: 30 | C40: =_xlfn.XLOOKUP(D40,商品汇总表!$B:$B,商品汇总表!$A:$A,"") -> #N/A | D40: {=LOOKUP(1,0/(('5.21出货明细'!AR:AR=$D$52)*('5.21出货明细'!A:A=B40)),'5.21出货明细'!E:E)} -> #N/A | E40: =_xlfn.XLOOKUP(D40,商品汇总表!$B:$B,商品汇总表!$D:$D,"") -> #N/A | F40: {=_xlfn.LET(_xlpm.数组,B40&D40,_xlpm.源数组,'5.21出货明细'!$A:$A&'5.21出货明细'!$E:$E,_xlpm.原单位,_xlfn.XLOOKUP(_xlpm.数组,_xlpm.源数组,'5.21出货明细'!$J:$J,""),_xlfn.HSTACK(_xlfn.XLOOKUP(_xlpm.数组,_xlpm.源数组,'5.21出货明细'!$K:$K,""),_xlfn.XLOOKUP(_xlpm.原单位,单位对照!$A:$A,单位对照!$B:$B,_xlpm.原单位),_xlfn.XLOOKUP(_xlpm.数组,_xlpm.源数组,'5.21出货明细'!$Z:$Z,""),_xlfn.XLOOKUP(_xlpm.数组,_xlpm.源数组,'5.21出货明细'!$AA:$AA,""),_xlfn.XLOOKUP(_xlpm.数组,_xlpm.源数组,'5.21出货明细'!$P:$P,""),_xlfn.XLOOKUP(_xlpm.数组,_xlpm.源数组,'5.21出货明细'!$Q:$Q,""),_xlfn.XLOOKUP(_xlpm.数组,_xlpm.源数组,'5.21出货明细'!$AT:$AT,"")))} -> #N/A | M40: 箱
B41: 31 | C41: =_xlfn.XLOOKUP(D41,商品汇总表!$B:$B,商品汇总表!$A:$A,"") -> #N/A | D41: {=LOOKUP(1,0/(('5.21出货明细'!AR:AR=$D$52)*('5.21出货明细'!A:A=B41)),'5.21出货明细'!E:E)} -> #N/A | E41: =_xlfn.XLOOKUP(D41,商品汇总表!$B:$B,商品汇总表!$D:$D,"") -> #N/A | F41: {=_xlfn.LET(_xlpm.数组,B41&D41,_xlpm.源数组,'5.21出货明细'!$A:$A&'5.21出货明细'!$E:$E,_xlpm.原单位,_xlfn.XLOOKUP(_xlpm.数组,_xlpm.源数组,'5.21出货明细'!$J:$J,""),_xlfn.HSTACK(_xlfn.XLOOKUP(_xlpm.数组,_xlpm.源数组,'5.21出货明细'!$K:$K,""),_xlfn.XLOOKUP(_xlpm.原单位,单位对照!$A:$A,单位对照!$B:$B,_xlpm.原单位),_xlfn.XLOOKUP(_xlpm.数组,_xlpm.源数组,'5.21出货明细'!$Z:$Z,""),_xlfn.XLOOKUP(_xlpm.数组,_xlpm.源数组,'5.21出货明细'!$AA:$AA,""),_xlfn.XLOOKUP(_xlpm.数组,_xlpm.源数组,'5.21出货明细'!$P:$P,""),_xlfn.XLOOKUP(_xlpm.数组,_xlpm.源数组,'5.21出货明细'!$Q:$Q,""),_xlfn.XLOOKUP(_xlpm.数组,_xlpm.源数组,'5.21出货明细'!$AT:$AT,"")))} -> #N/A | M41: 箱
B42: 32 | C42: =_xlfn.XLOOKUP(D42,商品汇总表!$B:$B,商品汇总表!$A:$A,"") -> #N/A | D42: {=LOOKUP(1,0/(('5.21出货明细'!AR:AR=$D$52)*('5.21出货明细'!A:A=B42)),'5.21出货明细'!E:E)} -> #N/A | E42: =_xlfn.XLOOKUP(D42,商品汇总表!$B:$B,商品汇总表!$D:$D,"") -> #N/A | F42: {=_xlfn.LET(_xlpm.数组,B42&D42,_xlpm.源数组,'5.21出货明细'!$A:$A&'5.21出货明细'!$E:$E,_xlpm.原单位,_xlfn.XLOOKUP(_xlpm.数组,_xlpm.源数组,'5.21出货明细'!$J:$J,""),_xlfn.HSTACK(_xlfn.XLOOKUP(_xlpm.数组,_xlpm.源数组,'5.21出货明细'!$K:$K,""),_xlfn.XLOOKUP(_xlpm.原单位,单位对照!$A:$A,单位对照!$B:$B,_xlpm.原单位),_xlfn.XLOOKUP(_xlpm.数组,_xlpm.源数组,'5.21出货明细'!$Z:$Z,""),_xlfn.XLOOKUP(_xlpm.数组,_xlpm.源数组,'5.21出货明细'!$AA:$AA,""),_xlfn.XLOOKUP(_xlpm.数组,_xlpm.源数组,'5.21出货明细'!$P:$P,""),_xlfn.XLOOKUP(_xlpm.数组,_xlpm.源数组,'5.21出货明细'!$Q:$Q,""),_xlfn.XLOOKUP(_xlpm.数组,_xlpm.源数组,'5.21出货明细'!$AT:$AT,"")))} -> #N/A | M42: 箱
B43: 33 | C43: =_xlfn.XLOOKUP(D43,商品汇总表!$B:$B,商品汇总表!$A:$A,"") -> #N/A | D43: {=LOOKUP(1,0/(('5.21出货明细'!AR:AR=$D$52)*('5.21出货明细'!A:A=B43)),'5.21出货明细'!E:E)} -> #N/A | E43: =_xlfn.XLOOKUP(D43,商品汇总表!$B:$B,商品汇总表!$D:$D,"") -> #N/A | F43: {=_xlfn.LET(_xlpm.数组,B43&D43,_xlpm.源数组,'5.21出货明细'!$A:$A&'5.21出货明细'!$E:$E,_xlpm.原单位,_xlfn.XLOOKUP(_xlpm.数组,_xlpm.源数组,'5.21出货明细'!$J:$J,""),_xlfn.HSTACK(_xlfn.XLOOKUP(_xlpm.数组,_xlpm.源数组,'5.21出货明细'!$K:$K,""),_xlfn.XLOOKUP(_xlpm.原单位,单位对照!$A:$A,单位对照!$B:$B,_xlpm.原单位),_xlfn.XLOOKUP(_xlpm.数组,_xlpm.源数组,'5.21出货明细'!$Z:$Z,""),_xlfn.XLOOKUP(_xlpm.数组,_xlpm.源数组,'5.21出货明细'!$AA:$AA,""),_xlfn.XLOOKUP(_xlpm.数组,_xlpm.源数组,'5.21出货明细'!$P:$P,""),_xlfn.XLOOKUP(_xlpm.数组,_xlpm.源数组,'5.21出货明细'!$Q:$Q,""),_xlfn.XLOOKUP(_xlpm.数组,_xlpm.源数组,'5.21出货明细'!$AT:$AT,"")))} -> #N/A | M43: 箱
B44: 34 | C44: =_xlfn.XLOOKUP(D44,商品汇总表!$B:$B,商品汇总表!$A:$A,"") -> #N/A | D44: {=LOOKUP(1,0/(('5.21出货明细'!AR:AR=$D$52)*('5.21出货明细'!A:A=B44)),'5.21出货明细'!E:E)} -> #N/A | E44: =_xlfn.XLOOKUP(D44,商品汇总表!$B:$B,商品汇总表!$D:$D,"") -> #N/A | F44: {=_xlfn.LET(_xlpm.数组,B44&D44,_xlpm.源数组,'5.21出货明细'!$A:$A&'5.21出货明细'!$E:$E,_xlpm.原单位,_xlfn.XLOOKUP(_xlpm.数组,_xlpm.源数组,'5.21出货明细'!$J:$J,""),_xlfn.HSTACK(_xlfn.XLOOKUP(_xlpm.数组,_xlpm.源数组,'5.21出货明细'!$K:$K,""),_xlfn.XLOOKUP(_xlpm.原单位,单位对照!$A:$A,单位对照!$B:$B,_xlpm.原单位),_xlfn.XLOOKUP(_xlpm.数组,_xlpm.源数组,'5.21出货明细'!$Z:$Z,""),_xlfn.XLOOKUP(_xlpm.数组,_xlpm.源数组,'5.21出货明细'!$AA:$AA,""),_xlfn.XLOOKUP(_xlpm.数组,_xlpm.源数组,'5.21出货明细'!$P:$P,""),_xlfn.XLOOKUP(_xlpm.数组,_xlpm.源数组,'5.21出货明细'!$Q:$Q,""),_xlfn.XLOOKUP(_xlpm.数组,_xlpm.源数组,'5.21出货明细'!$AT:$AT,"")))} -> #N/A | M44: 箱
B45: 35 | C45: =_xlfn.XLOOKUP(D45,商品汇总表!$B:$B,商品汇总表!$A:$A,"") -> #N/A | D45: {=LOOKUP(1,0/(('5.21出货明细'!AR:AR=$D$52)*('5.21出货明细'!A:A=B45)),'5.21出货明细'!E:E)} -> #N/A | E45: =_xlfn.XLOOKUP(D45,商品汇总表!$B:$B,商品汇总表!$D:$D,"") -> #N/A | F45: {=_xlfn.LET(_xlpm.数组,B45&D45,_xlpm.源数组,'5.21出货明细'!$A:$A&'5.21出货明细'!$E:$E,_xlpm.原单位,_xlfn.XLOOKUP(_xlpm.数组,_xlpm.源数组,'5.21出货明细'!$J:$J,""),_xlfn.HSTACK(_xlfn.XLOOKUP(_xlpm.数组,_xlpm.源数组,'5.21出货明细'!$K:$K,""),_xlfn.XLOOKUP(_xlpm.原单位,单位对照!$A:$A,单位对照!$B:$B,_xlpm.原单位),_xlfn.XLOOKUP(_xlpm.数组,_xlpm.源数组,'5.21出货明细'!$Z:$Z,""),_xlfn.XLOOKUP(_xlpm.数组,_xlpm.源数组,'5.21出货明细'!$AA:$AA,""),_xlfn.XLOOKUP(_xlpm.数组,_xlpm.源数组,'5.21出货明细'!$P:$P,""),_xlfn.XLOOKUP(_xlpm.数组,_xlpm.源数组,'5.21出货明细'!$Q:$Q,""),_xlfn.XLOOKUP(_xlpm.数组,_xlpm.源数组,'5.21出货明细'!$AT:$AT,"")))} -> #N/A | M45: 箱
B46: 36 | C46: =_xlfn.XLOOKUP(D46,商品汇总表!$B:$B,商品汇总表!$A:$A,"") -> #N/A | D46: {=LOOKUP(1,0/(('5.21出货明细'!AR:AR=$D$52)*('5.21出货明细'!A:A=B46)),'5.21出货明细'!E:E)} -> #N/A | E46: =_xlfn.XLOOKUP(D46,商品汇总表!$B:$B,商品汇总表!$D:$D,"") -> #N/A | F46: {=_xlfn.LET(_xlpm.数组,B46&D46,_xlpm.源数组,'5.21出货明细'!$A:$A&'5.21出货明细'!$E:$E,_xlpm.原单位,_xlfn.XLOOKUP(_xlpm.数组,_xlpm.源数组,'5.21出货明细'!$J:$J,""),_xlfn.HSTACK(_xlfn.XLOOKUP(_xlpm.数组,_xlpm.源数组,'5.21出货明细'!$K:$K,""),_xlfn.XLOOKUP(_xlpm.原单位,单位对照!$A:$A,单位对照!$B:$B,_xlpm.原单位),_xlfn.XLOOKUP(_xlpm.数组,_xlpm.源数组,'5.21出货明细'!$Z:$Z,""),_xlfn.XLOOKUP(_xlpm.数组,_xlpm.源数组,'5.21出货明细'!$AA:$AA,""),_xlfn.XLOOKUP(_xlpm.数组,_xlpm.源数组,'5.21出货明细'!$P:$P,""),_xlfn.XLOOKUP(_xlpm.数组,_xlpm.源数组,'5.21出货明细'!$Q:$Q,""),_xlfn.XLOOKUP(_xlpm.数组,_xlpm.源数组,'5.21出货明细'!$AT:$AT,"")))} -> #N/A | M46: 箱
B47: 37 | C47: =_xlfn.XLOOKUP(D47,商品汇总表!$B:$B,商品汇总表!$A:$A,"") -> #N/A | D47: {=LOOKUP(1,0/(('5.21出货明细'!AR:AR=$D$52)*('5.21出货明细'!A:A=B47)),'5.21出货明细'!E:E)} -> #N/A | E47: =_xlfn.XLOOKUP(D47,商品汇总表!$B:$B,商品汇总表!$D:$D,"") -> #N/A | F47: {=_xlfn.LET(_xlpm.数组,B47&D47,_xlpm.源数组,'5.21出货明细'!$A:$A&'5.21出货明细'!$E:$E,_xlpm.原单位,_xlfn.XLOOKUP(_xlpm.数组,_xlpm.源数组,'5.21出货明细'!$J:$J,""),_xlfn.HSTACK(_xlfn.XLOOKUP(_xlpm.数组,_xlpm.源数组,'5.21出货明细'!$K:$K,""),_xlfn.XLOOKUP(_xlpm.原单位,单位对照!$A:$A,单位对照!$B:$B,_xlpm.原单位),_xlfn.XLOOKUP(_xlpm.数组,_xlpm.源数组,'5.21出货明细'!$Z:$Z,""),_xlfn.XLOOKUP(_xlpm.数组,_xlpm.源数组,'5.21出货明细'!$AA:$AA,""),_xlfn.XLOOKUP(_xlpm.数组,_xlpm.源数组,'5.21出货明细'!$P:$P,""),_xlfn.XLOOKUP(_xlpm.数组,_xlpm.源数组,'5.21出货明细'!$Q:$Q,""),_xlfn.XLOOKUP(_xlpm.数组,_xlpm.源数组,'5.21出货明细'!$AT:$AT,"")))} -> #N/A | M47: 箱
B48: 38 | C48: =_xlfn.XLOOKUP(D48,商品汇总表!$B:$B,商品汇总表!$A:$A,"") -> #N/A | D48: {=LOOKUP(1,0/(('5.21出货明细'!AR:AR=$D$52)*('5.21出货明细'!A:A=B48)),'5.21出货明细'!E:E)} -> #N/A | E48: =_xlfn.XLOOKUP(D48,商品汇总表!$B:$B,商品汇总表!$D:$D,"") -> #N/A | F48: {=_xlfn.LET(_xlpm.数组,B48&D48,_xlpm.源数组,'5.21出货明细'!$A:$A&'5.21出货明细'!$E:$E,_xlpm.原单位,_xlfn.XLOOKUP(_xlpm.数组,_xlpm.源数组,'5.21出货明细'!$J:$J,""),_xlfn.HSTACK(_xlfn.XLOOKUP(_xlpm.数组,_xlpm.源数组,'5.21出货明细'!$K:$K,""),_xlfn.XLOOKUP(_xlpm.原单位,单位对照!$A:$A,单位对照!$B:$B,_xlpm.原单位),_xlfn.XLOOKUP(_xlpm.数组,_xlpm.源数组,'5.21出货明细'!$Z:$Z,""),_xlfn.XLOOKUP(_xlpm.数组,_xlpm.源数组,'5.21出货明细'!$AA:$AA,""),_xlfn.XLOOKUP(_xlpm.数组,_xlpm.源数组,'5.21出货明细'!$P:$P,""),_xlfn.XLOOKUP(_xlpm.数组,_xlpm.源数组,'5.21出货明细'!$Q:$Q,""),_xlfn.XLOOKUP(_xlpm.数组,_xlpm.源数组,'5.21出货明细'!$AT:$AT,"")))} -> #N/A | M48: 箱
B49: 39 | C49: =_xlfn.XLOOKUP(D49,商品汇总表!$B:$B,商品汇总表!$A:$A,"") -> #N/A | D49: {=LOOKUP(1,0/(('5.21出货明细'!AR:AR=$D$52)*('5.21出货明细'!A:A=B49)),'5.21出货明细'!E:E)} -> #N/A | E49: =_xlfn.XLOOKUP(D49,商品汇总表!$B:$B,商品汇总表!$D:$D,"") -> #N/A | F49: {=_xlfn.LET(_xlpm.数组,B49&D49,_xlpm.源数组,'5.21出货明细'!$A:$A&'5.21出货明细'!$E:$E,_xlpm.原单位,_xlfn.XLOOKUP(_xlpm.数组,_xlpm.源数组,'5.21出货明细'!$J:$J,""),_xlfn.HSTACK(_xlfn.XLOOKUP(_xlpm.数组,_xlpm.源数组,'5.21出货明细'!$K:$K,""),_xlfn.XLOOKUP(_xlpm.原单位,单位对照!$A:$A,单位对照!$B:$B,_xlpm.原单位),_xlfn.XLOOKUP(_xlpm.数组,_xlpm.源数组,'5.21出货明细'!$Z:$Z,""),_xlfn.XLOOKUP(_xlpm.数组,_xlpm.源数组,'5.21出货明细'!$AA:$AA,""),_xlfn.XLOOKUP(_xlpm.数组,_xlpm.源数组,'5.21出货明细'!$P:$P,""),_xlfn.XLOOKUP(_xlpm.数组,_xlpm.源数组,'5.21出货明细'!$Q:$Q,""),_xlfn.XLOOKUP(_xlpm.数组,_xlpm.源数组,'5.21出货明细'!$AT:$AT,"")))} -> #N/A | M49: 箱
B50: 40 | C50: =_xlfn.XLOOKUP(D50,商品汇总表!$B:$B,商品汇总表!$A:$A,"") -> #N/A | D50: {=LOOKUP(1,0/(('5.21出货明细'!AR:AR=$D$52)*('5.21出货明细'!A:A=B50)),'5.21出货明细'!E:E)} -> #N/A | E50: =_xlfn.XLOOKUP(D50,商品汇总表!$B:$B,商品汇总表!$D:$D,"") -> #N/A | F50: {=_xlfn.LET(_xlpm.数组,B50&D50,_xlpm.源数组,'5.21出货明细'!$A:$A&'5.21出货明细'!$E:$E,_xlpm.原单位,_xlfn.XLOOKUP(_xlpm.数组,_xlpm.源数组,'5.21出货明细'!$J:$J,""),_xlfn.HSTACK(_xlfn.XLOOKUP(_xlpm.数组,_xlpm.源数组,'5.21出货明细'!$K:$K,""),_xlfn.XLOOKUP(_xlpm.原单位,单位对照!$A:$A,单位对照!$B:$B,_xlpm.原单位),_xlfn.XLOOKUP(_xlpm.数组,_xlpm.源数组,'5.21出货明细'!$Z:$Z,""),_xlfn.XLOOKUP(_xlpm.数组,_xlpm.源数组,'5.21出货明细'!$AA:$AA,""),_xlfn.XLOOKUP(_xlpm.数组,_xlpm.源数组,'5.21出货明细'!$P:$P,""),_xlfn.XLOOKUP(_xlpm.数组,_xlpm.源数组,'5.21出货明细'!$Q:$Q,""),_xlfn.XLOOKUP(_xlpm.数组,_xlpm.源数组,'5.21出货明细'!$AT:$AT,"")))} -> #N/A | M50: 箱
B51: 41 | C51: =_xlfn.XLOOKUP(D51,商品汇总表!$B:$B,商品汇总表!$A:$A,"") -> #N/A | D51: {=LOOKUP(1,0/(('5.21出货明细'!AR:AR=$D$52)*('5.21出货明细'!A:A=B51)),'5.21出货明细'!E:E)} -> #N/A | E51: =_xlfn.XLOOKUP(D51,商品汇总表!$B:$B,商品汇总表!$D:$D,"") -> #N/A | F51: {=_xlfn.LET(_xlpm.数组,B51&D51,_xlpm.源数组,'5.21出货明细'!$A:$A&'5.21出货明细'!$E:$E,_xlpm.原单位,_xlfn.XLOOKUP(_xlpm.数组,_xlpm.源数组,'5.21出货明细'!$J:$J,""),_xlfn.HSTACK(_xlfn.XLOOKUP(_xlpm.数组,_xlpm.源数组,'5.21出货明细'!$K:$K,""),_xlfn.XLOOKUP(_xlpm.原单位,单位对照!$A:$A,单位对照!$B:$B,_xlpm.原单位),_xlfn.XLOOKUP(_xlpm.数组,_xlpm.源数组,'5.21出货明细'!$Z:$Z,""),_xlfn.XLOOKUP(_xlpm.数组,_xlpm.源数组,'5.21出货明细'!$AA:$AA,""),_xlfn.XLOOKUP(_xlpm.数组,_xlpm.源数组,'5.21出货明细'!$P:$P,""),_xlfn.XLOOKUP(_xlpm.数组,_xlpm.源数组,'5.21出货明细'!$Q:$Q,""),_xlfn.XLOOKUP(_xlpm.数组,_xlpm.源数组,'5.21出货明细'!$AT:$AT,"")))} -> #N/A | M51: 箱
D52: 兴信一般贸易 | F52: =SUM(F41:F51) -> #N/A | I52: =SUM(I40:I51) -> 0 | J52: =SUM(J40:J51) -> 0 | K52: =SUM(K40:K51) -> 0 | L52: =SUM(L40:L51) -> 0
B53: 42 | C53: =_xlfn.XLOOKUP(D53,商品汇总表!$B:$B,商品汇总表!$A:$A,"") | D53: {=_xlfn.UNIQUE(_xlfn._xlws.FILTER('5.21出货明细'!E:E,'5.21出货明细'!AR:AR=D56,""))} | E53: =_xlfn.XLOOKUP(D53,商品汇总表!$B:$B,商品汇总表!$D:$D,"") | F53: =SUMIFS('5.21出货明细'!$K:$K,'5.21出货明细'!$E:$E,$D53,'5.21出货明细'!$AR:$AR,$D$56) -> 0 | G53: =_xlfn.XLOOKUP(_xlfn.XLOOKUP($D53,'5.21出货明细'!$E:$E,'5.21出货明细'!$J:$J,""),单位对照!$A:$A,单位对照!$B:$B,"未匹配") -> 未匹配 | H53: =I53/F53 -> #DIV/0! | I53: =SUMIFS('5.21出货明细'!$AA:$AA,'5.21出货明细'!$E:$E,$D53,'5.21出货明细'!$AR:$AR,$D$56) -> 0 | J53: =SUMIFS('5.21出货明细'!$P:$P,'5.21出货明细'!$E:$E,$D53,'5.21出货明细'!$AR:$AR,$D$56) -> 0 | K53: =SUMIFS('5.21出货明细'!$Q:$Q,'5.21出货明细'!$E:$E,$D53,'5.21出货明细'!$AR:$AR,$D$56) -> 0 | L53: =SUMIFS('5.21出货明细'!$AT:$AT,'5.21出货明细'!$E:$E,$D53,'5.21出货明细'!$AR:$AR,$D$56) -> 0 | M53: 箱
B54: 43 | C54: =_xlfn.XLOOKUP(D54,商品汇总表!$B:$B,商品汇总表!$A:$A,"") -> 0 | E54: =_xlfn.XLOOKUP(D54,商品汇总表!$B:$B,商品汇总表!$D:$D,"") -> 0 | F54: =SUMIFS('5.21出货明细'!$K:$K,'5.21出货明细'!$E:$E,$D54,'5.21出货明细'!$AR:$AR,$D$56) -> 0 | G54: =_xlfn.XLOOKUP(_xlfn.XLOOKUP($D54,'5.21出货明细'!$E:$E,'5.21出货明细'!$J:$J,""),单位对照!$A:$A,单位对照!$B:$B,"未匹配") -> 0 | H54: =SUMIFS('5.21出货明细'!$AO:$AO,'5.21出货明细'!$E:$E,$D54,'5.21出货明细'!$AR:$AR,$D$56) -> 0 | I54: =SUMIFS('5.21出货明细'!$AA:$AA,'5.21出货明细'!$E:$E,$D54,'5.21出货明细'!$AR:$AR,$D$56) -> 0 | J54: =SUMIFS('5.21出货明细'!$P:$P,'5.21出货明细'!$E:$E,$D54,'5.21出货明细'!$AR:$AR,$D$56) -> 0 | K54: =SUMIFS('5.21出货明细'!$Q:$Q,'5.21出货明细'!$E:$E,$D54,'5.21出货明细'!$AR:$AR,$D$56) -> 0 | L54: =SUMIFS('5.21出货明细'!$AT:$AT,'5.21出货明细'!$E:$E,$D54,'5.21出货明细'!$AR:$AR,$D$56) -> 0 | M54: 箱
B55: 44 | C55: =_xlfn.XLOOKUP(D55,商品汇总表!$B:$B,商品汇总表!$A:$A,"") -> 0 | E55: =_xlfn.XLOOKUP(D55,商品汇总表!$B:$B,商品汇总表!$D:$D,"") -> 0 | F55: =SUMIFS('5.21出货明细'!$K:$K,'5.21出货明细'!$E:$E,$D55,'5.21出货明细'!$AR:$AR,$D$56) -> 0 | G55: =_xlfn.XLOOKUP(_xlfn.XLOOKUP($D55,'5.21出货明细'!$E:$E,'5.21出货明细'!$J:$J,""),单位对照!$A:$A,单位对照!$B:$B,"未匹配") -> 0 | H55: =SUMIFS('5.21出货明细'!$AO:$AO,'5.21出货明细'!$E:$E,$D55,'5.21出货明细'!$AR:$AR,$D$56) -> 0 | I55: =SUMIFS('5.21出货明细'!$AA:$AA,'5.21出货明细'!$E:$E,$D55,'5.21出货明细'!$AR:$AR,$D$56) -> 0 | J55: =SUMIFS('5.21出货明细'!$P:$P,'5.21出货明细'!$E:$E,$D55,'5.21出货明细'!$AR:$AR,$D$56) -> 0 | K55: =SUMIFS('5.21出货明细'!$Q:$Q,'5.21出货明细'!$E:$E,$D55,'5.21出货明细'!$AR:$AR,$D$56) -> 0 | L55: =SUMIFS('5.21出货明细'!$AT:$AT,'5.21出货明细'!$E:$E,$D55,'5.21出货明细'!$AR:$AR,$D$56) -> 0 | M55: 箱
D56: 河源市港正五金制造有限公司 | F56: =SUM(F53:F55) -> 0 | I56: =SUM(I53:I55) -> 0 | J56: =SUM(J53:J55) -> 0 | K56: =SUM(K53:K55) -> 0 | L56: =SUM(L53:L55) -> 0
B57: 75 | C57: =_xlfn.XLOOKUP(D57,商品汇总表!$B:$B,商品汇总表!$A:$A,"") -> #N/A | D57: {=LOOKUP(1,0/(('5.21出货明细'!AR:AR=$D$58)*('5.21出货明细'!A:A=B57)),'5.21出货明细'!E:E)} -> #N/A | E57: =_xlfn.XLOOKUP(D57,商品汇总表!$B:$B,商品汇总表!$D:$D,"") -> #N/A | F57: {=_xlfn.LET(_xlpm.数组,B57&D57,_xlpm.源数组,'5.21出货明细'!$A:$A&'5.21出货明细'!$E:$E,_xlpm.原单位,_xlfn.XLOOKUP(_xlpm.数组,_xlpm.源数组,'5.21出货明细'!$J:$J,""),_xlfn.HSTACK(_xlfn.XLOOKUP(_xlpm.数组,_xlpm.源数组,'5.21出货明细'!$K:$K,""),_xlfn.XLOOKUP(_xlpm.原单位,单位对照!$A:$A,单位对照!$B:$B,_xlpm.原单位),_xlfn.XLOOKUP(_xlpm.数组,_xlpm.源数组,'5.21出货明细'!$Z:$Z,""),_xlfn.XLOOKUP(_xlpm.数组,_xlpm.源数组,'5.21出货明细'!$AA:$AA,""),_xlfn.XLOOKUP(_xlpm.数组,_xlpm.源数组,'5.21出货明细'!$P:$P,""),_xlfn.XLOOKUP(_xlpm.数组,_xlpm.源数组,'5.21出货明细'!$Q:$Q,""),_xlfn.XLOOKUP(_xlpm.数组,_xlpm.源数组,'5.21出货明细'!$AT:$AT,"")))} -> #N/A | M57: 箱
D58: 深圳市科创德科技有限公司 | F58: =SUM(F57:F57) -> #N/A | I58: =SUM(I57:I57) -> 0 | J58: =SUM(J57:J57) -> 0 | K58: =SUM(K57:K57) -> 0 | L58: =SUM(L57:L57) -> 0
E59: 总合计 | I59: =I58+I56++I52+I39+I27 -> 0 | J59: =J58+J56++J52+J39+J27 -> 0 | K59: =K58+K56++K52+K39+K27 -> 0 | L59: =L58+L56++L52+L39+L27 -> 0
F61: Authorized Signature(s):

Sheet 销售合同
A1: 销 售 合 同
A2: SALES CONTRACT
A4: 卖 方: | B4: 深圳市华胜益出口贸易有限公司 | G4: 合同编号 S/C No : | I4: =发票!D5 -> 0
A5: Seller :
B6: 广东省深圳市龙华区大浪街道龙胜社区龙胜综合服务大楼602 | G6: 签订日期 DATE : | I6: =发票!H5 -> 45619
A8: 买 方: | B8: PT ROYAL REGENT INDONESIA
A9: Buyer :
A11: 兹经买卖双方同意所列条款达成以下交易：
A12: This contract is made by and between the BUYER and SELLER, in accordance with the terms and conditions stipulated below:
A14: 1. 序号 | B14: 2. 商品编号 | C14: 3. 品名及规格/型号 | E14: 4. 数量 | F14: 5.单位 | G14: 6. 单价及价格条款 | I14: 7. 金额
A15: Art No. | B15: Art No. | C15: Commodity & Specification | E15: QTY | F15: Unit | G15: Unit Price / Trade Terms | I15: Amount
A16: 1 | B16: {=_xlfn.HSTACK(_xlfn.XLOOKUP($A16,发票!$B:$B,发票!$C:$C),_xlfn.XLOOKUP($A16,发票!$B:$B,发票!$D:$D),_xlfn.XLOOKUP($A16,发票!$B:$B,发票!$E:$E),_xlfn.XLOOKUP($A16,发票!$B:$B,发票!$F:$F),_xlfn.XLOOKUP($A16,发票!$B:$B,发票!$G:$G))} -> #N/A | C16: #N/A | D16: #N/A | E16: #N/A | F16: 0 | G16: FOB DONG GUAN | I16: =_xlfn.XLOOKUP($A16,发票!$B:$B,发票!I:I,"") -> 0
A17: 2 | B17: {=_xlfn.HSTACK(_xlfn.XLOOKUP($A17,发票!$B:$B,发票!$C:$C),_xlfn.XLOOKUP($A17,发票!$B:$B,发票!$D:$D),_xlfn.XLOOKUP($A17,发票!$B:$B,发票!$E:$E),_xlfn.XLOOKUP($A17,发票!$B:$B,发票!$F:$F),_xlfn.XLOOKUP($A17,发票!$B:$B,发票!$G:$G))} -> #N/A | C17: #N/A | D17: #N/A | E17: #N/A | F17: 0 | G17: FOB DONG GUAN | I17: =_xlfn.XLOOKUP($A17,发票!$B:$B,发票!I:I,"") -> 0
A18: 3 | B18: {=_xlfn.HSTACK(_xlfn.XLOOKUP($A18,发票!$B:$B,发票!$C:$C),_xlfn.XLOOKUP($A18,发票!$B:$B,发票!$D:$D),_xlfn.XLOOKUP($A18,发票!$B:$B,发票!$E:$E),_xlfn.XLOOKUP($A18,发票!$B:$B,发票!$F:$F),_xlfn.XLOOKUP($A18,发票!$B:$B,发票!$G:$G))} -> #N/A | C18: #N/A | D18: #N/A | E18: #N/A | F18: 0 | G18: FOB DONG GUAN | I18: =_xlfn.XLOOKUP($A18,发票!$B:$B,发票!I:I,"") -> 0
A19: 4 | B19: {=_xlfn.HSTACK(_xlfn.XLOOKUP($A19,发票!$B:$B,发票!$C:$C),_xlfn.XLOOKUP($A19,发票!$B:$B,发票!$D:$D),_xlfn.XLOOKUP($A19,发票!$B:$B,发票!$E:$E),_xlfn.XLOOKUP($A19,发票!$B:$B,发票!$F:$F),_xlfn.XLOOKUP($A19,发票!$B:$B,发票!$G:$G))} -> #N/A | C19: #N/A | D19: #N/A | E19: #N/A | F19: 0 | G19: FOB DONG GUAN | I19: =_xlfn.XLOOKUP($A19,发票!$B:$B,发票!I:I,"") -> 0
A20: 5 | B20: {=_xlfn.HSTACK(_xlfn.XLOOKUP($A20,发票!$B:$B,发票!$C:$C),_xlfn.XLOOKUP($A20,发票!$B:$B,发票!$D:$D),_xlfn.XLOOKUP($A20,发票!$B:$B,发票!$E:$E),_xlfn.XLOOKUP($A20,发票!$B:$B,发票!$F:$F),_xlfn.XLOOKUP($A20,发票!$B:$B,发票!$G:$G))} -> #N/A | C20: #N/A | D20: #N/A | E20: #N/A | F20: 0 | G20: FOB DONG GUAN | I20: =_xlfn.XLOOKUP($A20,发票!$B:$B,发票!I:I,"") -> 0
A21: 6 | B21: {=_xlfn.HSTACK(_xlfn.XLOOKUP($A21,发票!$B:$B,发票!$C:$C),_xlfn.XLOOKUP($A21,发票!$B:$B,发票!$D:$D),_xlfn.XLOOKUP($A21,发票!$B:$B,发票!$E:$E),_xlfn.XLOOKUP($A21,发票!$B:$B,发票!$F:$F),_xlfn.XLOOKUP($A21,发票!$B:$B,发票!$G:$G))} -> #N/A | C21: #N/A | D21: #N/A | E21: #N/A | F21: 0 | G21: FOB DONG GUAN | I21: =_xlfn.XLOOKUP($A21,发票!$B:$B,发票!I:I,"") -> 0
A22: 7 | B22: {=_xlfn.HSTACK(_xlfn.XLOOKUP($A22,发票!$B:$B,发票!$C:$C),_xlfn.XLOOKUP($A22,发票!$B:$B,发票!$D:$D),_xlfn.XLOOKUP($A22,发票!$B:$B,发票!$E:$E),_xlfn.XLOOKUP($A22,发票!$B:$B,发票!$F:$F),_xlfn.XLOOKUP($A22,发票!$B:$B,发票!$G:$G))} -> #N/A | C22: #N/A | D22: #N/A | E22: #N/A | F22: 0 | G22: FOB DONG GUAN | I22: =_xlfn.XLOOKUP($A22,发票!$B:$B,发票!I:I,"") -> 0
A23: 8 | B23: {=_xlfn.HSTACK(_xlfn.XLOOKUP($A23,发票!$B:$B,发票!$C:$C),_xlfn.XLOOKUP($A23,发票!$B:$B,发票!$D:$D),_xlfn.XLOOKUP($A23,发票!$B:$B,发票!$E:$E),_xlfn.XLOOKUP($A23,发票!$B:$B,发票!$F:$F),_xlfn.XLOOKUP($A23,发票!$B:$B,发票!$G:$G))} -> #N/A | C23: #N/A | D23: #N/A | E23: #N/A | F23: 0 | G23: FOB DONG GUAN | I23: =_xlfn.XLOOKUP($A23,发票!$B:$B,发票!I:I,"") -> 0
A24: 9 | B24: {=_xlfn.HSTACK(_xlfn.XLOOKUP($A24,发票!$B:$B,发票!$C:$C),_xlfn.XLOOKUP($A24,发票!$B:$B,发票!$D:$D),_xlfn.XLOOKUP($A24,发票!$B:$B,发票!$E:$E),_xlfn.XLOOKUP($A24,发票!$B:$B,发票!$F:$F),_xlfn.XLOOKUP($A24,发票!$B:$B,发票!$G:$G))} -> #N/A | C24: #N/A | D24: #N/A | E24: #N/A | F24: 0 | G24: FOB DONG GUAN | I24: =_xlfn.XLOOKUP($A24,发票!$B:$B,发票!I:I,"") -> 0
A25: 10 | B25: {=_xlfn.HSTACK(_xlfn.XLOOKUP($A25,发票!$B:$B,发票!$C:$C),_xlfn.XLOOKUP($A25,发票!$B:$B,发票!$D:$D),_xlfn.XLOOKUP($A25,发票!$B:$B,发票!$E:$E),_xlfn.XLOOKUP($A25,发票!$B:$B,发票!$F:$F),_xlfn.XLOOKUP($A25,发票!$B:$B,发票!$G:$G))} -> #N/A | C25: #N/A | D25: #N/A | E25: #N/A | F25: 0 | G25: FOB DONG GUAN | I25: =_xlfn.XLOOKUP($A25,发票!$B:$B,发票!I:I,"") -> 0
A26: 11 | B26: {=_xlfn.HSTACK(_xlfn.XLOOKUP($A26,发票!$B:$B,发票!$C:$C),_xlfn.XLOOKUP($A26,发票!$B:$B,发票!$D:$D),_xlfn.XLOOKUP($A26,发票!$B:$B,发票!$E:$E),_xlfn.XLOOKUP($A26,发票!$B:$B,发票!$F:$F),_xlfn.XLOOKUP($A26,发票!$B:$B,发票!$G:$G))} -> #N/A | C26: #N/A | D26: #N/A | E26: #N/A | F26: 0 | G26: FOB DONG GUAN | I26: =_xlfn.XLOOKUP($A26,发票!$B:$B,发票!I:I,"") -> 0
A27: 12 | B27: {=_xlfn.HSTACK(_xlfn.XLOOKUP($A27,发票!$B:$B,发票!$C:$C),_xlfn.XLOOKUP($A27,发票!$B:$B,发票!$D:$D),_xlfn.XLOOKUP($A27,发票!$B:$B,发票!$E:$E),_xlfn.XLOOKUP($A27,发票!$B:$B,发票!$F:$F),_xlfn.XLOOKUP($A27,发票!$B:$B,发票!$G:$G))} -> #N/A | C27: #N/A | D27: #N/A | E27: #N/A | F27: 0 | G27: FOB DONG GUAN | I27: =_xlfn.XLOOKUP($A27,发票!$B:$B,发票!I:I,"") -> 0
E52: =发票!#REF! -> #REF! | F52: =发票!#REF! -> #REF! | G52: FOB DONG GUAN | I52: =发票!#REF! -> #REF!
E53: =SUM(E16:E52) -> #N/A | G53: Total Value | I53: =发票!#REF! -> #REF!
A54: 7. 包装
A55: 8. 装运期及运输方式 | E55: via Truck
A56: 9 装运港及目的地
A57: 10. 付款方式 | D57: T/C pay, 60 days after invoice date.
A58: 11. 备注 | C58: 未尽事宜，经双方协商解决。
A59: Remarks
A60: E.&.O.E
A61: The Buyer | E61: The Seller
A62: 精駿企業有限公司 | E62: ZHONG SHAN JUN TAI IMPORT&EXPORT TRADING Co., LTD.
A64: Authorized Signature(s) | E64: Authorized Signature(s)

Sheet 装箱单 (2)
A1: 装 箱 单
A2: PACKING LIST
G3: 日 期:
A4: 客 户 | G4: 发票编号: | H4: =发票!D5 -> 0
A5: To Messrers：PT ROYAL REGENT INDONESIA
A6: 船 名 | C6: 至 | F6: 付 款 条 件
A7: Shipped by：________________ From | C7: to | F7: Terms of Payment:__FOB_______
A8: 项号 | B8: 货物名称及规格 | C8: 总箱数 | E8: 总数量 | G8: 总毛重 | H8: 总净重
A9: Ctn.No. | B9: Description | C9: Ge.Crate | E9: Ge.Quantity | G9: G.W.(KG) | H9: N.W.(KG)
A10: 1 | B10: {=_xlfn.HSTACK(_xlfn.XLOOKUP($A10,发票!$B:$B,发票!$D:$D),_xlfn.XLOOKUP($A10,发票!$B:$B,发票!$L:$L),_xlfn.XLOOKUP($A10,发票!$B:$B,发票!$M:$M),_xlfn.XLOOKUP($A10,发票!$B:$B,发票!$F:$F),_xlfn.XLOOKUP($A10,发票!$B:$B,发票!$G:$G),_xlfn.XLOOKUP($A10,发票!$B:$B,发票!$J:$J),_xlfn.XLOOKUP($A10,发票!$B:$B,发票!$K:$K))} -> #N/A | C10: 0 | D10: 箱 | E10: #N/A | F10: 0 | G10: 0 | H10: 0 | J10: Crate
A11: 2 | B11: {=_xlfn.HSTACK(_xlfn.XLOOKUP($A11,发票!$B:$B,发票!$D:$D),_xlfn.XLOOKUP($A11,发票!$B:$B,发票!$L:$L),_xlfn.XLOOKUP($A11,发票!$B:$B,发票!$M:$M),_xlfn.XLOOKUP($A11,发票!$B:$B,发票!$F:$F),_xlfn.XLOOKUP($A11,发票!$B:$B,发票!$G:$G),_xlfn.XLOOKUP($A11,发票!$B:$B,发票!$J:$J),_xlfn.XLOOKUP($A11,发票!$B:$B,发票!$K:$K))} -> #N/A | C11: 0 | D11: 箱 | E11: #N/A | F11: 0 | G11: 0 | H11: 0
A12: 3 | B12: {=_xlfn.HSTACK(_xlfn.XLOOKUP($A12,发票!$B:$B,发票!$D:$D),_xlfn.XLOOKUP($A12,发票!$B:$B,发票!$L:$L),_xlfn.XLOOKUP($A12,发票!$B:$B,发票!$M:$M),_xlfn.XLOOKUP($A12,发票!$B:$B,发票!$F:$F),_xlfn.XLOOKUP($A12,发票!$B:$B,发票!$G:$G),_xlfn.XLOOKUP($A12,发票!$B:$B,发票!$J:$J),_xlfn.XLOOKUP($A12,发票!$B:$B,发票!$K:$K))} -> #N/A | C12: 0 | D12: 箱 | E12: #N/A | F12: 0 | G12: 0 | H12: 0
A13: 4 | B13: {=_xlfn.HSTACK(_xlfn.XLOOKUP($A13,发票!$B:$B,发票!$D:$D),_xlfn.XLOOKUP($A13,发票!$B:$B,发票!$L:$L),_xlfn.XLOOKUP($A13,发票!$B:$B,发票!$M:$M),_xlfn.XLOOKUP($A13,发票!$B:$B,发票!$F:$F),_xlfn.XLOOKUP($A13,发票!$B:$B,发票!$G:$G),_xlfn.XLOOKUP($A13,发票!$B:$B,发票!$J:$J),_xlfn.XLOOKUP($A13,发票!$B:$B,发票!$K:$K))} -> #N/A | C13: 0 | D13: 箱 | E13: #N/A | F13: 0 | G13: 0 | H13: 0
A14: 5 | B14: {=_xlfn.HSTACK(_xlfn.XLOOKUP($A14,发票!$B:$B,发票!$D:$D),_xlfn.XLOOKUP($A14,发票!$B:$B,发票!$L:$L),_xlfn.XLOOKUP($A14,发票!$B:$B,发票!$M:$M),_xlfn.XLOOKUP($A14,发票!$B:$B,发票!$F:$F),_xlfn.XLOOKUP($A14,发票!$B:$B,发票!$G:$G),_xlfn.XLOOKUP($A14,发票!$B:$B,发票!$J:$J),_xlfn.XLOOKUP($A14,发票!$B:$B,发票!$K:$K))} -> #N/A | C14: 0 | D14: 箱 | E14: #N/A | F14: 0 | G14: 0 | H14: 0
A15: 6 | B15: {=_xlfn.HSTACK(_xlfn.XLOOKUP($A15,发票!$B:$B,发票!$D:$D),_xlfn.XLOOKUP($A15,发票!$B:$B,发票!$L:$L),_xlfn.XLOOKUP($A15,发票!$B:$B,发票!$M:$M),_xlfn.XLOOKUP($A15,发票!$B:$B,发票!$F:$F),_xlfn.XLOOKUP($A15,发票!$B:$B,发票!$G:$G),_xlfn.XLOOKUP($A15,发票!$B:$B,发票!$J:$J),_xlfn.XLOOKUP($A15,发票!$B:$B,发票!$K:$K))} -> #N/A | C15: 0 | D15: 箱 | E15: #N/A | F15: 0 | G15: 0 | H15: 0
A16: 7 | B16: {=_xlfn.HSTACK(_xlfn.XLOOKUP($A16,发票!$B:$B,发票!$D:$D),_xlfn.XLOOKUP($A16,发票!$B:$B,发票!$L:$L),_xlfn.XLOOKUP($A16,发票!$B:$B,发票!$M:$M),_xlfn.XLOOKUP($A16,发票!$B:$B,发票!$F:$F),_xlfn.XLOOKUP($A16,发票!$B:$B,发票!$G:$G),_xlfn.XLOOKUP($A16,发票!$B:$B,发票!$J:$J),_xlfn.XLOOKUP($A16,发票!$B:$B,发票!$K:$K))} -> #N/A | C16: 0 | D16: 箱 | E16: #N/A | F16: 0 | G16: 0 | H16: 0
A47: 合计 | C47: =SUM(C10:C46) -> 0 | E47: =SUM(E10:E46) -> #N/A | G47: =SUM(G10:G46) -> 0 | H47: =SUM(H10:H46) -> 0
A48: Total

Sheet 草稿大单-1
A1: 中华人民共和国海关出口货物报关单
E2: 商检号： | K2: 海关编号
A3: 出口口岸 | F3: 备案号 | J3: 出口日期 | M3: 申报日期
A4: 蛇口海关 | J4: =TODAY() -> 46317 | M4: =TODAY() -> 46317
A5: 经营单位 | D5: (91440300MAD2R7KL8L) | F5: 运输方式 | H5: 运输工具名称 | L5: 提运单号
A6: 深圳市华胜益出口贸易有限公司 | M6: =司机资料!B8 -> 粤BFS571
A7: 发货单位 | D7: (91440300MAD2R7KL8L) | F7: 贸易方式 | J7: 征免性质 | M7: 结汇方式
A8: 深圳市华胜益出口贸易有限公司 | F8: 一般贸易 | J8: 一般征税 | M8: 先出后结
A9: 许可证号 | E9: 运抵国 | H9: 指运港 | M9: 境内货源地
E10: 印度尼西亚 | H10: 印度尼西亚 | M10: 深圳其他
A11: 批准文号 | E11: 成交方式 | F11: 运费 | M11: 杂费
E12: FOB
A13: 合同协议号 | E13: 件数 | G13: 包装种类 | I13: 毛重 | M13: 净重
A14: =发票!D5 -> 0 | E14: =SUM('装箱单 (2)'!C47) -> 0 | G14: 袋/箱 | I14: =SUM('装箱单 (2)'!G47) -> 0 | M14: =SUM('装箱单 (2)'!H47) -> 0
A15: 集装箱号 | E15: 随附单据 | K15: 生产厂家
A16: =司机资料!B2 -> MAGU2543655
A17: 标记唛码及备注 | D17: =司机资料!B5 -> 20GP
E18: 100%国料【申请退税】包装:袋/箱
A20: 项号 | B20: 商品编码 | D20: 商品名称、规格型号 | G20: 数量及单位 | I20: 原产国 | J20: 最终目的国 | L20: 单价 | N20: 总价 | O20: 币制 | P20: 征免 | Q20: 总净重
A21: 1 | B21: =_xlfn.XLOOKUP($A21,发票!$B:$B,发票!$C:$C,"") -> #N/A | D21: =_xlfn.XLOOKUP($A21,发票!$B:$B,发票!$D:$D,"") -> #N/A | E21: =_xlfn.XLOOKUP($A21,发票!$B:$B,发票!$E:$E,"") -> #N/A | G21: =_xlfn.XLOOKUP($A21,发票!$B:$B,发票!$F:$F,"") -> #N/A | H21: =_xlfn.XLOOKUP($A21,发票!$B:$B,发票!$G:$G,"") -> 0 | I21: 中国 | J21: 印度尼西亚 | L21: =_xlfn.XLOOKUP($A21,发票!$B:$B,发票!$H:$H,"") -> 0 | N21: =_xlfn.XLOOKUP($A21,发票!$B:$B,发票!I:I,"") -> 0 | O21: USD | P21: 照章征税 | Q21: =_xlfn.XLOOKUP($A21,发票!$B:$B,发票!K:K,"") -> 0
A22: 2 | B22: =_xlfn.XLOOKUP($A22,发票!$B:$B,发票!$C:$C,"") -> #N/A | D22: =_xlfn.XLOOKUP($A22,发票!$B:$B,发票!$D:$D,"") -> #N/A | E22: =_xlfn.XLOOKUP($A22,发票!$B:$B,发票!$E:$E,"") -> #N/A | G22: =_xlfn.XLOOKUP($A22,发票!$B:$B,发票!$F:$F,"") -> #N/A | H22: =_xlfn.XLOOKUP($A22,发票!$B:$B,发票!$G:$G,"") -> 0 | I22: 中国 | J22: 印度尼西亚 | L22: =_xlfn.XLOOKUP($A22,发票!$B:$B,发票!$H:$H,"") -> 0 | N22: =_xlfn.XLOOKUP($A22,发票!$B:$B,发票!I:I,"") -> 0 | O22: USD | P22: 照章征税 | Q22: =_xlfn.XLOOKUP($A22,发票!$B:$B,发票!K:K,"") -> 0
A23: 3 | B23: =_xlfn.XLOOKUP($A23,发票!$B:$B,发票!$C:$C,"") -> #N/A | D23: =_xlfn.XLOOKUP($A23,发票!$B:$B,发票!$D:$D,"") -> #N/A | E23: =_xlfn.XLOOKUP($A23,发票!$B:$B,发票!$E:$E,"") -> #N/A | G23: =_xlfn.XLOOKUP($A23,发票!$B:$B,发票!$F:$F,"") -> #N/A | H23: =_xlfn.XLOOKUP($A23,发票!$B:$B,发票!$G:$G,"") -> 0 | I23: 中国 | J23: 印度尼西亚 | L23: =_xlfn.XLOOKUP($A23,发票!$B:$B,发票!$H:$H,"") -> 0 | N23: =_xlfn.XLOOKUP($A23,发票!$B:$B,发票!I:I,"") -> 0 | O23: USD | P23: 照章征税 | Q23: =_xlfn.XLOOKUP($A23,发票!$B:$B,发票!K:K,"") -> 0
A24: 4 | B24: =_xlfn.XLOOKUP($A24,发票!$B:$B,发票!$C:$C,"") -> #N/A | D24: =_xlfn.XLOOKUP($A24,发票!$B:$B,发票!$D:$D,"") -> #N/A | E24: =_xlfn.XLOOKUP($A24,发票!$B:$B,发票!$E:$E,"") -> #N/A | G24: =_xlfn.XLOOKUP($A24,发票!$B:$B,发票!$F:$F,"") -> #N/A | H24: =_xlfn.XLOOKUP($A24,发票!$B:$B,发票!$G:$G,"") -> 0 | I24: 中国 | J24: 印度尼西亚 | L24: =_xlfn.XLOOKUP($A24,发票!$B:$B,发票!$H:$H,"") -> 0 | N24: =_xlfn.XLOOKUP($A24,发票!$B:$B,发票!I:I,"") -> 0 | O24: USD | P24: 照章征税 | Q24: =_xlfn.XLOOKUP($A24,发票!$B:$B,发票!K:K,"") -> 0
A25: 5 | B25: =_xlfn.XLOOKUP($A25,发票!$B:$B,发票!$C:$C,"") -> #N/A | D25: =_xlfn.XLOOKUP($A25,发票!$B:$B,发票!$D:$D,"") -> #N/A | E25: =_xlfn.XLOOKUP($A25,发票!$B:$B,发票!$E:$E,"") -> #N/A | G25: =_xlfn.XLOOKUP($A25,发票!$B:$B,发票!$F:$F,"") -> #N/A | H25: =_xlfn.XLOOKUP($A25,发票!$B:$B,发票!$G:$G,"") -> 0 | I25: 中国 | J25: 印度尼西亚 | L25: =_xlfn.XLOOKUP($A25,发票!$B:$B,发票!$H:$H,"") -> 0 | N25: =_xlfn.XLOOKUP($A25,发票!$B:$B,发票!I:I,"") -> 0 | O25: USD | P25: 照章征税 | Q25: =_xlfn.XLOOKUP($A25,发票!$B:$B,发票!K:K,"") -> 0
A26: 6 | B26: =_xlfn.XLOOKUP($A26,发票!$B:$B,发票!$C:$C,"") -> #N/A | D26: =_xlfn.XLOOKUP($A26,发票!$B:$B,发票!$D:$D,"") -> #N/A | E26: =_xlfn.XLOOKUP($A26,发票!$B:$B,发票!$E:$E,"") -> #N/A | G26: =_xlfn.XLOOKUP($A26,发票!$B:$B,发票!$F:$F,"") -> #N/A | H26: =_xlfn.XLOOKUP($A26,发票!$B:$B,发票!$G:$G,"") -> 0 | I26: 中国 | J26: 印度尼西亚 | L26: =_xlfn.XLOOKUP($A26,发票!$B:$B,发票!$H:$H,"") -> 0 | N26: =_xlfn.XLOOKUP($A26,发票!$B:$B,发票!I:I,"") -> 0 | O26: USD | P26: 照章征税 | Q26: =_xlfn.XLOOKUP($A26,发票!$B:$B,发票!K:K,"") -> 0
A27: 7 | B27: =_xlfn.XLOOKUP($A27,发票!$B:$B,发票!$C:$C,"") -> #N/A | D27: =_xlfn.XLOOKUP($A27,发票!$B:$B,发票!$D:$D,"") -> #N/A | E27: =_xlfn.XLOOKUP($A27,发票!$B:$B,发票!$E:$E,"") -> #N/A | G27: =_xlfn.XLOOKUP($A27,发票!$B:$B,发票!$F:$F,"") -> #N/A | H27: =_xlfn.XLOOKUP($A27,发票!$B:$B,发票!$G:$G,"") -> 0 | I27: 中国 | J27: 印度尼西亚 | L27: =_xlfn.XLOOKUP($A27,发票!$B:$B,发票!$H:$H,"") -> 0 | N27: =_xlfn.XLOOKUP($A27,发票!$B:$B,发票!I:I,"") -> 0 | O27: USD | P27: 照章征税 | Q27: =_xlfn.XLOOKUP($A27,发票!$B:$B,发票!K:K,"") -> 0
A28: 8 | B28: =_xlfn.XLOOKUP($A28,发票!$B:$B,发票!$C:$C,"") -> #N/A | D28: =_xlfn.XLOOKUP($A28,发票!$B:$B,发票!$D:$D,"") -> #N/A | E28: =_xlfn.XLOOKUP($A28,发票!$B:$B,发票!$E:$E,"") -> #N/A | G28: =_xlfn.XLOOKUP($A28,发票!$B:$B,发票!$F:$F,"") -> #N/A | H28: =_xlfn.XLOOKUP($A28,发票!$B:$B,发票!$G:$G,"") -> 0 | I28: 中国 | J28: 印度尼西亚 | L28: =_xlfn.XLOOKUP($A28,发票!$B:$B,发票!$H:$H,"") -> 0 | N28: =_xlfn.XLOOKUP($A28,发票!$B:$B,发票!I:I,"") -> 0 | O28: USD | P28: 照章征税 | Q28: =_xlfn.XLOOKUP($A28,发票!$B:$B,发票!K:K,"") -> 0
A29: 9 | B29: =_xlfn.XLOOKUP($A29,发票!$B:$B,发票!$C:$C,"") -> #N/A | D29: =_xlfn.XLOOKUP($A29,发票!$B:$B,发票!$D:$D,"") -> #N/A | E29: =_xlfn.XLOOKUP($A29,发票!$B:$B,发票!$E:$E,"") -> #N/A | G29: =_xlfn.XLOOKUP($A29,发票!$B:$B,发票!$F:$F,"") -> #N/A | H29: =_xlfn.XLOOKUP($A29,发票!$B:$B,发票!$G:$G,"") -> 0 | I29: 中国 | J29: 印度尼西亚 | L29: =_xlfn.XLOOKUP($A29,发票!$B:$B,发票!$H:$H,"") -> 0 | N29: =_xlfn.XLOOKUP($A29,发票!$B:$B,发票!I:I,"") -> 0 | O29: USD | P29: 照章征税 | Q29: =_xlfn.XLOOKUP($A29,发票!$B:$B,发票!K:K,"") -> 0
A30: 10 | B30: =_xlfn.XLOOKUP($A30,发票!$B:$B,发票!$C:$C,"") -> #N/A | D30: =_xlfn.XLOOKUP($A30,发票!$B:$B,发票!$D:$D,"") -> #N/A | E30: =_xlfn.XLOOKUP($A30,发票!$B:$B,发票!$E:$E,"") -> #N/A | G30: =_xlfn.XLOOKUP($A30,发票!$B:$B,发票!$F:$F,"") -> #N/A | H30: =_xlfn.XLOOKUP($A30,发票!$B:$B,发票!$G:$G,"") -> 0 | I30: 中国 | J30: 印度尼西亚 | L30: =_xlfn.XLOOKUP($A30,发票!$B:$B,发票!$H:$H,"") -> 0 | N30: =_xlfn.XLOOKUP($A30,发票!$B:$B,发票!I:I,"") -> 0 | O30: USD | P30: 照章征税 | Q30: =_xlfn.XLOOKUP($A30,发票!$B:$B,发票!K:K,"") -> 0
A31: 11 | B31: =_xlfn.XLOOKUP($A31,发票!$B:$B,发票!$C:$C,"") -> #N/A | D31: =_xlfn.XLOOKUP($A31,发票!$B:$B,发票!$D:$D,"") -> #N/A | E31: =_xlfn.XLOOKUP($A31,发票!$B:$B,发票!$E:$E,"") -> #N/A | G31: =_xlfn.XLOOKUP($A31,发票!$B:$B,发票!$F:$F,"") -> #N/A | H31: =_xlfn.XLOOKUP($A31,发票!$B:$B,发票!$G:$G,"") -> 0 | I31: 中国 | J31: 印度尼西亚 | L31: =_xlfn.XLOOKUP($A31,发票!$B:$B,发票!$H:$H,"") -> 0 | N31: =_xlfn.XLOOKUP($A31,发票!$B:$B,发票!I:I,"") -> 0 | O31: USD | P31: 照章征税 | Q31: =_xlfn.XLOOKUP($A31,发票!$B:$B,发票!K:K,"") -> 0
A32: 12 | B32: =_xlfn.XLOOKUP($A32,发票!$B:$B,发票!$C:$C,"") -> #N/A | D32: =_xlfn.XLOOKUP($A32,发票!$B:$B,发票!$D:$D,"") -> #N/A | E32: =_xlfn.XLOOKUP($A32,发票!$B:$B,发票!$E:$E,"") -> #N/A | G32: =_xlfn.XLOOKUP($A32,发票!$B:$B,发票!$F:$F,"") -> #N/A | H32: =_xlfn.XLOOKUP($A32,发票!$B:$B,发票!$G:$G,"") -> 0 | I32: 中国 | J32: 印度尼西亚 | L32: =_xlfn.XLOOKUP($A32,发票!$B:$B,发票!$H:$H,"") -> 0 | N32: =_xlfn.XLOOKUP($A32,发票!$B:$B,发票!I:I,"") -> 0 | O32: USD | P32: 照章征税 | Q32: =_xlfn.XLOOKUP($A32,发票!$B:$B,发票!K:K,"") -> 0
N52: =SUM(N21:N51) -> 0 | Q52: =SUM(Q21:Q51) -> 0
A53: 税费征收情况
A56: 录入员 录入单位 | F56: 兹声明以上申报无讹并承担法律责任 | K56: 海关审单批注及放行日期（盖章）
A58: 报关员 | K58: 审单 | N58: 审价
F59: 申报单位（盖章）
K60: 征税 | N60: 统计
A61: 单位地址
K62: 查验 | N62: 放行
A63: 邮编 | D63: 电话 | G63: 填制日期

Sheet 司机资料
A1: 订舱号： | B1: 237891915
A2: 柜号： | B2: MAGU2543655
A3: 封条： | B3: CN4690610
A4: 柜重： | B4: 2130
A5: 柜型： | B5: 20GP
A6: 司机： | B6: 陈志伟
A7: 电话： | B7: 15917133346
A8: 车牌： | B8: 粤BFS571

Sheet 单位对照
A1: 原单位 | B1: 填表单位
A2: KGM | B2: 千克
A3: TNE | B3: 吨
A4: GRM | B4: 克
A5: PCE | B5: 个
A6: SET | B6: 套
A7: PRS | B7: 双
A8: DZN | B8: 打
A9: BOX | B9: 箱
A10: CTN | B10: 纸箱
A11: BAG | B11: 袋
A12: PKG | B12: 件
... A18: NMB | B18: 数量

Sheet WpsReserved_CellImgList
